Workbook

Sheet Dashboard
A1: Retail & Distribution Co. Executive Dashboard
A2: Sales · Finance · HR · Supply Chain
A4: Company-Wide KPIs
A5: TOTAL REVENUE | D5: GROSS PROFIT | G5: GROSS MARGIN | J5: TOTAL ORDERS
A6: ='Sales Analysis'!C6 -> 1544129.2 | D6: ='Finance Analysis'!E6 -> 638866.24 | G6: ='Finance Analysis'!G6 -> 0.41373886 | J6: ='Sales Analysis'!A6 -> 400
A8: ACTIVE HEADCOUNT | D8: TOTAL PAYROLL | G8: SKUs NEEDING REORDER | J8: AR GAP (Uncollected)
A9: ='HR Analysis'!A6 -> 36 | D9: ='HR Analysis'!C6 -> 2921762 | G9: ='Supply Chain Analysis'!C6 -> 8 | J9: ='Finance Analysis'!G9 -> 275847.3
A12: Chart Data
A13: Month | B13: Revenue
A14: ='Sales Analysis'!A65 -> 2023-01 | B14: ='Sales Analysis'!B65 -> 35933.363
A15: ='Sales Analysis'!A66 -> 2023-02 | B15: ='Sales Analysis'!B66 -> 49557.449
A16: ='Sales Analysis'!A67 -> 2023-03 | B16: ='Sales Analysis'!B67 -> 37361.666
A17: ='Sales Analysis'!A68 -> 2023-04 | B17: ='Sales Analysis'!B68 -> 26172.149
A18: ='Sales Analysis'!A69 -> 2023-05 | B18: ='Sales Analysis'!B69 -> 45340.938
A19: ='Sales Analysis'!A70 -> 2023-06 | B19: ='Sales Analysis'!B70 -> 49946.831
A20: ='Sales Analysis'!A71 -> 2023-07 | B20: ='Sales Analysis'!B71 -> 52097.839
A21: ='Sales Analysis'!A72 -> 2023-08 | B21: ='Sales Analysis'!B72 -> 69113.531
A22: ='Sales Analysis'!A73 -> 2023-09 | B22: ='Sales Analysis'!B73 -> 36998.58
A23: ='Sales Analysis'!A74 -> 2023-10 | B23: ='Sales Analysis'!B74 -> 39838.62
A24: ='Sales Analysis'!A75 -> 2023-11 | B24: ='Sales Analysis'!B75 -> 34961.761
A25: ='Sales Analysis'!A76 -> 2023-12 | B25: ='Sales Analysis'!B76 -> 41076.233
... A49: ='Sales Analysis'!A100 -> 2025-12 | B49: ='Sales Analysis'!B100 -> 41335.026
A51: Category | B51: Revenue
A52: ='Sales Analysis'!A13 -> Sporting Goods | B52: ='Sales Analysis'!B13 -> 269240.84
A53: ='Sales Analysis'!A14 -> Apparel | B53: ='Sales Analysis'!B14 -> 206243
A54: ='Sales Analysis'!A15 -> Office Supplies | B54: ='Sales Analysis'!B15 -> 188788.64
A55: ='Sales Analysis'!A16 -> Electronics | B55: ='Sales Analysis'!B16 -> 185455.92
A56: ='Sales Analysis'!A17 -> Groceries | B56: ='Sales Analysis'!B17 -> 184134.4
A57: ='Sales Analysis'!A18 -> Health & Beauty | B57: ='Sales Analysis'!B18 -> 177044.39
A58: ='Sales Analysis'!A19 -> Automotive Parts | B58: ='Sales Analysis'!B19 -> 155430.56
A59: ='Sales Analysis'!A20 -> Furniture | B59: ='Sales Analysis'!B20 -> 144037.7
A60: ='Sales Analysis'!A21 -> Home & Kitchen | B60: ='Sales Analysis'!B21 -> 135507.78
A61: ='Sales Analysis'!A22 -> Toys & Games | B61: ='Sales Analysis'!B22 -> 109793.87
A63: Status | B63: Count
A64: Delivered | B64: =COUNTIF(Orders!$F$2:$F$401,"Delivered") -> 182
A65: Returned | B65: =COUNTIF(Orders!$F$2:$F$401,"Returned") -> 68
A66: Pending | B66: =COUNTIF(Orders!$F$2:$F$401,"Pending") -> 56
A67: Cancelled | B67: =COUNTIF(Orders!$F$2:$F$401,"Cancelled") -> 52
A68: Shipped | B68: =COUNTIF(Orders!$F$2:$F$401,"Shipped") -> 42
A70: Department | B70: Headcount
A71: =Departments!B2 -> Sales | B71: =Departments!D2 -> 0
A72: =Departments!B3 -> Marketing | B72: =Departments!D3 -> 4
A73: =Departments!B4 -> Finance | B73: =Departments!D4 -> 6
A74: =Departments!B5 -> Operations | B74: =Departments!D5 -> 4
A75: =Departments!B6 -> Human Resources | B75: =Departments!D6 -> 6
A76: =Departments!B7 -> IT | B76: =Departments!D7 -> 6
A77: =Departments!B8 -> Customer Support | B77: =Departments!D8 -> 6

Sheet Sales Analysis
A1: Sales Performance Analysis
A4: Key Performance Indicators
A5: TOTAL ORDERS | C5: REVENUE (excl. Cancelled) | E5: AVG ORDER VALUE | G5: UNITS SOLD
A6: =COUNTA(Orders!A2:A401) -> 400 | C6: =SUMIFS(Orders!H2:H401,Orders!F2:F401,"<>Cancelled") -> 1544129.2 | E6: =C6/COUNTIFS(Orders!F2:F401,"<>Cancelled") -> 4437.1528 | G6: =SUM(OrderItems!D2:D1254) -> 6902
A8: CANCELLATION RATE | C8: RETURN RATE | E8: AVG DISCOUNT GIVEN | G8: ACTIVE CUSTOMERS
A9: =COUNTIF(Orders!F2:F401,"Cancelled")/A6 -> 0.13 | C9: =COUNTIF(Orders!F2:F401,"Returned")/A6 -> 0.17 | E9: =AVERAGE(OrderItems!F2:F1254) -> 0.073264166 | G9: =COUNTIF(Customers!I2:I61,">0") -> 60
A11: Revenue by Category | F11: Revenue by Ship Region
A12: Category | B12: Revenue | C12: Units Sold | D12: Product Count | F12: Region | G12: Revenue | H12: Orders
A13: =INDEX(Categories!$B$2:$B$11,MATCH("Sporting Goods",Categories!$B$2:$B$11,0)) -> Sporting Goods | B13: =INDEX(Categories!$E$2:$E$11,MATCH($A13,Categories!$B$2:$B$11,0)) -> 269240.84 | C13: =INDEX(Categories!$D$2:$D$11,MATCH($A13,Categories!$B$2:$B$11,0)) -> 757 | D13: =INDEX(Categories!$C$2:$C$11,MATCH($A13,Categories!$B$2:$B$11,0)) -> 10 | F13: North America | G13: =SUMIFS(Orders!$H$2:$H$401,Orders!$G$2:$G$401,$F13,Orders!$F$2:$F$401,"<>Cancelled") -> 297426.94 | H13: =COUNTIFS(Orders!$G$2:$G$401,$F13) -> 75
A14: =INDEX(Categories!$B$2:$B$11,MATCH("Apparel",Categories!$B$2:$B$11,0)) -> Apparel | B14: =INDEX(Categories!$E$2:$E$11,MATCH($A14,Categories!$B$2:$B$11,0)) -> 206243 | C14: =INDEX(Categories!$D$2:$D$11,MATCH($A14,Categories!$B$2:$B$11,0)) -> 794 | D14: =INDEX(Categories!$C$2:$C$11,MATCH($A14,Categories!$B$2:$B$11,0)) -> 10 | F14: Europe | G14: =SUMIFS(Orders!$H$2:$H$401,Orders!$G$2:$G$401,$F14,Orders!$F$2:$F$401,"<>Cancelled") -> 307118.18 | H14: =COUNTIFS(Orders!$G$2:$G$401,$F14) -> 77
A15: =INDEX(Categories!$B$2:$B$11,MATCH("Office Supplies",Categories!$B$2:$B$11,0)) -> Office Supplies | B15: =INDEX(Categories!$E$2:$E$11,MATCH($A15,Categories!$B$2:$B$11,0)) -> 188788.64 | C15: =INDEX(Categories!$D$2:$D$11,MATCH($A15,Categories!$B$2:$B$11,0)) -> 666 | D15: =INDEX(Categories!$C$2:$C$11,MATCH($A15,Categories!$B$2:$B$11,0)) -> 10 | F15: Asia Pacific | G15: =SUMIFS(Orders!$H$2:$H$401,Orders!$G$2:$G$401,$F15,Orders!$F$2:$F$401,"<>Cancelled") -> 298341.04 | H15: =COUNTIFS(Orders!$G$2:$G$401,$F15) -> 79
A16: =INDEX(Categories!$B$2:$B$11,MATCH("Electronics",Categories!$B$2:$B$11,0)) -> Electronics | B16: =INDEX(Categories!$E$2:$E$11,MATCH($A16,Categories!$B$2:$B$11,0)) -> 185455.92 | C16: =INDEX(Categories!$D$2:$D$11,MATCH($A16,Categories!$B$2:$B$11,0)) -> 711 | D16: =INDEX(Categories!$C$2:$C$11,MATCH($A16,Categories!$B$2:$B$11,0)) -> 10 | F16: Middle East | G16: =SUMIFS(Orders!$H$2:$H$401,Orders!$G$2:$G$401,$F16,Orders!$F$2:$F$401,"<>Cancelled") -> 310171.62 | H16: =COUNTIFS(Orders!$G$2:$G$401,$F16) -> 88
A17: =INDEX(Categories!$B$2:$B$11,MATCH("Groceries",Categories!$B$2:$B$11,0)) -> Groceries | B17: =INDEX(Categories!$E$2:$E$11,MATCH($A17,Categories!$B$2:$B$11,0)) -> 184134.4 | C17: =INDEX(Categories!$D$2:$D$11,MATCH($A17,Categories!$B$2:$B$11,0)) -> 710 | D17: =INDEX(Categories!$C$2:$C$11,MATCH($A17,Categories!$B$2:$B$11,0)) -> 10 | F17: Latin America | G17: =SUMIFS(Orders!$H$2:$H$401,Orders!$G$2:$G$401,$F17,Orders!$F$2:$F$401,"<>Cancelled") -> 331071.38 | H17: =COUNTIFS(Orders!$G$2:$G$401,$F17) -> 81
A18: =INDEX(Categories!$B$2:$B$11,MATCH("Health & Beauty",Categories!$B$2:$B$11,0)) -> Health & Beauty | B18: =INDEX(Categories!$E$2:$E$11,MATCH($A18,Categories!$B$2:$B$11,0)) -> 177044.39 | C18: =INDEX(Categories!$D$2:$D$11,MATCH($A18,Categories!$B$2:$B$11,0)) -> 638 | D18: =INDEX(Categories!$C$2:$C$11,MATCH($A18,Categories!$B$2:$B$11,0)) -> 10
A19: =INDEX(Categories!$B$2:$B$11,MATCH("Automotive Parts",Categories!$B$2:$B$11,0)) -> Automotive Parts | B19: =INDEX(Categories!$E$2:$E$11,MATCH($A19,Categories!$B$2:$B$11,0)) -> 155430.56 | C19: =INDEX(Categories!$D$2:$D$11,MATCH($A19,Categories!$B$2:$B$11,0)) -> 654 | D19: =INDEX(Categories!$C$2:$C$11,MATCH($A19,Categories!$B$2:$B$11,0)) -> 10
A20: =INDEX(Categories!$B$2:$B$11,MATCH("Furniture",Categories!$B$2:$B$11,0)) -> Furniture | B20: =INDEX(Categories!$E$2:$E$11,MATCH($A20,Categories!$B$2:$B$11,0)) -> 144037.7 | C20: =INDEX(Categories!$D$2:$D$11,MATCH($A20,Categories!$B$2:$B$11,0)) -> 621 | D20: =INDEX(Categories!$C$2:$C$11,MATCH($A20,Categories!$B$2:$B$11,0)) -> 10
A21: =INDEX(Categories!$B$2:$B$11,MATCH("Home & Kitchen",Categories!$B$2:$B$11,0)) -> Home & Kitchen | B21: =INDEX(Categories!$E$2:$E$11,MATCH($A21,Categories!$B$2:$B$11,0)) -> 135507.78 | C21: =INDEX(Categories!$D$2:$D$11,MATCH($A21,Categories!$B$2:$B$11,0)) -> 710 | D21: =INDEX(Categories!$C$2:$C$11,MATCH($A21,Categories!$B$2:$B$11,0)) -> 10
A22: =INDEX(Categories!$B$2:$B$11,MATCH("Toys & Games",Categories!$B$2:$B$11,0)) -> Toys & Games | B22: =INDEX(Categories!$E$2:$E$11,MATCH($A22,Categories!$B$2:$B$11,0)) -> 109793.87 | C22: =INDEX(Categories!$D$2:$D$11,MATCH($A22,Categories!$B$2:$B$11,0)) -> 641 | D22: =INDEX(Categories!$C$2:$C$11,MATCH($A22,Categories!$B$2:$B$11,0)) -> 10
A24: Revenue by Customer Segment
A25: Segment | B25: Revenue | C25: Orders
A26: Corporate | B26: =SUMIFS(Orders!$H$2:$H$401,Orders!$L$2:$L$401,$A26,Orders!$F$2:$F$401,"<>Cancelled") -> 457649.96 | C26: =COUNTIFS(Orders!$L$2:$L$401,$A26) -> 113
A27: Small Business | B27: =SUMIFS(Orders!$H$2:$H$401,Orders!$L$2:$L$401,$A27,Orders!$F$2:$F$401,"<>Cancelled") -> 483432.45 | C27: =COUNTIFS(Orders!$L$2:$L$401,$A27) -> 126
A28: Consumer | B28: =SUMIFS(Orders!$H$2:$H$401,Orders!$L$2:$L$401,$A28,Orders!$F$2:$F$401,"<>Cancelled") -> 603046.76 | C28: =COUNTIFS(Orders!$L$2:$L$401,$A28) -> 161
A30: Top 10 Products by Revenue
A31: Product ID | B31: Product Name | C31: Category | D31: Revenue | E31: Units Sold
A32: 36 | B32: =INDEX(Products!$B$2:$B$101,MATCH($A32,Products!$A$2:$A$101,0)) -> Rain Jacket | C32: =INDEX(Products!$J$2:$J$101,MATCH($A32,Products!$A$2:$A$101,0)) -> Apparel | D32: =INDEX(Products!$O$2:$O$101,MATCH($A32,Products!$A$2:$A$101,0)) -> 41485.567 | E32: =INDEX(Products!$N$2:$N$101,MATCH($A32,Products!$A$2:$A$101,0)) -> 95
A33: 51 | B33: =INDEX(Products!$B$2:$B$101,MATCH($A33,Products!$A$2:$A$101,0)) -> Yoga Mat | C33: =INDEX(Products!$J$2:$J$101,MATCH($A33,Products!$A$2:$A$101,0)) -> Sporting Goods | D33: =INDEX(Products!$O$2:$O$101,MATCH($A33,Products!$A$2:$A$101,0)) -> 41242.635 | E33: =INDEX(Products!$N$2:$N$101,MATCH($A33,Products!$A$2:$A$101,0)) -> 104
A34: 50 | B34: =INDEX(Products!$B$2:$B$101,MATCH($A34,Products!$A$2:$A$101,0)) -> Electric Kettle | C34: =INDEX(Products!$J$2:$J$101,MATCH($A34,Products!$A$2:$A$101,0)) -> Home & Kitchen | D34: =INDEX(Products!$O$2:$O$101,MATCH($A34,Products!$A$2:$A$101,0)) -> 39460.8 | E34: =INDEX(Products!$N$2:$N$101,MATCH($A34,Products!$A$2:$A$101,0)) -> 105
A35: 55 | B35: =INDEX(Products!$B$2:$B$101,MATCH($A35,Products!$A$2:$A$101,0)) -> Camping Tent | C35: =INDEX(Products!$J$2:$J$101,MATCH($A35,Products!$A$2:$A$101,0)) -> Sporting Goods | D35: =INDEX(Products!$O$2:$O$101,MATCH($A35,Products!$A$2:$A$101,0)) -> 37089.374 | E35: =INDEX(Products!$N$2:$N$101,MATCH($A35,Products!$A$2:$A$101,0)) -> 106
A36: 53 | B36: =INDEX(Products!$B$2:$B$101,MATCH($A36,Products!$A$2:$A$101,0)) -> Soccer Ball | C36: =INDEX(Products!$J$2:$J$101,MATCH($A36,Products!$A$2:$A$101,0)) -> Sporting Goods | D36: =INDEX(Products!$O$2:$O$101,MATCH($A36,Products!$A$2:$A$101,0)) -> 36659.1 | E36: =INDEX(Products!$N$2:$N$101,MATCH($A36,Products!$A$2:$A$101,0)) -> 74
A37: 34 | B37: =INDEX(Products!$B$2:$B$101,MATCH($A37,Products!$A$2:$A$101,0)) -> Wool Sweater | C37: =INDEX(Products!$J$2:$J$101,MATCH($A37,Products!$A$2:$A$101,0)) -> Apparel | D37: =INDEX(Products!$O$2:$O$101,MATCH($A37,Products!$A$2:$A$101,0)) -> 35994.425 | E37: =INDEX(Products!$N$2:$N$101,MATCH($A37,Products!$A$2:$A$101,0)) -> 113
A38: 11 | B38: =INDEX(Products!$B$2:$B$101,MATCH($A38,Products!$A$2:$A$101,0)) -> Stapler | C38: =INDEX(Products!$J$2:$J$101,MATCH($A38,Products!$A$2:$A$101,0)) -> Office Supplies | D38: =INDEX(Products!$O$2:$O$101,MATCH($A38,Products!$A$2:$A$101,0)) -> 34118.78 | E38: =INDEX(Products!$N$2:$N$101,MATCH($A38,Products!$A$2:$A$101,0)) -> 87
A39: 72 | B39: =INDEX(Products!$B$2:$B$101,MATCH($A39,Products!$A$2:$A$101,0)) -> Hair Dryer | C39: =INDEX(Products!$J$2:$J$101,MATCH($A39,Products!$A$2:$A$101,0)) -> Health & Beauty | D39: =INDEX(Products!$O$2:$O$101,MATCH($A39,Products!$A$2:$A$101,0)) -> 33261.105 | E39: =INDEX(Products!$N$2:$N$101,MATCH($A39,Products!$A$2:$A$101,0)) -> 69
A40: 33 | B40: =INDEX(Products!$B$2:$B$101,MATCH($A40,Products!$A$2:$A$101,0)) -> Running Shoes | C40: =INDEX(Products!$J$2:$J$101,MATCH($A40,Products!$A$2:$A$101,0)) -> Apparel | D40: =INDEX(Products!$O$2:$O$101,MATCH($A40,Products!$A$2:$A$101,0)) -> 32684.583 | E40: =INDEX(Products!$N$2:$N$101,MATCH($A40,Products!$A$2:$A$101,0)) -> 81
A41: 58 | B41: =INDEX(Products!$B$2:$B$101,MATCH($A41,Products!$A$2:$A$101,0)) -> Water Bottle | C41: =INDEX(Products!$J$2:$J$101,MATCH($A41,Products!$A$2:$A$101,0)) -> Sporting Goods | D41: =INDEX(Products!$O$2:$O$101,MATCH($A41,Products!$A$2:$A$101,0)) -> 31433.695 | E41: =INDEX(Products!$N$2:$N$101,MATCH($A41,Products!$A$2:$A$101,0)) -> 85
A43: Top 10 Customers by Revenue
A44: Customer ID | B44: Company | C44: Segment | D44: Revenue
A45: 40 | B45: =INDEX(Customers!$B$2:$B$61,MATCH($A45,Customers!$A$2:$A$61,0)) -> Union Traders | C45: =INDEX(Customers!$G$2:$G$61,MATCH($A45,Customers!$A$2:$A$61,0)) -> Corporate | D45: =INDEX(Customers!$J$2:$J$61,MATCH($A45,Customers!$A$2:$A$61,0)) -> 81483.696
A46: 56 | B46: =INDEX(Customers!$B$2:$B$61,MATCH($A46,Customers!$A$2:$A$61,0)) -> Coastal Ventures | C46: =INDEX(Customers!$G$2:$G$61,MATCH($A46,Customers!$A$2:$A$61,0)) -> Consumer | D46: =INDEX(Customers!$J$2:$J$61,MATCH($A46,Customers!$A$2:$A$61,0)) -> 61687.656
A47: 31 | B47: =INDEX(Customers!$B$2:$B$61,MATCH($A47,Customers!$A$2:$A$61,0)) -> Silver Ventures | C47: =INDEX(Customers!$G$2:$G$61,MATCH($A47,Customers!$A$2:$A$61,0)) -> Consumer | D47: =INDEX(Customers!$J$2:$J$61,MATCH($A47,Customers!$A$2:$A$61,0)) -> 59497.623
A48: 30 | B48: =INDEX(Customers!$B$2:$B$61,MATCH($A48,Customers!$A$2:$A$61,0)) -> Sunset Industries | C48: =INDEX(Customers!$G$2:$G$61,MATCH($A48,Customers!$A$2:$A$61,0)) -> Consumer | D48: =INDEX(Customers!$J$2:$J$61,MATCH($A48,Customers!$A$2:$A$61,0)) -> 56501.296
A49: 10 | B49: =INDEX(Customers!$B$2:$B$61,MATCH($A49,Customers!$A$2:$A$61,0)) -> Horizon Traders | C49: =INDEX(Customers!$G$2:$G$61,MATCH($A49,Customers!$A$2:$A$61,0)) -> Corporate | D49: =INDEX(Customers!$J$2:$J$61,MATCH($A49,Customers!$A$2:$A$61,0)) -> 55426.68
A50: 49 | B50: =INDEX(Customers!$B$2:$B$61,MATCH($A50,Customers!$A$2:$A$61,0)) -> Urban Distributors | C50: =INDEX(Customers!$G$2:$G$61,MATCH($A50,Customers!$A$2:$A$61,0)) -> Corporate | D50: =INDEX(Customers!$J$2:$J$61,MATCH($A50,Customers!$A$2:$A$61,0)) -> 54215.192
A51: 6 | B51: =INDEX(Customers!$B$2:$B$61,MATCH($A51,Customers!$A$2:$A$61,0)) -> Nova Industries | C51: =INDEX(Customers!$G$2:$G$61,MATCH($A51,Customers!$A$2:$A$61,0)) -> Consumer | D51: =INDEX(Customers!$J$2:$J$61,MATCH($A51,Customers!$A$2:$A$61,0)) -> 46488.101
A52: 55 | B52: =INDEX(Customers!$B$2:$B$61,MATCH($A52,Customers!$A$2:$A$61,0)) -> Alpha Wholesale | C52: =INDEX(Customers!$G$2:$G$61,MATCH($A52,Customers!$A$2:$A$61,0)) -> Consumer | D52: =INDEX(Customers!$J$2:$J$61,MATCH($A52,Customers!$A$2:$A$61,0)) -> 45176.289
A53: 50 | B53: =INDEX(Customers!$B$2:$B$61,MATCH($A53,Customers!$A$2:$A$61,0)) -> Summit Enterprises | C53: =INDEX(Customers!$G$2:$G$61,MATCH($A53,Customers!$A$2:$A$61,0)) -> Consumer | D53: =INDEX(Customers!$J$2:$J$61,MATCH($A53,Customers!$A$2:$A$61,0)) -> 45141.263
A54: 33 | B54: =INDEX(Customers!$B$2:$B$61,MATCH($A54,Customers!$A$2:$A$61,0)) -> Coastal Imports | C54: =INDEX(Customers!$G$2:$G$61,MATCH($A54,Customers!$A$2:$A$61,0)) -> Consumer | D54: =INDEX(Customers!$J$2:$J$61,MATCH($A54,Customers!$A$2:$A$61,0)) -> 44966.746
A56: Sales Rep Performance
A57: Employee ID | B57: Name | C57: Orders Handled | D57: Revenue Generated | E57: Avg Order Value
A58: 1 | B58: =INDEX(Employees!$B$2:$B$37,MATCH($A58,Employees!$A$2:$A$37,0))&" "&INDEX(Employees!$C$2:$C$37,MATCH($A58,Employees!$A$2:$A$37,0)) -> Daniel Brown | C58: =INDEX(Employees!$O$2:$O$37,MATCH($A58,Employees!$A$2:$A$37,0)) -> 89 | D58: =INDEX(Employees!$P$2:$P$37,MATCH($A58,Employees!$A$2:$A$37,0)) -> 377581.84 | E58: =IFERROR(D58/C58,0) -> 4242.4925
A59: 8 | B59: =INDEX(Employees!$B$2:$B$37,MATCH($A59,Employees!$A$2:$A$37,0))&" "&INDEX(Employees!$C$2:$C$37,MATCH($A59,Employees!$A$2:$A$37,0)) -> John Gonzalez | C59: =INDEX(Employees!$O$2:$O$37,MATCH($A59,Employees!$A$2:$A$37,0)) -> 115 | D59: =INDEX(Employees!$P$2:$P$37,MATCH($A59,Employees!$A$2:$A$37,0)) -> 497216.81 | E59: =IFERROR(D59/C59,0) -> 4323.6245
A60: 9 | B60: =INDEX(Employees!$B$2:$B$37,MATCH($A60,Employees!$A$2:$A$37,0))&" "&INDEX(Employees!$C$2:$C$37,MATCH($A60,Employees!$A$2:$A$37,0)) -> William Johnson | C60: =INDEX(Employees!$O$2:$O$37,MATCH($A60,Employees!$A$2:$A$37,0)) -> 93 | D60: =INDEX(Employees!$P$2:$P$37,MATCH($A60,Employees!$A$2:$A$37,0)) -> 419101.89 | E60: =IFERROR(D60/C60,0) -> 4506.4719
A61: 10 | B61: =INDEX(Employees!$B$2:$B$37,MATCH($A61,Employees!$A$2:$A$37,0))&" "&INDEX(Employees!$C$2:$C$37,MATCH($A61,Employees!$A$2:$A$37,0)) -> John Moore | C61: =INDEX(Employees!$O$2:$O$37,MATCH($A61,Employees!$A$2:$A$37,0)) -> 103 | D61: =INDEX(Employees!$P$2:$P$37,MATCH($A61,Employees!$A$2:$A$37,0)) -> 461776.55 | E61: =IFERROR(D61/C61,0) -> 4483.2675
A63: Monthly Revenue Trend
A64: Month | B64: Revenue | C64: Orders | D64: Avg Order Value
A65: 2023-01 | B65: =SUMIFS(Orders!$H$2:$H$401,Orders!$K$2:$K$401,$A65,Orders!$F$2:$F$401,"<>Cancelled") -> 35933.363 | C65: =COUNTIFS(Orders!$K$2:$K$401,$A65) -> 6 | D65: =IFERROR(B65/C65,0) -> 5988.8938
A66: 2023-02 | B66: =SUMIFS(Orders!$H$2:$H$401,Orders!$K$2:$K$401,$A66,Orders!$F$2:$F$401,"<>Cancelled") -> 49557.449 | C66: =COUNTIFS(Orders!$K$2:$K$401,$A66) -> 11 | D66: =IFERROR(B66/C66,0) -> 4505.2226
A67: 2023-03 | B67: =SUMIFS(Orders!$H$2:$H$401,Orders!$K$2:$K$401,$A67,Orders!$F$2:$F$401,"<>Cancelled") -> 37361.666 | C67: =COUNTIFS(Orders!$K$2:$K$401,$A67) -> 14 | D67: =IFERROR(B67/C67,0) -> 2668.6904
A68: 2023-04 | B68: =SUMIFS(Orders!$H$2:$H$401,Orders!$K$2:$K$401,$A68,Orders!$F$2:$F$401,"<>Cancelled") -> 26172.149 | C68: =COUNTIFS(Orders!$K$2:$K$401,$A68) -> 10 | D68: =IFERROR(B68/C68,0) -> 2617.2149
A69: 2023-05 | B69: =SUMIFS(Orders!$H$2:$H$401,Orders!$K$2:$K$401,$A69,Orders!$F$2:$F$401,"<>Cancelled") -> 45340.938 | C69: =COUNTIFS(Orders!$K$2:$K$401,$A69) -> 10 | D69: =IFERROR(B69/C69,0) -> 4534.0938
A70: 2023-06 | B70: =SUMIFS(Orders!$H$2:$H$401,Orders!$K$2:$K$401,$A70,Orders!$F$2:$F$401,"<>Cancelled") -> 49946.831 | C70: =COUNTIFS(Orders!$K$2:$K$401,$A70) -> 13 | D70: =IFERROR(B70/C70,0) -> 3842.0639
A71: 2023-07 | B71: =SUMIFS(Orders!$H$2:$H$401,Orders!$K$2:$K$401,$A71,Orders!$F$2:$F$401,"<>Cancelled") -> 52097.839 | C71: =COUNTIFS(Orders!$K$2:$K$401,$A71) -> 13 | D71: =IFERROR(B71/C71,0) -> 4007.526
A72: 2023-08 | B72: =SUMIFS(Orders!$H$2:$H$401,Orders!$K$2:$K$401,$A72,Orders!$F$2:$F$401,"<>Cancelled") -> 69113.531 | C72: =COUNTIFS(Orders!$K$2:$K$401,$A72) -> 15 | D72: =IFERROR(B72/C72,0) -> 4607.5688
A73: 2023-09 | B73: =SUMIFS(Orders!$H$2:$H$401,Orders!$K$2:$K$401,$A73,Orders!$F$2:$F$401,"<>Cancelled") -> 36998.58 | C73: =COUNTIFS(Orders!$K$2:$K$401,$A73) -> 11 | D73: =IFERROR(B73/C73,0) -> 3363.5073
A74: 2023-10 | B74: =SUMIFS(Orders!$H$2:$H$401,Orders!$K$2:$K$401,$A74,Orders!$F$2:$F$401,"<>Cancelled") -> 39838.62 | C74: =COUNTIFS(Orders!$K$2:$K$401,$A74) -> 13 | D74: =IFERROR(B74/C74,0) -> 3064.5092
A75: 2023-11 | B75: =SUMIFS(Orders!$H$2:$H$401,Orders!$K$2:$K$401,$A75,Orders!$F$2:$F$401,"<>Cancelled") -> 34961.761 | C75: =COUNTIFS(Orders!$K$2:$K$401,$A75) -> 13 | D75: =IFERROR(B75/C75,0) -> 2689.3662
A76: 2023-12 | B76: =SUMIFS(Orders!$H$2:$H$401,Orders!$K$2:$K$401,$A76,Orders!$F$2:$F$401,"<>Cancelled") -> 41076.233 | C76: =COUNTIFS(Orders!$K$2:$K$401,$A76) -> 11 | D76: =IFERROR(B76/C76,0) -> 3734.203
... A100: 2025-12 | B100: =SUMIFS(Orders!$H$2:$H$401,Orders!$K$2:$K$401,$A100,Orders!$F$2:$F$401,"<>Cancelled") -> 41335.026 | C100: =COUNTIFS(Orders!$K$2:$K$401,$A100) -> 12 | D100: =IFERROR(B100/C100,0) -> 3444.5855

Sheet Finance Analysis
A1: Finance Analysis
A2: Revenue, cost, margin, payments and payroll vs. budget
A4: Key Performance Indicators
A5: GROSS REVENUE (excl. Cancelled) | C5: TOTAL COGS | E5: GROSS PROFIT | G5: GROSS MARGIN %
A6: =SUMIFS(Orders!H2:H401,Orders!F2:F401,"<>Cancelled") -> 1544129.2 | C6: =SUMIFS(Orders!I2:I401,Orders!F2:F401,"<>Cancelled") -> 905262.92 | E6: =A6-C6 -> 638866.24 | G6: =E6/A6 -> 0.41373886
A8: CASH COLLECTED (Completed) | C8: REFUNDED | E8: PENDING PAYMENTS | G8: AR GAP (Revenue-Collected)
A9: =SUMIFS(Payments!D2:D349,Payments!F2:F349,"Completed") -> 1268281.9 | C9: =SUMIFS(Payments!D2:D349,Payments!F2:F349,"Refunded") -> 144617.54 | E9: =SUMIFS(Payments!D2:D349,Payments!F2:F349,"Pending") -> 131229.75 | G9: =A6-A9 -> 275847.3
A11: Payments by Status | F11: Payments by Method
A12: Status | B12: Count | C12: Total Amount | D12: % of Payments | F12: Method | G12: Count | H12: Total Amount
A13: Completed | B13: =COUNTIF(Payments!$F$2:$F$349,$A13) -> 284 | C13: =SUMIF(Payments!$F$2:$F$349,$A13,Payments!$D$2:$D$349) -> 1268281.9 | D13: =B13/COUNTA(Payments!$A$2:$A$349) -> 0.81609195 | F13: Credit Card | G13: =COUNTIF(Payments!$E$2:$E$349,$F13) -> 92 | H13: =SUMIF(Payments!$E$2:$E$349,$F13,Payments!$D$2:$D$349) -> 438262.21
A14: Refunded | B14: =COUNTIF(Payments!$F$2:$F$349,$A14) -> 33 | C14: =SUMIF(Payments!$F$2:$F$349,$A14,Payments!$D$2:$D$349) -> 144617.54 | D14: =B14/COUNTA(Payments!$A$2:$A$349) -> 0.094827586 | F14: Bank Transfer | G14: =COUNTIF(Payments!$E$2:$E$349,$F14) -> 90 | H14: =SUMIF(Payments!$E$2:$E$349,$F14,Payments!$D$2:$D$349) -> 416570.46
A15: Pending | B15: =COUNTIF(Payments!$F$2:$F$349,$A15) -> 31 | C15: =SUMIF(Payments!$F$2:$F$349,$A15,Payments!$D$2:$D$349) -> 131229.75 | D15: =B15/COUNTA(Payments!$A$2:$A$349) -> 0.08908046 | F15: PayPal | G15: =COUNTIF(Payments!$E$2:$E$349,$F15) -> 84 | H15: =SUMIF(Payments!$E$2:$E$349,$F15,Payments!$D$2:$D$349) -> 373894.6
F16: Check | G16: =COUNTIF(Payments!$E$2:$E$349,$F16) -> 82 | H16: =SUMIF(Payments!$E$2:$E$349,$F16,Payments!$D$2:$D$349) -> 315401.89
A17: Department Budget vs. Payroll Cost
A18: Department | B18: Budget | C18: Headcount | D18: Payroll Cost | E18: Variance | F18: Utilization %
A19: =Departments!B2 -> Sales | B19: =Departments!C2 -> 500000 | C19: =Departments!D2 -> 0 | D19: =Departments!E2 -> 0 | E19: =Departments!F2 -> 500000 | F19: =Departments!G2 -> 0
A20: =Departments!B3 -> Marketing | B20: =Departments!C3 -> 250000 | C20: =Departments!D3 -> 4 | D20: =Departments!E3 -> 355891.84 | E20: =Departments!F3 -> -105891.84 | F20: =Departments!G3 -> 1.4235674
A21: =Departments!B4 -> Finance | B21: =Departments!C4 -> 300000 | C21: =Departments!D4 -> 6 | D21: =Departments!E4 -> 458531.52 | E21: =Departments!F4 -> -158531.52 | F21: =Departments!G4 -> 1.5284384
A22: =Departments!B5 -> Operations | B22: =Departments!C5 -> 450000 | C22: =Departments!D5 -> 4 | D22: =Departments!E5 -> 338462.72 | E22: =Departments!F5 -> 111537.28 | F22: =Departments!G5 -> 0.75213938
A23: =Departments!B6 -> Human Resources | B23: =Departments!C6 -> 150000 | C23: =Departments!D6 -> 6 | D23: =Departments!E6 -> 477814.43 | E23: =Departments!F6 -> -327814.43 | F23: =Departments!G6 -> 3.1854295
A24: =Departments!B7 -> IT | B24: =Departments!C7 -> 350000 | C24: =Departments!D7 -> 6 | D24: =Departments!E7 -> 431307.33 | E24: =Departments!F7 -> -81307.33 | F24: =Departments!G7 -> 1.2323067
A25: =Departments!B8 -> Customer Support | B25: =Departments!C8 -> 200000 | C25: =Departments!D8 -> 6 | D25: =Departments!E8 -> 508330.64 | E25: =Departments!F8 -> -308330.64 | F25: =Departments!G8 -> 2.5416532
A27: Category Profitability
A28: Category | B28: Revenue | C28: Inventory Value | D28: Est. COGS on Sales | E28: Est. Margin %
A29: =INDEX(Categories!$B$2:$B$11,MATCH("Sporting Goods",Categories!$B$2:$B$11,0)) -> Sporting Goods | B29: =INDEX(Categories!$E$2:$E$11,MATCH($A29,Categories!$B$2:$B$11,0)) -> 269240.84 | C29: =INDEX(Categories!$F$2:$F$11,MATCH($A29,Categories!$B$2:$B$11,0)) -> 517487.33 | D29: =SUMIFS(OrderItems!$K$2:$K$1254,OrderItems!$I$2:$I$1254,$A29) -> 149778.88 | E29: =IFERROR((B29-D29)/B29,0) -> 0.44369925
A30: =INDEX(Categories!$B$2:$B$11,MATCH("Apparel",Categories!$B$2:$B$11,0)) -> Apparel | B30: =INDEX(Categories!$E$2:$E$11,MATCH($A30,Categories!$B$2:$B$11,0)) -> 206243 | C30: =INDEX(Categories!$F$2:$F$11,MATCH($A30,Categories!$B$2:$B$11,0)) -> 342078.09 | D30: =SUMIFS(OrderItems!$K$2:$K$1254,OrderItems!$I$2:$I$1254,$A30) -> 121515.51 | E30: =IFERROR((B30-D30)/B30,0) -> 0.4108139
A31: =INDEX(Categories!$B$2:$B$11,MATCH("Office Supplies",Categories!$B$2:$B$11,0)) -> Office Supplies | B31: =INDEX(Categories!$E$2:$E$11,MATCH($A31,Categories!$B$2:$B$11,0)) -> 188788.64 | C31: =INDEX(Categories!$F$2:$F$11,MATCH($A31,Categories!$B$2:$B$11,0)) -> 494090.55 | D31: =SUMIFS(OrderItems!$K$2:$K$1254,OrderItems!$I$2:$I$1254,$A31) -> 117283.98 | E31: =IFERROR((B31-D31)/B31,0) -> 0.37875509
A32: =INDEX(Categories!$B$2:$B$11,MATCH("Electronics",Categories!$B$2:$B$11,0)) -> Electronics | B32: =INDEX(Categories!$E$2:$E$11,MATCH($A32,Categories!$B$2:$B$11,0)) -> 185455.92 | C32: =INDEX(Categories!$F$2:$F$11,MATCH($A32,Categories!$B$2:$B$11,0)) -> 474429.85 | D32: =SUMIFS(OrderItems!$K$2:$K$1254,OrderItems!$I$2:$I$1254,$A32) -> 107693.74 | E32: =IFERROR((B32-D32)/B32,0) -> 0.41930276
A33: =INDEX(Categories!$B$2:$B$11,MATCH("Groceries",Categories!$B$2:$B$11,0)) -> Groceries | B33: =INDEX(Categories!$E$2:$E$11,MATCH($A33,Categories!$B$2:$B$11,0)) -> 184134.4 | C33: =INDEX(Categories!$F$2:$F$11,MATCH($A33,Categories!$B$2:$B$11,0)) -> 343753.31 | D33: =SUMIFS(OrderItems!$K$2:$K$1254,OrderItems!$I$2:$I$1254,$A33) -> 105551.09 | E33: =IFERROR((B33-D33)/B33,0) -> 0.42677148
A34: =INDEX(Categories!$B$2:$B$11,MATCH("Health & Beauty",Categories!$B$2:$B$11,0)) -> Health & Beauty | B34: =INDEX(Categories!$E$2:$E$11,MATCH($A34,Categories!$B$2:$B$11,0)) -> 177044.39 | C34: =INDEX(Categories!$F$2:$F$11,MATCH($A34,Categories!$B$2:$B$11,0)) -> 466264.94 | D34: =SUMIFS(OrderItems!$K$2:$K$1254,OrderItems!$I$2:$I$1254,$A34) -> 106106.16 | E34: =IFERROR((B34-D34)/B34,0) -> 0.40068048
A35: =INDEX(Categories!$B$2:$B$11,MATCH("Automotive Parts",Categories!$B$2:$B$11,0)) -> Automotive Parts | B35: =INDEX(Categories!$E$2:$E$11,MATCH($A35,Categories!$B$2:$B$11,0)) -> 155430.56 | C35: =INDEX(Categories!$F$2:$F$11,MATCH($A35,Categories!$B$2:$B$11,0)) -> 359871.16 | D35: =SUMIFS(OrderItems!$K$2:$K$1254,OrderItems!$I$2:$I$1254,$A35) -> 91834.81 | E35: =IFERROR((B35-D35)/B35,0) -> 0.40915859
A36: =INDEX(Categories!$B$2:$B$11,MATCH("Furniture",Categories!$B$2:$B$11,0)) -> Furniture | B36: =INDEX(Categories!$E$2:$E$11,MATCH($A36,Categories!$B$2:$B$11,0)) -> 144037.7 | C36: =INDEX(Categories!$F$2:$F$11,MATCH($A36,Categories!$B$2:$B$11,0)) -> 374937.3 | D36: =SUMIFS(OrderItems!$K$2:$K$1254,OrderItems!$I$2:$I$1254,$A36) -> 86135.48 | E36: =IFERROR((B36-D36)/B36,0) -> 0.4019935
A37: =INDEX(Categories!$B$2:$B$11,MATCH("Home & Kitchen",Categories!$B$2:$B$11,0)) -> Home & Kitchen | B37: =INDEX(Categories!$E$2:$E$11,MATCH($A37,Categories!$B$2:$B$11,0)) -> 135507.78 | C37: =INDEX(Categories!$F$2:$F$11,MATCH($A37,Categories!$B$2:$B$11,0)) -> 246239.51 | D37: =SUMIFS(OrderItems!$K$2:$K$1254,OrderItems!$I$2:$I$1254,$A37) -> 79897.14 | E37: =IFERROR((B37-D37)/B37,0) -> 0.41038706
A38: =INDEX(Categories!$B$2:$B$11,MATCH("Toys & Games",Categories!$B$2:$B$11,0)) -> Toys & Games | B38: =INDEX(Categories!$E$2:$E$11,MATCH($A38,Categories!$B$2:$B$11,0)) -> 109793.87 | C38: =INDEX(Categories!$F$2:$F$11,MATCH($A38,Categories!$B$2:$B$11,0)) -> 199556.26 | D38: =SUMIFS(OrderItems!$K$2:$K$1254,OrderItems!$I$2:$I$1254,$A38) -> 63061.95 | E38: =IFERROR((B38-D38)/B38,0) -> 0.42563322
A40: Monthly Cash Collected (Completed Payments)
A41: Month | B41: Cash Collected | C41: Payment Count
A42: 2023-01 | B42: =SUMIFS(Payments!$D$2:$D$349,Payments!$H$2:$H$349,$A42,Payments!$F$2:$F$349,"Completed") -> 13815.4 | C42: =COUNTIFS(Payments!$H$2:$H$349,$A42,Payments!$F$2:$F$349,"Completed") -> 3
A43: 2023-02 | B43: =SUMIFS(Payments!$D$2:$D$349,Payments!$H$2:$H$349,$A43,Payments!$F$2:$F$349,"Completed") -> 37838.82 | C43: =COUNTIFS(Payments!$H$2:$H$349,$A43,Payments!$F$2:$F$349,"Completed") -> 7
A44: 2023-03 | B44: =SUMIFS(Payments!$D$2:$D$349,Payments!$H$2:$H$349,$A44,Payments!$F$2:$F$349,"Completed") -> 29759.34 | C44: =COUNTIFS(Payments!$H$2:$H$349,$A44,Payments!$F$2:$F$349,"Completed") -> 7
A45: 2023-04 | B45: =SUMIFS(Payments!$D$2:$D$349,Payments!$H$2:$H$349,$A45,Payments!$F$2:$F$349,"Completed") -> 25786.11 | C45: =COUNTIFS(Payments!$H$2:$H$349,$A45,Payments!$F$2:$F$349,"Completed") -> 4
A46: 2023-05 | B46: =SUMIFS(Payments!$D$2:$D$349,Payments!$H$2:$H$349,$A46,Payments!$F$2:$F$349,"Completed") -> 37229.77 | C46: =COUNTIFS(Payments!$H$2:$H$349,$A46,Payments!$F$2:$F$349,"Completed") -> 9
A47: 2023-06 | B47: =SUMIFS(Payments!$D$2:$D$349,Payments!$H$2:$H$349,$A47,Payments!$F$2:$F$349,"Completed") -> 45740.94 | C47: =COUNTIFS(Payments!$H$2:$H$349,$A47,Payments!$F$2:$F$349,"Completed") -> 9
A48: 2023-07 | B48: =SUMIFS(Payments!$D$2:$D$349,Payments!$H$2:$H$349,$A48,Payments!$F$2:$F$349,"Completed") -> 21294.19 | C48: =COUNTIFS(Payments!$H$2:$H$349,$A48,Payments!$F$2:$F$349,"Completed") -> 6
A49: 2023-08 | B49: =SUMIFS(Payments!$D$2:$D$349,Payments!$H$2:$H$349,$A49,Payments!$F$2:$F$349,"Completed") -> 74913.99 | C49: =COUNTIFS(Payments!$H$2:$H$349,$A49,Payments!$F$2:$F$349,"Completed") -> 13
A50: 2023-09 | B50: =SUMIFS(Payments!$D$2:$D$349,Payments!$H$2:$H$349,$A50,Payments!$F$2:$F$349,"Completed") -> 25610.24 | C50: =COUNTIFS(Payments!$H$2:$H$349,$A50,Payments!$F$2:$F$349,"Completed") -> 7
A51: 2023-10 | B51: =SUMIFS(Payments!$D$2:$D$349,Payments!$H$2:$H$349,$A51,Payments!$F$2:$F$349,"Completed") -> 34818.06 | C51: =COUNTIFS(Payments!$H$2:$H$349,$A51,Payments!$F$2:$F$349,"Completed") -> 8
A52: 2023-11 | B52: =SUMIFS(Payments!$D$2:$D$349,Payments!$H$2:$H$349,$A52,Payments!$F$2:$F$349,"Completed") -> 26359.76 | C52: =COUNTIFS(Payments!$H$2:$H$349,$A52,Payments!$F$2:$F$349,"Completed") -> 8
A53: 2023-12 | B53: =SUMIFS(Payments!$D$2:$D$349,Payments!$H$2:$H$349,$A53,Payments!$F$2:$F$349,"Completed") -> 19677.95 | C53: =COUNTIFS(Payments!$H$2:$H$349,$A53,Payments!$F$2:$F$349,"Completed") -> 6
... A77: 2025-12 | B77: =SUMIFS(Payments!$D$2:$D$349,Payments!$H$2:$H$349,$A77,Payments!$F$2:$F$349,"Completed") -> 36488.79 | C77: =COUNTIFS(Payments!$H$2:$H$349,$A77,Payments!$F$2:$F$349,"Completed") -> 9

Sheet HR Analysis
A1: Human Resources Analysis
A2: Headcount, compensation, tenure and org structure
A4: Key Performance Indicators
A5: TOTAL HEADCOUNT | C5: TOTAL PAYROLL (Annual) | E5: AVERAGE SALARY | G5: AVG TENURE (Years)
A6: =COUNTA(Employees!A2:A37) -> 36 | C6: =SUM(Employees!I2:I37) -> 2921762 | E6: =AVERAGE(Employees!I2:I37) -> 81160.055 | G6: =AVERAGE(Employees!L2:L37) -> 6.6777778
A8: TOTAL DEPT BUDGET | C8: PAYROLL / BUDGET % | E8: MEDIAN SALARY | G8: HEADCOUNT W/ DIRECT REPORTS
A9: =SUM(Departments!C2:C8) -> 2200000 | C9: =B6/A9 -> 0 | E9: =MEDIAN(Employees!I2:I37) -> 80304.775 | G9: =COUNTIF(Employees!N2:N37,">0") -> 7
A11: Headcount & Compensation by Department
A12: Department | B12: Headcount | C12: Avg Salary | D12: Min Salary | E12: Max Salary | F12: Total Payroll
A13: =Departments!B2 -> Sales | B13: =Departments!D2 -> 0 | C13: =IFERROR(AVERAGEIF(Employees!$E$2:$E$37,Departments!A2,Employees!$I$2:$I$37),0) -> 0 | D13: =IFERROR(minifs(Employees!$I$2:$I$37,Employees!$E$2:$E$37,Departments!A2),0) -> 0 | E13: =IFERROR(maxifs(Employees!$I$2:$I$37,Employees!$E$2:$E$37,Departments!A2),0) -> 0 | F13: =Departments!E2 -> 0
A14: =Departments!B3 -> Marketing | B14: =Departments!D3 -> 4 | C14: =IFERROR(AVERAGEIF(Employees!$E$2:$E$37,Departments!A3,Employees!$I$2:$I$37),0) -> 88972.96 | D14: =IFERROR(minifs(Employees!$I$2:$I$37,Employees!$E$2:$E$37,Departments!A3),0) -> 0 | E14: =IFERROR(maxifs(Employees!$I$2:$I$37,Employees!$E$2:$E$37,Departments!A3),0) -> 0 | F14: =Departments!E3 -> 355891.84
A15: =Departments!B4 -> Finance | B15: =Departments!D4 -> 6 | C15: =IFERROR(AVERAGEIF(Employees!$E$2:$E$37,Departments!A4,Employees!$I$2:$I$37),0) -> 76421.92 | D15: =IFERROR(minifs(Employees!$I$2:$I$37,Employees!$E$2:$E$37,Departments!A4),0) -> 0 | E15: =IFERROR(maxifs(Employees!$I$2:$I$37,Employees!$E$2:$E$37,Departments!A4),0) -> 0 | F15: =Departments!E4 -> 458531.52
A16: =Departments!B5 -> Operations | B16: =Departments!D5 -> 4 | C16: =IFERROR(AVERAGEIF(Employees!$E$2:$E$37,Departments!A5,Employees!$I$2:$I$37),0) -> 84615.68 | D16: =IFERROR(minifs(Employees!$I$2:$I$37,Employees!$E$2:$E$37,Departments!A5),0) -> 0 | E16: =IFERROR(maxifs(Employees!$I$2:$I$37,Employees!$E$2:$E$37,Departments!A5),0) -> 0 | F16: =Departments!E5 -> 338462.72
A17: =Departments!B6 -> Human Resources | B17: =Departments!D6 -> 6 | C17: =IFERROR(AVERAGEIF(Employees!$E$2:$E$37,Departments!A6,Employees!$I$2:$I$37),0) -> 79635.738 | D17: =IFERROR(minifs(Employees!$I$2:$I$37,Employees!$E$2:$E$37,Departments!A6),0) -> 0 | E17: =IFERROR(maxifs(Employees!$I$2:$I$37,Employees!$E$2:$E$37,Departments!A6),0) -> 0 | F17: =Departments!E6 -> 477814.43
A18: =Departments!B7 -> IT | B18: =Departments!D7 -> 6 | C18: =IFERROR(AVERAGEIF(Employees!$E$2:$E$37,Departments!A7,Employees!$I$2:$I$37),0) -> 71884.555 | D18: =IFERROR(minifs(Employees!$I$2:$I$37,Employees!$E$2:$E$37,Departments!A7),0) -> 0 | E18: =IFERROR(maxifs(Employees!$I$2:$I$37,Employees!$E$2:$E$37,Departments!A7),0) -> 0 | F18: =Departments!E7 -> 431307.33
A19: =Departments!B8 -> Customer Support | B19: =Departments!D8 -> 6 | C19: =IFERROR(AVERAGEIF(Employees!$E$2:$E$37,Departments!A8,Employees!$I$2:$I$37),0) -> 84721.773 | D19: =IFERROR(minifs(Employees!$I$2:$I$37,Employees!$E$2:$E$37,Departments!A8),0) -> 0 | E19: =IFERROR(maxifs(Employees!$I$2:$I$37,Employees!$E$2:$E$37,Departments!A8),0) -> 0 | F19: =Departments!E8 -> 508330.64
A21: Headcount by Region
A22: Region | B22: Headcount | C22: Avg Salary
A23: North America | B23: =COUNTIF(Employees!$J$2:$J$37,$A23) -> 8 | C23: =IFERROR(AVERAGEIF(Employees!$J$2:$J$37,$A23,Employees!$I$2:$I$37),0) -> 74055.154
A24: Europe | B24: =COUNTIF(Employees!$J$2:$J$37,$A24) -> 6 | C24: =IFERROR(AVERAGEIF(Employees!$J$2:$J$37,$A24,Employees!$I$2:$I$37),0) -> 79553.392
A25: Asia Pacific | B25: =COUNTIF(Employees!$J$2:$J$37,$A25) -> 11 | C25: =IFERROR(AVERAGEIF(Employees!$J$2:$J$37,$A25,Employees!$I$2:$I$37),0) -> 85148.41
A26: Middle East | B26: =COUNTIF(Employees!$J$2:$J$37,$A26) -> 6 | C26: =IFERROR(AVERAGEIF(Employees!$J$2:$J$37,$A26,Employees!$I$2:$I$37),0) -> 94548.898
A27: Latin America | B27: =COUNTIF(Employees!$J$2:$J$37,$A27) -> 5 | C27: =IFERROR(AVERAGEIF(Employees!$J$2:$J$37,$A27,Employees!$I$2:$I$37),0) -> 69614.9
A29: Tenure Distribution
A30: Tenure Band | B30: Headcount
A31: 0-2 years | B31: =COUNTIFS(Employees!$L$2:$L$37,"<2") -> 1
A32: 2-5 years | B32: =COUNTIFS(Employees!$L$2:$L$37,">=2",Employees!$L$2:$L$37,"<5") -> 11
A33: 5-8 years | B33: =COUNTIFS(Employees!$L$2:$L$37,">=5",Employees!$L$2:$L$37,"<8") -> 9
A34: 8+ years | B34: =COUNTIFS(Employees!$L$2:$L$37,">=8") -> 15
A36: Manager Span of Control
A37: Employee ID | B37: Manager Name | C37: Department | D37: Direct Reports
A38: 1 | B38: =INDEX(Employees!$B$2:$B$37,MATCH($A38,Employees!$A$2:$A$37,0))&" "&INDEX(Employees!$C$2:$C$37,MATCH($A38,Employees!$A$2:$A$37,0)) -> Daniel Brown | C38: =INDEX(Employees!$K$2:$K$37,MATCH($A38,Employees!$A$2:$A$37,0)) -> Unassigned | D38: =INDEX(Employees!$N$2:$N$37,MATCH($A38,Employees!$A$2:$A$37,0)) -> 3
A39: 2 | B39: =INDEX(Employees!$B$2:$B$37,MATCH($A39,Employees!$A$2:$A$37,0))&" "&INDEX(Employees!$C$2:$C$37,MATCH($A39,Employees!$A$2:$A$37,0)) -> Linda Jones | C39: =INDEX(Employees!$K$2:$K$37,MATCH($A39,Employees!$A$2:$A$37,0)) -> Marketing | D39: =INDEX(Employees!$N$2:$N$37,MATCH($A39,Employees!$A$2:$A$37,0)) -> 3
A40: 3 | B40: =INDEX(Employees!$B$2:$B$37,MATCH($A40,Employees!$A$2:$A$37,0))&" "&INDEX(Employees!$C$2:$C$37,MATCH($A40,Employees!$A$2:$A$37,0)) -> John Jackson | C40: =INDEX(Employees!$K$2:$K$37,MATCH($A40,Employees!$A$2:$A$37,0)) -> Finance | D40: =INDEX(Employees!$N$2:$N$37,MATCH($A40,Employees!$A$2:$A$37,0)) -> 5
A41: 4 | B41: =INDEX(Employees!$B$2:$B$37,MATCH($A41,Employees!$A$2:$A$37,0))&" "&INDEX(Employees!$C$2:$C$37,MATCH($A41,Employees!$A$2:$A$37,0)) -> Michael Davis | C41: =INDEX(Employees!$K$2:$K$37,MATCH($A41,Employees!$A$2:$A$37,0)) -> Operations | D41: =INDEX(Employees!$N$2:$N$37,MATCH($A41,Employees!$A$2:$A$37,0)) -> 3
A42: 5 | B42: =INDEX(Employees!$B$2:$B$37,MATCH($A42,Employees!$A$2:$A$37,0))&" "&INDEX(Employees!$C$2:$C$37,MATCH($A42,Employees!$A$2:$A$37,0)) -> Michael Moore | C42: =INDEX(Employees!$K$2:$K$37,MATCH($A42,Employees!$A$2:$A$37,0)) -> Human Resources | D42: =INDEX(Employees!$N$2:$N$37,MATCH($A42,Employees!$A$2:$A$37,0)) -> 5
A43: 6 | B43: =INDEX(Employees!$B$2:$B$37,MATCH($A43,Employees!$A$2:$A$37,0))&" "&INDEX(Employees!$C$2:$C$37,MATCH($A43,Employees!$A$2:$A$37,0)) -> William Smith | C43: =INDEX(Employees!$K$2:$K$37,MATCH($A43,Employees!$A$2:$A$37,0)) -> IT | D43: =INDEX(Employees!$N$2:$N$37,MATCH($A43,Employees!$A$2:$A$37,0)) -> 5
A44: 7 | B44: =INDEX(Employees!$B$2:$B$37,MATCH($A44,Employees!$A$2:$A$37,0))&" "&INDEX(Employees!$C$2:$C$37,MATCH($A44,Employees!$A$2:$A$37,0)) -> William Jones | C44: =INDEX(Employees!$K$2:$K$37,MATCH($A44,Employees!$A$2:$A$37,0)) -> Customer Support | D44: =INDEX(Employees!$N$2:$N$37,MATCH($A44,Employees!$A$2:$A$37,0)) -> 5

Sheet Supply Chain Analysis
A1: Supply Chain & Inventory Analysis
A2: Stock health, supplier performance and inventory movement
A4: Key Performance Indicators
A5: TOTAL SKUs | C5: SKUs AT/BELOW REORDER LEVEL | E5: TOTAL INVENTORY VALUE | G5: DISCONTINUED W/ STOCK
A6: =COUNTA(Products!A2:A101) -> 100 | C6: =COUNTIF(Products!M2:M101,"REORDER") -> 8 | E6: =SUM(Products!L2:L101) -> 3818708.3 | G6: =COUNTIFS(Products!I2:I101,TRUE(),Products!G2:G101,">0") -> 0
A8: TOTAL RESTOCK UNITS | C8: TOTAL DAMAGED UNITS | E8: AVG SUPPLIER LEAD TIME (days) | G8: AVG SUPPLIER RATING
A9: =SUMIF(InventoryTransactions!D2:D351,"Restock",InventoryTransactions!E2:E351) -> 29554 | C9: =-SUMIF(InventoryTransactions!D2:D351,"Damaged",InventoryTransactions!E2:E351) -> 1317 | E9: =AVERAGE(Suppliers!D2:D13) -> 22.833333 | G9: =AVERAGE(Suppliers!E2:E13) -> 3.8958333
A11: Reorder Alert — Stock At or Below Reorder Level
A12: Product ID | B12: Product Name | C12: Category | D12: Stock Qty | E12: Reorder Level | F12: Supplier
A13: 14 | B13: =INDEX(Products!$B$2:$B$101,MATCH($A13,Products!$A$2:$A$101,0)) -> Sticky Notes | C13: =INDEX(Products!$J$2:$J$101,MATCH($A13,Products!$A$2:$A$101,0)) -> Office Supplies | D13: =INDEX(Products!$G$2:$G$101,MATCH($A13,Products!$A$2:$A$101,0)) -> 13 | E13: =INDEX(Products!$H$2:$H$101,MATCH($A13,Products!$A$2:$A$101,0)) -> 79 | F13: =INDEX(Products!$K$2:$K$101,MATCH($A13,Products!$A$2:$A$101,0)) -> EastPoint Textiles
A14: 3 | B14: =INDEX(Products!$B$2:$B$101,MATCH($A14,Products!$A$2:$A$101,0)) -> USB-C Hub | C14: =INDEX(Products!$J$2:$J$101,MATCH($A14,Products!$A$2:$A$101,0)) -> Electronics | D14: =INDEX(Products!$G$2:$G$101,MATCH($A14,Products!$A$2:$A$101,0)) -> 14 | E14: =INDEX(Products!$H$2:$H$101,MATCH($A14,Products!$A$2:$A$101,0)) -> 44 | F14: =INDEX(Products!$K$2:$K$101,MATCH($A14,Products!$A$2:$A$101,0)) -> Zenith Materials
A15: 39 | B15: =INDEX(Products!$B$2:$B$101,MATCH($A15,Products!$A$2:$A$101,0)) -> Winter Gloves | C15: =INDEX(Products!$J$2:$J$101,MATCH($A15,Products!$A$2:$A$101,0)) -> Apparel | D15: =INDEX(Products!$G$2:$G$101,MATCH($A15,Products!$A$2:$A$101,0)) -> 27 | E15: =INDEX(Products!$H$2:$H$101,MATCH($A15,Products!$A$2:$A$101,0)) -> 29 | F15: =INDEX(Products!$K$2:$K$101,MATCH($A15,Products!$A$2:$A$101,0)) -> Zenith Materials
A16: 68 | B16: =INDEX(Products!$B$2:$B$101,MATCH($A16,Products!$A$2:$A$101,0)) -> Art Supply Kit | C16: =INDEX(Products!$J$2:$J$101,MATCH($A16,Products!$A$2:$A$101,0)) -> Toys & Games | D16: =INDEX(Products!$G$2:$G$101,MATCH($A16,Products!$A$2:$A$101,0)) -> 35 | E16: =INDEX(Products!$H$2:$H$101,MATCH($A16,Products!$A$2:$A$101,0)) -> 37 | F16: =INDEX(Products!$K$2:$K$101,MATCH($A16,Products!$A$2:$A$101,0)) -> Continental Fabrics
A17: 80 | B17: =INDEX(Products!$B$2:$B$101,MATCH($A17,Products!$A$2:$A$101,0)) -> Body Lotion | C17: =INDEX(Products!$J$2:$J$101,MATCH($A17,Products!$A$2:$A$101,0)) -> Health & Beauty | D17: =INDEX(Products!$G$2:$G$101,MATCH($A17,Products!$A$2:$A$101,0)) -> 35 | E17: =INDEX(Products!$H$2:$H$101,MATCH($A17,Products!$A$2:$A$101,0)) -> 35 | F17: =INDEX(Products!$K$2:$K$101,MATCH($A17,Products!$A$2:$A$101,0)) -> Zenith Materials
A18: 43 | B18: =INDEX(Products!$B$2:$B$101,MATCH($A18,Products!$A$2:$A$101,0)) -> Non-stick Pan Set | C18: =INDEX(Products!$J$2:$J$101,MATCH($A18,Products!$A$2:$A$101,0)) -> Home & Kitchen | D18: =INDEX(Products!$G$2:$G$101,MATCH($A18,Products!$A$2:$A$101,0)) -> 50 | E18: =INDEX(Products!$H$2:$H$101,MATCH($A18,Products!$A$2:$A$101,0)) -> 80 | F18: =INDEX(Products!$K$2:$K$101,MATCH($A18,Products!$A$2:$A$101,0)) -> Summit Hardware
A19: 16 | B19: =INDEX(Products!$B$2:$B$101,MATCH($A19,Products!$A$2:$A$101,0)) -> Whiteboard | C19: =INDEX(Products!$J$2:$J$101,MATCH($A19,Products!$A$2:$A$101,0)) -> Office Supplies | D19: =INDEX(Products!$G$2:$G$101,MATCH($A19,Products!$A$2:$A$101,0)) -> 52 | E19: =INDEX(Products!$H$2:$H$101,MATCH($A19,Products!$A$2:$A$101,0)) -> 64 | F19: =INDEX(Products!$K$2:$K$101,MATCH($A19,Products!$A$2:$A$101,0)) -> Summit Hardware
A20: 38 | B20: =INDEX(Products!$B$2:$B$101,MATCH($A20,Products!$A$2:$A$101,0)) -> Leather Belt | C20: =INDEX(Products!$J$2:$J$101,MATCH($A20,Products!$A$2:$A$101,0)) -> Apparel | D20: =INDEX(Products!$G$2:$G$101,MATCH($A20,Products!$A$2:$A$101,0)) -> 58 | E20: =INDEX(Products!$H$2:$H$101,MATCH($A20,Products!$A$2:$A$101,0)) -> 72 | F20: =INDEX(Products!$K$2:$K$101,MATCH($A20,Products!$A$2:$A$101,0)) -> Acme Manufacturing
A22: Supplier Performance Scorecard
A23: Supplier | B23: Country | C23: Lead Time (days) | D23: Rating | E23: Products Supplied | F23: Total Restock Qty
A24: =INDEX(Suppliers!$B$2:$B$13,MATCH(10,Suppliers!$A$2:$A$13,0)) -> Summit Hardware | B24: =INDEX(Suppliers!$C$2:$C$13,MATCH(10,Suppliers!$A$2:$A$13,0)) -> Poland | C24: =INDEX(Suppliers!$D$2:$D$13,MATCH(10,Suppliers!$A$2:$A$13,0)) -> 42 | D24: =INDEX(Suppliers!$E$2:$E$13,MATCH(10,Suppliers!$A$2:$A$13,0)) -> 4.88 | E24: =INDEX(Suppliers!$F$2:$F$13,MATCH(10,Suppliers!$A$2:$A$13,0)) -> 8 | F24: =INDEX(Suppliers!$G$2:$G$13,MATCH(10,Suppliers!$A$2:$A$13,0)) -> 3021
A25: =INDEX(Suppliers!$B$2:$B$13,MATCH(2,Suppliers!$A$2:$A$13,0)) -> Global Parts Ltd | B25: =INDEX(Suppliers!$C$2:$C$13,MATCH(2,Suppliers!$A$2:$A$13,0)) -> USA | C25: =INDEX(Suppliers!$D$2:$D$13,MATCH(2,Suppliers!$A$2:$A$13,0)) -> 25 | D25: =INDEX(Suppliers!$E$2:$E$13,MATCH(2,Suppliers!$A$2:$A$13,0)) -> 4.76 | E25: =INDEX(Suppliers!$F$2:$F$13,MATCH(2,Suppliers!$A$2:$A$13,0)) -> 11 | F25: =INDEX(Suppliers!$G$2:$G$13,MATCH(2,Suppliers!$A$2:$A$13,0)) -> 3607
A26: =INDEX(Suppliers!$B$2:$B$13,MATCH(11,Suppliers!$A$2:$A$13,0)) -> Redwood Electronics | B26: =INDEX(Suppliers!$C$2:$C$13,MATCH(11,Suppliers!$A$2:$A$13,0)) -> Taiwan | C26: =INDEX(Suppliers!$D$2:$D$13,MATCH(11,Suppliers!$A$2:$A$13,0)) -> 6 | D26: =INDEX(Suppliers!$E$2:$E$13,MATCH(11,Suppliers!$A$2:$A$13,0)) -> 4.68 | E26: =INDEX(Suppliers!$F$2:$F$13,MATCH(11,Suppliers!$A$2:$A$13,0)) -> 8 | F26: =INDEX(Suppliers!$G$2:$G$13,MATCH(11,Suppliers!$A$2:$A$13,0)) -> 2411
A27: =INDEX(Suppliers!$B$2:$B$13,MATCH(5,Suppliers!$A$2:$A$13,0)) -> Pacific Rim Supply | B27: =INDEX(Suppliers!$C$2:$C$13,MATCH(5,Suppliers!$A$2:$A$13,0)) -> India | C27: =INDEX(Suppliers!$D$2:$D$13,MATCH(5,Suppliers!$A$2:$A$13,0)) -> 14 | D27: =INDEX(Suppliers!$E$2:$E$13,MATCH(5,Suppliers!$A$2:$A$13,0)) -> 4.35 | E27: =INDEX(Suppliers!$F$2:$F$13,MATCH(5,Suppliers!$A$2:$A$13,0)) -> 12 | F27: =INDEX(Suppliers!$G$2:$G$13,MATCH(5,Suppliers!$A$2:$A$13,0)) -> 3359
A28: =INDEX(Suppliers!$B$2:$B$13,MATCH(7,Suppliers!$A$2:$A$13,0)) -> BrightPath Goods | B28: =INDEX(Suppliers!$C$2:$C$13,MATCH(7,Suppliers!$A$2:$A$13,0)) -> South Korea | C28: =INDEX(Suppliers!$D$2:$D$13,MATCH(7,Suppliers!$A$2:$A$13,0)) -> 26 | D28: =INDEX(Suppliers!$E$2:$E$13,MATCH(7,Suppliers!$A$2:$A$13,0)) -> 3.99 | E28: =INDEX(Suppliers!$F$2:$F$13,MATCH(7,Suppliers!$A$2:$A$13,0)) -> 12 | F28: =INDEX(Suppliers!$G$2:$G$13,MATCH(7,Suppliers!$A$2:$A$13,0)) -> 3282
A29: =INDEX(Suppliers!$B$2:$B$13,MATCH(6,Suppliers!$A$2:$A$13,0)) -> Ironwood Industries | B29: =INDEX(Suppliers!$C$2:$C$13,MATCH(6,Suppliers!$A$2:$A$13,0)) -> Mexico | C29: =INDEX(Suppliers!$D$2:$D$13,MATCH(6,Suppliers!$A$2:$A$13,0)) -> 9 | D29: =INDEX(Suppliers!$E$2:$E$13,MATCH(6,Suppliers!$A$2:$A$13,0)) -> 3.71 | E29: =INDEX(Suppliers!$F$2:$F$13,MATCH(6,Suppliers!$A$2:$A$13,0)) -> 3 | F29: =INDEX(Suppliers!$G$2:$G$13,MATCH(6,Suppliers!$A$2:$A$13,0)) -> 872
A30: =INDEX(Suppliers!$B$2:$B$13,MATCH(9,Suppliers!$A$2:$A$13,0)) -> Continental Fabrics | B30: =INDEX(Suppliers!$C$2:$C$13,MATCH(9,Suppliers!$A$2:$A$13,0)) -> Turkey | C30: =INDEX(Suppliers!$D$2:$D$13,MATCH(9,Suppliers!$A$2:$A$13,0)) -> 31 | D30: =INDEX(Suppliers!$E$2:$E$13,MATCH(9,Suppliers!$A$2:$A$13,0)) -> 3.66 | E30: =INDEX(Suppliers!$F$2:$F$13,MATCH(9,Suppliers!$A$2:$A$13,0)) -> 4 | F30: =INDEX(Suppliers!$G$2:$G$13,MATCH(9,Suppliers!$A$2:$A$13,0)) -> 805
A31: =INDEX(Suppliers!$B$2:$B$13,MATCH(4,Suppliers!$A$2:$A$13,0)) -> Nordic Components | B31: =INDEX(Suppliers!$C$2:$C$13,MATCH(4,Suppliers!$A$2:$A$13,0)) -> Vietnam | C31: =INDEX(Suppliers!$D$2:$D$13,MATCH(4,Suppliers!$A$2:$A$13,0)) -> 19 | D31: =INDEX(Suppliers!$E$2:$E$13,MATCH(4,Suppliers!$A$2:$A$13,0)) -> 3.64 | E31: =INDEX(Suppliers!$F$2:$F$13,MATCH(4,Suppliers!$A$2:$A$13,0)) -> 7 | F31: =INDEX(Suppliers!$G$2:$G$13,MATCH(4,Suppliers!$A$2:$A$13,0)) -> 3645
A32: =INDEX(Suppliers!$B$2:$B$13,MATCH(12,Suppliers!$A$2:$A$13,0)) -> Falcon Packaging | B32: =INDEX(Suppliers!$C$2:$C$13,MATCH(12,Suppliers!$A$2:$A$13,0)) -> Canada | C32: =INDEX(Suppliers!$D$2:$D$13,MATCH(12,Suppliers!$A$2:$A$13,0)) -> 41 | D32: =INDEX(Suppliers!$E$2:$E$13,MATCH(12,Suppliers!$A$2:$A$13,0)) -> 3.64 | E32: =INDEX(Suppliers!$F$2:$F$13,MATCH(12,Suppliers!$A$2:$A$13,0)) -> 11 | F32: =INDEX(Suppliers!$G$2:$G$13,MATCH(12,Suppliers!$A$2:$A$13,0)) -> 2662
A33: =INDEX(Suppliers!$B$2:$B$13,MATCH(1,Suppliers!$A$2:$A$13,0)) -> Acme Manufacturing | B33: =INDEX(Suppliers!$C$2:$C$13,MATCH(1,Suppliers!$A$2:$A$13,0)) -> China | C33: =INDEX(Suppliers!$D$2:$D$13,MATCH(1,Suppliers!$A$2:$A$13,0)) -> 20 | D33: =INDEX(Suppliers!$E$2:$E$13,MATCH(1,Suppliers!$A$2:$A$13,0)) -> 3.4 | E33: =INDEX(Suppliers!$F$2:$F$13,MATCH(1,Suppliers!$A$2:$A$13,0)) -> 9 | F33: =INDEX(Suppliers!$G$2:$G$13,MATCH(1,Suppliers!$A$2:$A$13,0)) -> 2613
A34: =INDEX(Suppliers!$B$2:$B$13,MATCH(3,Suppliers!$A$2:$A$13,0)) -> EastPoint Textiles | B34: =INDEX(Suppliers!$C$2:$C$13,MATCH(3,Suppliers!$A$2:$A$13,0)) -> Germany | C34: =INDEX(Suppliers!$D$2:$D$13,MATCH(3,Suppliers!$A$2:$A$13,0)) -> 10 | D34: =INDEX(Suppliers!$E$2:$E$13,MATCH(3,Suppliers!$A$2:$A$13,0)) -> 3.1 | E34: =INDEX(Suppliers!$F$2:$F$13,MATCH(3,Suppliers!$A$2:$A$13,0)) -> 3 | F34: =INDEX(Suppliers!$G$2:$G$13,MATCH(3,Suppliers!$A$2:$A$13,0)) -> 334
A35: =INDEX(Suppliers!$B$2:$B$13,MATCH(8,Suppliers!$A$2:$A$13,0)) -> Zenith Materials | B35: =INDEX(Suppliers!$C$2:$C$13,MATCH(8,Suppliers!$A$2:$A$13,0)) -> Italy | C35: =INDEX(Suppliers!$D$2:$D$13,MATCH(8,Suppliers!$A$2:$A$13,0)) -> 31 | D35: =INDEX(Suppliers!$E$2:$E$13,MATCH(8,Suppliers!$A$2:$A$13,0)) -> 2.94 | E35: =INDEX(Suppliers!$F$2:$F$13,MATCH(8,Suppliers!$A$2:$A$13,0)) -> 12 | F35: =INDEX(Suppliers!$G$2:$G$13,MATCH(8,Suppliers!$A$2:$A$13,0)) -> 2943
A37: Inventory Movement by Transaction Type
A38: Transaction Type | B38: Transaction Count | C38: Total Units
A39: Restock | B39: =COUNTIF(InventoryTransactions!$D$2:$D$351,$A39) -> 169 | C39: =SUMIF(InventoryTransactions!$D$2:$D$351,$A39,InventoryTransactions!$E$2:$E$351) -> 29554
A40: Sale | B40: =COUNTIF(InventoryTransactions!$D$2:$D$351,$A40) -> 51 | C40: =SUMIF(InventoryTransactions!$D$2:$D$351,$A40,InventoryTransactions!$E$2:$E$351) -> -1161
A41: Return | B41: =COUNTIF(InventoryTransactions!$D$2:$D$351,$A41) -> 0 | C41: =SUMIF(InventoryTransactions!$D$2:$D$351,$A41,InventoryTransactions!$E$2:$E$351) -> 0
A42: Adjustment | B42: =COUNTIF(InventoryTransactions!$D$2:$D$351,$A42) -> 68 | C42: =SUMIF(InventoryTransactions!$D$2:$D$351,$A42,InventoryTransactions!$E$2:$E$351) -> -1554
A43: Damaged | B43: =COUNTIF(InventoryTransactions!$D$2:$D$351,$A43) -> 62 | C43: =SUMIF(InventoryTransactions!$D$2:$D$351,$A43,InventoryTransactions!$E$2:$E$351) -> -1317
A45: Inventory Value & Sell-Through by Category
A46: Category | B46: Inventory Value | C46: Units Sold (YTD all) | D46: Sell-Through Ratio
A47: =INDEX(Categories!$B$2:$B$11,MATCH("Sporting Goods",Categories!$B$2:$B$11,0)) -> Sporting Goods | B47: =INDEX(Categories!$F$2:$F$11,MATCH($A47,Categories!$B$2:$B$11,0)) -> 517487.33 | C47: =INDEX(Categories!$D$2:$D$11,MATCH($A47,Categories!$B$2:$B$11,0)) -> 757 | D47: =IFERROR(C47/(SUMIF(Products!$J$2:$J$101,$A47,Products!$G$2:$G$101)+C47),0) -> 0.21366074
A48: =INDEX(Categories!$B$2:$B$11,MATCH("Apparel",Categories!$B$2:$B$11,0)) -> Apparel | B48: =INDEX(Categories!$F$2:$F$11,MATCH($A48,Categories!$B$2:$B$11,0)) -> 342078.09 | C48: =INDEX(Categories!$D$2:$D$11,MATCH($A48,Categories!$B$2:$B$11,0)) -> 794 | D48: =IFERROR(C48/(SUMIF(Products!$J$2:$J$101,$A48,Products!$G$2:$G$101)+C48),0) -> 0.28747285
A49: =INDEX(Categories!$B$2:$B$11,MATCH("Office Supplies",Categories!$B$2:$B$11,0)) -> Office Supplies | B49: =INDEX(Categories!$F$2:$F$11,MATCH($A49,Categories!$B$2:$B$11,0)) -> 494090.55 | C49: =INDEX(Categories!$D$2:$D$11,MATCH($A49,Categories!$B$2:$B$11,0)) -> 666 | D49: =IFERROR(C49/(SUMIF(Products!$J$2:$J$101,$A49,Products!$G$2:$G$101)+C49),0) -> 0.19170984
A50: =INDEX(Categories!$B$2:$B$11,MATCH("Electronics",Categories!$B$2:$B$11,0)) -> Electronics | B50: =INDEX(Categories!$F$2:$F$11,MATCH($A50,Categories!$B$2:$B$11,0)) -> 474429.85 | C50: =INDEX(Categories!$D$2:$D$11,MATCH($A50,Categories!$B$2:$B$11,0)) -> 711 | D50: =IFERROR(C50/(SUMIF(Products!$J$2:$J$101,$A50,Products!$G$2:$G$101)+C50),0) -> 0.20454545
A51: =INDEX(Categories!$B$2:$B$11,MATCH("Groceries",Categories!$B$2:$B$11,0)) -> Groceries | B51: =INDEX(Categories!$F$2:$F$11,MATCH($A51,Categories!$B$2:$B$11,0)) -> 343753.31 | C51: =INDEX(Categories!$D$2:$D$11,MATCH($A51,Categories!$B$2:$B$11,0)) -> 710 | D51: =IFERROR(C51/(SUMIF(Products!$J$2:$J$101,$A51,Products!$G$2:$G$101)+C51),0) -> 0.22001859
A52: =INDEX(Categories!$B$2:$B$11,MATCH("Health & Beauty",Categories!$B$2:$B$11,0)) -> Health & Beauty | B52: =INDEX(Categories!$F$2:$F$11,MATCH($A52,Categories!$B$2:$B$11,0)) -> 466264.94 | C52: =INDEX(Categories!$D$2:$D$11,MATCH($A52,Categories!$B$2:$B$11,0)) -> 638 | D52: =IFERROR(C52/(SUMIF(Products!$J$2:$J$101,$A52,Products!$G$2:$G$101)+C52),0) -> 0.17493831
A53: =INDEX(Categories!$B$2:$B$11,MATCH("Automotive Parts",Categories!$B$2:$B$11,0)) -> Automotive Parts | B53: =INDEX(Categories!$F$2:$F$11,MATCH($A53,Categories!$B$2:$B$11,0)) -> 359871.16 | C53: =INDEX(Categories!$D$2:$D$11,MATCH($A53,Categories!$B$2:$B$11,0)) -> 654 | D53: =IFERROR(C53/(SUMIF(Products!$J$2:$J$101,$A53,Products!$G$2:$G$101)+C53),0) -> 0.21219987
A54: =INDEX(Categories!$B$2:$B$11,MATCH("Furniture",Categories!$B$2:$B$11,0)) -> Furniture | B54: =INDEX(Categories!$F$2:$F$11,MATCH($A54,Categories!$B$2:$B$11,0)) -> 374937.3 | C54: =INDEX(Categories!$D$2:$D$11,MATCH($A54,Categories!$B$2:$B$11,0)) -> 621 | D54: =IFERROR(C54/(SUMIF(Products!$J$2:$J$101,$A54,Products!$G$2:$G$101)+C54),0) -> 0.20583361
A55: =INDEX(Categories!$B$2:$B$11,MATCH("Home & Kitchen",Categories!$B$2:$B$11,0)) -> Home & Kitchen | B55: =INDEX(Categories!$F$2:$F$11,MATCH($A55,Categories!$B$2:$B$11,0)) -> 246239.51 | C55: =INDEX(Categories!$D$2:$D$11,MATCH($A55,Categories!$B$2:$B$11,0)) -> 710 | D55: =IFERROR(C55/(SUMIF(Products!$J$2:$J$101,$A55,Products!$G$2:$G$101)+C55),0) -> 0.22910616
A56: =INDEX(Categories!$B$2:$B$11,MATCH("Toys & Games",Categories!$B$2:$B$11,0)) -> Toys & Games | B56: =INDEX(Categories!$F$2:$F$11,MATCH($A56,Categories!$B$2:$B$11,0)) -> 199556.26 | C56: =INDEX(Categories!$D$2:$D$11,MATCH($A56,Categories!$B$2:$B$11,0)) -> 641 | D56: =IFERROR(C56/(SUMIF(Products!$J$2:$J$101,$A56,Products!$G$2:$G$101)+C56),0) -> 0.22187608

Sheet Departments
A1: Retail & Distribution Co. Executive Dashboard | B1: department name | C1: budget | D1: Headcount | E1: Total Salary Cost | F1: Budget Variance | G1: Budget Utilization %
A2: Sales · Finance · HR · Supply Chain | B2: Sales | C2: 500000 | D2: =COUNTIF(Employees!$E$2:$E$37,A2) -> 0 | E2: =SUMIF(Employees!$E$2:$E$37,A2,Employees!$I$2:$I$37) -> 0 | F2: =C2-E2 -> 500000 | G2: =IFERROR(E2/C2,0) -> 0
A3: 2 | B3: Marketing | C3: 250000 | D3: =COUNTIF(Employees!$E$2:$E$37,A3) -> 4 | E3: =SUMIF(Employees!$E$2:$E$37,A3,Employees!$I$2:$I$37) -> 355891.84 | F3: =C3-E3 -> -105891.84 | G3: =IFERROR(E3/C3,0) -> 1.4235674
A4: 3 | B4: Finance | C4: 300000 | D4: =COUNTIF(Employees!$E$2:$E$37,A4) -> 6 | E4: =SUMIF(Employees!$E$2:$E$37,A4,Employees!$I$2:$I$37) -> 458531.52 | F4: =C4-E4 -> -158531.52 | G4: =IFERROR(E4/C4,0) -> 1.5284384
A5: 4 | B5: Operations | C5: 450000 | D5: =COUNTIF(Employees!$E$2:$E$37,A5) -> 4 | E5: =SUMIF(Employees!$E$2:$E$37,A5,Employees!$I$2:$I$37) -> 338462.72 | F5: =C5-E5 -> 111537.28 | G5: =IFERROR(E5/C5,0) -> 0.75213938
A6: 5 | B6: Human Resources | C6: 150000 | D6: =COUNTIF(Employees!$E$2:$E$37,A6) -> 6 | E6: =SUMIF(Employees!$E$2:$E$37,A6,Employees!$I$2:$I$37) -> 477814.43 | F6: =C6-E6 -> -327814.43 | G6: =IFERROR(E6/C6,0) -> 3.1854295
A7: 6 | B7: IT | C7: 350000 | D7: =COUNTIF(Employees!$E$2:$E$37,A7) -> 6 | E7: =SUMIF(Employees!$E$2:$E$37,A7,Employees!$I$2:$I$37) -> 431307.33 | F7: =C7-E7 -> -81307.33 | G7: =IFERROR(E7/C7,0) -> 1.2323067
A8: 7 | B8: Customer Support | C8: 200000 | D8: =COUNTIF(Employees!$E$2:$E$37,A8) -> 6 | E8: =SUMIF(Employees!$E$2:$E$37,A8,Employees!$I$2:$I$37) -> 508330.64 | F8: =C8-E8 -> -308330.64 | G8: =IFERROR(E8/C8,0) -> 2.5416532
A12: Chart Data

Sheet Employees
A1: employee id | B1: first name | C1: last name | D1: email | E1: department id | F1: manager id | G1: job title | H1: hire date | I1: salary | J1: region | K1: Department Name | L1: Tenure (Years) | M1: Manager Name | N1: Direct Reports | O1: Orders Handled | P1: Revenue Generated
A2: 1 | B2: Daniel | C2: Brown | D2: daniel.brown1@company.com | E2: 1 | G2: Account Executive | H2: 2015-02-21 | I2: 118369.77 | J2: Europe | K2: =IFERROR(INDEX(Departments!$B$2:$B$8,MATCH(E2,Departments!$A$2:$A$8,0)),"Unassigned") -> Unassigned | L2: =ROUND((TODAY()-H2)/365.25,1) -> 11.5 | M2: =IFERROR(INDEX($B$2:$B$37,MATCH(F2,$A$2:$A$37,0))&" "&INDEX($C$2:$C$37,MATCH(F2,$A$2:$A$37,0)),"(Top Level)") -> (Top Level) | N2: =COUNTIF($F$2:$F$37,A2) -> 3 | O2: =COUNTIF(Orders!$C$2:$C$401,A2) -> 89 | P2: =SUMIF(Orders!$C$2:$C$401,A2,Orders!$H$2:$H$401) -> 377581.84
A3: 2 | B3: Linda | C3: Jones | D3: linda.jones2@company.com | E3: 2 | G3: SEO Analyst | H3: 2015-07-29 | I3: 115451.48 | J3: Middle East | K3: =IFERROR(INDEX(Departments!$B$2:$B$8,MATCH(E3,Departments!$A$2:$A$8,0)),"Unassigned") -> Marketing | L3: =ROUND((TODAY()-H3)/365.25,1) -> 11.1 | M3: =IFERROR(INDEX($B$2:$B$37,MATCH(F3,$A$2:$A$37,0))&" "&INDEX($C$2:$C$37,MATCH(F3,$A$2:$A$37,0)),"(Top Level)") -> (Top Level) | N3: =COUNTIF($F$2:$F$37,A3) -> 3 | O3: =COUNTIF(Orders!$C$2:$C$401,A3) -> 0 | P3: =SUMIF(Orders!$C$2:$C$401,A3,Orders!$H$2:$H$401) -> 0
A4: 3 | B4: John | C4: Jackson | D4: john.jackson3@company.com | E4: 3 | G4: Controller | H4: 2017-05-14 | I4: 86430.22 | J4: North America | K4: =IFERROR(INDEX(Departments!$B$2:$B$8,MATCH(E4,Departments!$A$2:$A$8,0)),"Unassigned") -> Finance | L4: =ROUND((TODAY()-H4)/365.25,1) -> 9.3 | M4: =IFERROR(INDEX($B$2:$B$37,MATCH(F4,$A$2:$A$37,0))&" "&INDEX($C$2:$C$37,MATCH(F4,$A$2:$A$37,0)),"(Top Level)") -> (Top Level) | N4: =COUNTIF($F$2:$F$37,A4) -> 5 | O4: =COUNTIF(Orders!$C$2:$C$401,A4) -> 0 | P4: =SUMIF(Orders!$C$2:$C$401,A4,Orders!$H$2:$H$401) -> 0
A5: 4 | B5: Michael | C5: Davis | D5: michael.davis4@company.com | E5: 4 | G5: Warehouse Supervisor | H5: 2017-10-31 | I5: 112090.84 | J5: Middle East | K5: =IFERROR(INDEX(Departments!$B$2:$B$8,MATCH(E5,Departments!$A$2:$A$8,0)),"Unassigned") -> Operations | L5: =ROUND((TODAY()-H5)/365.25,1) -> 8.9 | M5: =IFERROR(INDEX($B$2:$B$37,MATCH(F5,$A$2:$A$37,0))&" "&INDEX($C$2:$C$37,MATCH(F5,$A$2:$A$37,0)),"(Top Level)") -> (Top Level) | N5: =COUNTIF($F$2:$F$37,A5) -> 3 | O5: =COUNTIF(Orders!$C$2:$C$401,A5) -> 0 | P5: =SUMIF(Orders!$C$2:$C$401,A5,Orders!$H$2:$H$401) -> 0
A6: 5 | B6: Michael | C6: Moore | D6: michael.moore5@company.com | E6: 5 | G6: HR Manager | H6: 2017-05-09 | I6: 94919.83 | J6: Middle East | K6: =IFERROR(INDEX(Departments!$B$2:$B$8,MATCH(E6,Departments!$A$2:$A$8,0)),"Unassigned") -> Human Resources | L6: =ROUND((TODAY()-H6)/365.25,1) -> 9.3 | M6: =IFERROR(INDEX($B$2:$B$37,MATCH(F6,$A$2:$A$37,0))&" "&INDEX($C$2:$C$37,MATCH(F6,$A$2:$A$37,0)),"(Top Level)") -> (Top Level) | N6: =COUNTIF($F$2:$F$37,A6) -> 5 | O6: =COUNTIF(Orders!$C$2:$C$401,A6) -> 0 | P6: =SUMIF(Orders!$C$2:$C$401,A6,Orders!$H$2:$H$401) -> 0
A7: 6 | B7: William | C7: Smith | D7: william.smith6@company.com | E7: 6 | G7: IT Manager | H7: 2015-11-23 | I7: 116416.27 | J7: Asia Pacific | K7: =IFERROR(INDEX(Departments!$B$2:$B$8,MATCH(E7,Departments!$A$2:$A$8,0)),"Unassigned") -> IT | L7: =ROUND((TODAY()-H7)/365.25,1) -> 10.8 | M7: =IFERROR(INDEX($B$2:$B$37,MATCH(F7,$A$2:$A$37,0))&" "&INDEX($C$2:$C$37,MATCH(F7,$A$2:$A$37,0)),"(Top Level)") -> (Top Level) | N7: =COUNTIF($F$2:$F$37,A7) -> 5 | O7: =COUNTIF(Orders!$C$2:$C$401,A7) -> 0 | P7: =SUMIF(Orders!$C$2:$C$401,A7,Orders!$H$2:$H$401) -> 0
A8: 7 | B8: William | C8: Jones | D8: william.jones7@company.com | E8: 7 | G8: Customer Success Manager | H8: 2016-03-16 | I8: 128074.59 | J8: Asia Pacific | K8: =IFERROR(INDEX(Departments!$B$2:$B$8,MATCH(E8,Departments!$A$2:$A$8,0)),"Unassigned") -> Customer Support | L8: =ROUND((TODAY()-H8)/365.25,1) -> 10.5 | M8: =IFERROR(INDEX($B$2:$B$37,MATCH(F8,$A$2:$A$37,0))&" "&INDEX($C$2:$C$37,MATCH(F8,$A$2:$A$37,0)),"(Top Level)") -> (Top Level) | N8: =COUNTIF($F$2:$F$37,A8) -> 5 | O8: =COUNTIF(Orders!$C$2:$C$401,A8) -> 0 | P8: =SUMIF(Orders!$C$2:$C$401,A8,Orders!$H$2:$H$401) -> 0
A9: 8 | B9: John | C9: Gonzalez | D9: john.gonzalez8@company.com | E9: 1 | F9: 1 | G9: Senior Sales Rep | H9: 2017-01-31 | I9: 87374.72 | J9: Middle East | K9: =IFERROR(INDEX(Departments!$B$2:$B$8,MATCH(E9,Departments!$A$2:$A$8,0)),"Unassigned") -> Unassigned | L9: =ROUND((TODAY()-H9)/365.25,1) -> 9.6 | M9: =IFERROR(INDEX($B$2:$B$37,MATCH(F9,$A$2:$A$37,0))&" "&INDEX($C$2:$C$37,MATCH(F9,$A$2:$A$37,0)),"(Top Level)") -> Daniel Brown | N9: =COUNTIF($F$2:$F$37,A9) -> 0 | O9: =COUNTIF(Orders!$C$2:$C$401,A9) -> 115 | P9: =SUMIF(Orders!$C$2:$C$401,A9,Orders!$H$2:$H$401) -> 497216.81
A10: 9 | B10: William | C10: Johnson | D10: william.johnson9@company.com | E10: 1 | F10: 1 | G10: Sales Manager | H10: 2024-03-07 | I10: 71811.4 | J10: Latin America | K10: =IFERROR(INDEX(Departments!$B$2:$B$8,MATCH(E10,Departments!$A$2:$A$8,0)),"Unassigned") -> Unassigned | L10: =ROUND((TODAY()-H10)/365.25,1) -> 2.5 | M10: =IFERROR(INDEX($B$2:$B$37,MATCH(F10,$A$2:$A$37,0))&" "&INDEX($C$2:$C$37,MATCH(F10,$A$2:$A$37,0)),"(Top Level)") -> Daniel Brown | N10: =COUNTIF($F$2:$F$37,A10) -> 0 | O10: =COUNTIF(Orders!$C$2:$C$401,A10) -> 93 | P10: =SUMIF(Orders!$C$2:$C$401,A10,Orders!$H$2:$H$401) -> 419101.89
A11: 10 | B11: John | C11: Moore | D11: john.moore10@company.com | E11: 1 | F11: 1 | G11: Senior Sales Rep | H11: 2019-04-15 | I11: 73867.61 | J11: North America | K11: =IFERROR(INDEX(Departments!$B$2:$B$8,MATCH(E11,Departments!$A$2:$A$8,0)),"Unassigned") -> Unassigned | L11: =ROUND((TODAY()-H11)/365.25,1) -> 7.4 | M11: =IFERROR(INDEX($B$2:$B$37,MATCH(F11,$A$2:$A$37,0))&" "&INDEX($C$2:$C$37,MATCH(F11,$A$2:$A$37,0)),"(Top Level)") -> Daniel Brown | N11: =COUNTIF($F$2:$F$37,A11) -> 0 | O11: =COUNTIF(Orders!$C$2:$C$401,A11) -> 103 | P11: =SUMIF(Orders!$C$2:$C$401,A11,Orders!$H$2:$H$401) -> 461776.55
A12: 11 | B12: Nancy | C12: Davis | D12: nancy.davis11@company.com | E12: 2 | F12: 2 | G12: Content Strategist | H12: 2024-09-01 | I12: 94261.08 | J12: Europe | K12: =IFERROR(INDEX(Departments!$B$2:$B$8,MATCH(E12,Departments!$A$2:$A$8,0)),"Unassigned") -> Marketing | L12: =ROUND((TODAY()-H12)/365.25,1) -> 2 | M12: =IFERROR(INDEX($B$2:$B$37,MATCH(F12,$A$2:$A$37,0))&" "&INDEX($C$2:$C$37,MATCH(F12,$A$2:$A$37,0)),"(Top Level)") -> Linda Jones | N12: =COUNTIF($F$2:$F$37,A12) -> 0 | O12: =COUNTIF(Orders!$C$2:$C$401,A12) -> 0 | P12: =SUMIF(Orders!$C$2:$C$401,A12,Orders!$H$2:$H$401) -> 0
A13: 12 | B13: Margaret | C13: Brown | D13: margaret.brown12@company.com | E13: 2 | F13: 2 | G13: Content Strategist | H13: 2020-04-05 | I13: 67670.52 | J13: Asia Pacific | K13: =IFERROR(INDEX(Departments!$B$2:$B$8,MATCH(E13,Departments!$A$2:$A$8,0)),"Unassigned") -> Marketing | L13: =ROUND((TODAY()-H13)/365.25,1) -> 6.4 | M13: =IFERROR(INDEX($B$2:$B$37,MATCH(F13,$A$2:$A$37,0))&" "&INDEX($C$2:$C$37,MATCH(F13,$A$2:$A$37,0)),"(Top Level)") -> Linda Jones | N13: =COUNTIF($F$2:$F$37,A13) -> 0 | O13: =COUNTIF(Orders!$C$2:$C$401,A13) -> 0 | P13: =SUMIF(Orders!$C$2:$C$401,A13,Orders!$H$2:$H$401) -> 0
A14: 13 | B14: Jennifer | C14: Lopez | D14: jennifer.lopez13@company.com | E14: 2 | F14: 2 | G14: Marketing Specialist | H14: 2019-12-26 | I14: 78508.76 | J14: North America | K14: =IFERROR(INDEX(Departments!$B$2:$B$8,MATCH(E14,Departments!$A$2:$A$8,0)),"Unassigned") -> Marketing | L14: =ROUND((TODAY()-H14)/365.25,1) -> 6.7 | M14: =IFERROR(INDEX($B$2:$B$37,MATCH(F14,$A$2:$A$37,0))&" "&INDEX($C$2:$C$37,MATCH(F14,$A$2:$A$37,0)),"(Top Level)") -> Linda Jones | N14: =COUNTIF($F$2:$F$37,A14) -> 0 | O14: =COUNTIF(Orders!$C$2:$C$401,A14) -> 0 | P14: =SUMIF(Orders!$C$2:$C$401,A14,Orders!$H$2:$H$401) -> 0
A15: 14 | B15: Daniel | C15: Garcia | D15: daniel.garcia14@company.com | E15: 3 | F15: 3 | G15: Finance Manager | H15: 2021-12-27 | I15: 57240.55 | J15: Latin America | K15: =IFERROR(INDEX(Departments!$B$2:$B$8,MATCH(E15,Departments!$A$2:$A$8,0)),"Unassigned") -> Finance | L15: =ROUND((TODAY()-H15)/365.25,1) -> 4.7 | M15: =IFERROR(INDEX($B$2:$B$37,MATCH(F15,$A$2:$A$37,0))&" "&INDEX($C$2:$C$37,MATCH(F15,$A$2:$A$37,0)),"(Top Level)") -> John Jackson | N15: =COUNTIF($F$2:$F$37,A15) -> 0 | O15: =COUNTIF(Orders!$C$2:$C$401,A15) -> 0 | P15: =SUMIF(Orders!$C$2:$C$401,A15,Orders!$H$2:$H$401) -> 0
A16: 15 | B16: Richard | C16: Rodriguez | D16: richard.rodriguez15@company.com | E16: 3 | F16: 3 | G16: Finance Manager | H16: 2023-03-06 | I16: 72847.49 | J16: Asia Pacific | K16: =IFERROR(INDEX(Departments!$B$2:$B$8,MATCH(E16,Departments!$A$2:$A$8,0)),"Unassigned") -> Finance | L16: =ROUND((TODAY()-H16)/365.25,1) -> 3.5 | M16: =IFERROR(INDEX($B$2:$B$37,MATCH(F16,$A$2:$A$37,0))&" "&INDEX($C$2:$C$37,MATCH(F16,$A$2:$A$37,0)),"(Top Level)") -> John Jackson | N16: =COUNTIF($F$2:$F$37,A16) -> 0 | O16: =COUNTIF(Orders!$C$2:$C$401,A16) -> 0 | P16: =SUMIF(Orders!$C$2:$C$401,A16,Orders!$H$2:$H$401) -> 0
A17: 16 | B17: Mark | C17: Johnson | D17: mark.johnson16@company.com | E17: 3 | F17: 3 | G17: Financial Analyst | H17: 2018-07-27 | I17: 85252.29 | J17: Latin America | K17: =IFERROR(INDEX(Departments!$B$2:$B$8,MATCH(E17,Departments!$A$2:$A$8,0)),"Unassigned") -> Finance | L17: =ROUND((TODAY()-H17)/365.25,1) -> 8.1 | M17: =IFERROR(INDEX($B$2:$B$37,MATCH(F17,$A$2:$A$37,0))&" "&INDEX($C$2:$C$37,MATCH(F17,$A$2:$A$37,0)),"(Top Level)") -> John Jackson | N17: =COUNTIF($F$2:$F$37,A17) -> 0 | O17: =COUNTIF(Orders!$C$2:$C$401,A17) -> 0 | P17: =SUMIF(Orders!$C$2:$C$401,A17,Orders!$H$2:$H$401) -> 0
A18: 17 | B18: William | C18: Williams | D18: william.williams17@company.com | E18: 3 | F18: 3 | G18: Finance Manager | H18: 2018-05-14 | I18: 88818.38 | J18: Asia Pacific | K18: =IFERROR(INDEX(Departments!$B$2:$B$8,MATCH(E18,Departments!$A$2:$A$8,0)),"Unassigned") -> Finance | L18: =ROUND((TODAY()-H18)/365.25,1) -> 8.3 | M18: =IFERROR(INDEX($B$2:$B$37,MATCH(F18,$A$2:$A$37,0))&" "&INDEX($C$2:$C$37,MATCH(F18,$A$2:$A$37,0)),"(Top Level)") -> John Jackson | N18: =COUNTIF($F$2:$F$37,A18) -> 0 | O18: =COUNTIF(Orders!$C$2:$C$401,A18) -> 0 | P18: =SUMIF(Orders!$C$2:$C$401,A18,Orders!$H$2:$H$401) -> 0
A19: 18 | B19: Michael | C19: Thomas | D19: michael.thomas18@company.com | E19: 3 | F19: 3 | G19: Finance Manager | H19: 2020-06-08 | I19: 67942.59 | J19: Asia Pacific | K19: =IFERROR(INDEX(Departments!$B$2:$B$8,MATCH(E19,Departments!$A$2:$A$8,0)),"Unassigned") -> Finance | L19: =ROUND((TODAY()-H19)/365.25,1) -> 6.3 | M19: =IFERROR(INDEX($B$2:$B$37,MATCH(F19,$A$2:$A$37,0))&" "&INDEX($C$2:$C$37,MATCH(F19,$A$2:$A$37,0)),"(Top Level)") -> John Jackson | N19: =COUNTIF($F$2:$F$37,A19) -> 0 | O19: =COUNTIF(Orders!$C$2:$C$401,A19) -> 0 | P19: =SUMIF(Orders!$C$2:$C$401,A19,Orders!$H$2:$H$401) -> 0
A20: 19 | B20: Linda | C20: Moore | D20: linda.moore19@company.com | E20: 4 | F20: 4 | G20: Logistics Coordinator | H20: 2022-01-16 | I20: 82350.69 | J20: Latin America | K20: =IFERROR(INDEX(Departments!$B$2:$B$8,MATCH(E20,Departments!$A$2:$A$8,0)),"Unassigned") -> Operations | L20: =ROUND((TODAY()-H20)/365.25,1) -> 4.6 | M20: =IFERROR(INDEX($B$2:$B$37,MATCH(F20,$A$2:$A$37,0))&" "&INDEX($C$2:$C$37,MATCH(F20,$A$2:$A$37,0)),"(Top Level)") -> Michael Davis | N20: =COUNTIF($F$2:$F$37,A20) -> 0 | O20: =COUNTIF(Orders!$C$2:$C$401,A20) -> 0 | P20: =SUMIF(Orders!$C$2:$C$401,A20,Orders!$H$2:$H$401) -> 0
... A37: 36 | B37: John | C37: Johnson | D37: john.johnson36@company.com | E37: 7 | F37: 7 | G37: Support Agent | H37: 2018-07-26 | I37: 90271 | J37: Asia Pacific | K37: =IFERROR(INDEX(Departments!$B$2:$B$8,MATCH(E37,Departments!$A$2:$A$8,0)),"Unassigned") -> Customer Support | L37: =ROUND((TODAY()-H37)/365.25,1) -> 8.1 | M37: =IFERROR(INDEX($B$2:$B$37,MATCH(F37,$A$2:$A$37,0))&" "&INDEX($C$2:$C$37,MATCH(F37,$A$2:$A$37,0)),"(Top Level)") -> William Jones | N37: =COUNTIF($F$2:$F$37,A37) -> 0 | O37: =COUNTIF(Orders!$C$2:$C$401,A37) -> 0 | P37: =SUMIF(Orders!$C$2:$C$401,A37,Orders!$H$2:$H$401) -> 0

Sheet Customers
A1: customer_id | B1: company name | C1: contact name | D1: email | E1: country | F1: city | G1: segment | H1: signup date | I1: Total Orders | J1: Total Revenue | K1: Avg Order Value
A2: 1 | B2: Summit Industries | C2: Linda Rodriguez | D2: linda.rodriguez1@example.com | E2: Italy | F2: Milan | G2: Corporate | H2: 2021-05-27 | I2: =COUNTIF(Orders!$B$2:$B$401,A2) -> 5 | J2: =SUMIF(Orders!$B$2:$B$401,A2,Orders!$H$2:$H$401) -> 30053.016 | K2: =IFERROR(J2/I2,0) -> 6010.6032
A3: 2 | B3: Ironclad Logistics | C3: Lisa Jackson | D3: lisa.jackson2@example.com | E3: UAE | F3: Dubai | G3: Corporate | H3: 2021-09-22 | I3: =COUNTIF(Orders!$B$2:$B$401,A3) -> 3 | J3: =SUMIF(Orders!$B$2:$B$401,A3,Orders!$H$2:$H$401) -> 15188.331 | K3: =IFERROR(J3/I3,0) -> 5062.777
A4: 3 | B4: Crestline Wholesale | C4: Susan Miller | D4: susan.miller3@example.com | E4: USA | F4: Seattle | G4: Consumer | H4: 2023-11-01 | I4: =COUNTIF(Orders!$B$2:$B$401,A4) -> 3 | J4: =SUMIF(Orders!$B$2:$B$401,A4,Orders!$H$2:$H$401) -> 18853.145 | K4: =IFERROR(J4/I4,0) -> 6284.3818
A5: 4 | B5: Silver Group | C5: Susan Anderson | D5: susan.anderson4@example.com | E5: USA | F5: Chicago | G5: Small Business | H5: 2020-02-08 | I5: =COUNTIF(Orders!$B$2:$B$401,A5) -> 4 | J5: =SUMIF(Orders!$B$2:$B$401,A5,Orders!$H$2:$H$401) -> 10838.086 | K5: =IFERROR(J5/I5,0) -> 2709.5216
A6: 5 | B6: Prime Group | C6: Lisa Hernandez | D6: lisa.hernandez5@example.com | E6: USA | F6: Seattle | G6: Consumer | H6: 2021-02-23 | I6: =COUNTIF(Orders!$B$2:$B$401,A6) -> 4 | J6: =SUMIF(Orders!$B$2:$B$401,A6,Orders!$H$2:$H$401) -> 21579.464 | K6: =IFERROR(J6/I6,0) -> 5394.866
A7: 6 | B7: Nova Industries | C7: Joseph Jones | D7: joseph.jones6@example.com | E7: Australia | F7: Melbourne | G7: Consumer | H7: 2022-02-14 | I7: =COUNTIF(Orders!$B$2:$B$401,A7) -> 10 | J7: =SUMIF(Orders!$B$2:$B$401,A7,Orders!$H$2:$H$401) -> 46488.101 | K7: =IFERROR(J7/I7,0) -> 4648.8101
A8: 7 | B8: Urban Supply Co | C8: Margaret Williams | D8: margaret.williams7@example.com | E8: Japan | F8: Tokyo | G8: Small Business | H8: 2020-02-06 | I8: =COUNTIF(Orders!$B$2:$B$401,A8) -> 4 | J8: =SUMIF(Orders!$B$2:$B$401,A8,Orders!$H$2:$H$401) -> 17833.693 | K8: =IFERROR(J8/I8,0) -> 4458.4233
A9: 8 | B9: Prime Solutions | C9: Sarah Smith | D9: sarah.smith8@example.com | E9: USA | F9: Austin | G9: Consumer | H9: 2020-11-12 | I9: =COUNTIF(Orders!$B$2:$B$401,A9) -> 9 | J9: =SUMIF(Orders!$B$2:$B$401,A9,Orders!$H$2:$H$401) -> 28811.665 | K9: =IFERROR(J9/I9,0) -> 3201.2962
A10: 9 | B10: Northern Distributors | C10: Jessica Miller | D10: jessica.miller9@example.com | E10: Australia | F10: Sydney | G10: Consumer | H10: 2020-11-05 | I10: =COUNTIF(Orders!$B$2:$B$401,A10) -> 4 | J10: =SUMIF(Orders!$B$2:$B$401,A10,Orders!$H$2:$H$401) -> 14596.396 | K10: =IFERROR(J10/I10,0) -> 3649.099
A11: 10 | B11: Horizon Traders | C11: Richard Rodriguez | D11: richard.rodriguez10@example.com | E11: Japan | F11: Tokyo | G11: Corporate | H11: 2023-09-29 | I11: =COUNTIF(Orders!$B$2:$B$401,A11) -> 8 | J11: =SUMIF(Orders!$B$2:$B$401,A11,Orders!$H$2:$H$401) -> 55426.68 | K11: =IFERROR(J11/I11,0) -> 6928.335
A12: 11 | B12: Ironclad Solutions | C12: Matthew Thomas | D12: matthew.thomas11@example.com | E12: Canada | F12: Toronto | G12: Consumer | H12: 2022-04-30 | I12: =COUNTIF(Orders!$B$2:$B$401,A12) -> 9 | J12: =SUMIF(Orders!$B$2:$B$401,A12,Orders!$H$2:$H$401) -> 37463.524 | K12: =IFERROR(J12/I12,0) -> 4162.6138
A13: 12 | B13: Nova Traders | C13: Charles Moore | D13: charles.moore12@example.com | E13: USA | F13: Chicago | G13: Small Business | H13: 2022-07-08 | I13: =COUNTIF(Orders!$B$2:$B$401,A13) -> 10 | J13: =SUMIF(Orders!$B$2:$B$401,A13,Orders!$H$2:$H$401) -> 38655.065 | K13: =IFERROR(J13/I13,0) -> 3865.5065
... A61: 60 | B61: Crestline Solutions | C61: Linda Rodriguez | D61: linda.rodriguez60@example.com | E61: Japan | F61: Tokyo | G61: Consumer | H61: 2022-03-16 | I61: =COUNTIF(Orders!$B$2:$B$401,A61) -> 9 | J61: =SUMIF(Orders!$B$2:$B$401,A61,Orders!$H$2:$H$401) -> 28706.987 | K61: =IFERROR(J61/I61,0) -> 3189.6652

Sheet Suppliers
A1: supplier id | B1: supplier name | C1: country | D1: lead time days | E1: rating | F1: Products Supplied | G1: Total Restock Qty | H1: Total Damaged Qty
A2: 1 | B2: Acme Manufacturing | C2: China | D2: 20 | E2: 3.4 | F2: =COUNTIF(Products!$D$2:$D$101,A2) -> 9 | G2: =SUMIFS(InventoryTransactions!$E$2:$E$351,InventoryTransactions!$H$2:$H$351,A2,InventoryTransactions!$D$2:$D$351,"Restock") -> 2613 | H2: =-SUMIFS(InventoryTransactions!$E$2:$E$351,InventoryTransactions!$H$2:$H$351,A2,InventoryTransactions!$D$2:$D$351,"Damaged") -> 83
A3: 2 | B3: Global Parts Ltd | C3: USA | D3: 25 | E3: 4.76 | F3: =COUNTIF(Products!$D$2:$D$101,A3) -> 11 | G3: =SUMIFS(InventoryTransactions!$E$2:$E$351,InventoryTransactions!$H$2:$H$351,A3,InventoryTransactions!$D$2:$D$351,"Restock") -> 3607 | H3: =-SUMIFS(InventoryTransactions!$E$2:$E$351,InventoryTransactions!$H$2:$H$351,A3,InventoryTransactions!$D$2:$D$351,"Damaged") -> 255
A4: 3 | B4: EastPoint Textiles | C4: Germany | D4: 10 | E4: 3.1 | F4: =COUNTIF(Products!$D$2:$D$101,A4) -> 3 | G4: =SUMIFS(InventoryTransactions!$E$2:$E$351,InventoryTransactions!$H$2:$H$351,A4,InventoryTransactions!$D$2:$D$351,"Restock") -> 334 | H4: =-SUMIFS(InventoryTransactions!$E$2:$E$351,InventoryTransactions!$H$2:$H$351,A4,InventoryTransactions!$D$2:$D$351,"Damaged") -> 45
A5: 4 | B5: Nordic Components | C5: Vietnam | D5: 19 | E5: 3.64 | F5: =COUNTIF(Products!$D$2:$D$101,A5) -> 7 | G5: =SUMIFS(InventoryTransactions!$E$2:$E$351,InventoryTransactions!$H$2:$H$351,A5,InventoryTransactions!$D$2:$D$351,"Restock") -> 3645 | H5: =-SUMIFS(InventoryTransactions!$E$2:$E$351,InventoryTransactions!$H$2:$H$351,A5,InventoryTransactions!$D$2:$D$351,"Damaged") -> 19
A6: 5 | B6: Pacific Rim Supply | C6: India | D6: 14 | E6: 4.35 | F6: =COUNTIF(Products!$D$2:$D$101,A6) -> 12 | G6: =SUMIFS(InventoryTransactions!$E$2:$E$351,InventoryTransactions!$H$2:$H$351,A6,InventoryTransactions!$D$2:$D$351,"Restock") -> 3359 | H6: =-SUMIFS(InventoryTransactions!$E$2:$E$351,InventoryTransactions!$H$2:$H$351,A6,InventoryTransactions!$D$2:$D$351,"Damaged") -> 67
A7: 6 | B7: Ironwood Industries | C7: Mexico | D7: 9 | E7: 3.71 | F7: =COUNTIF(Products!$D$2:$D$101,A7) -> 3 | G7: =SUMIFS(InventoryTransactions!$E$2:$E$351,InventoryTransactions!$H$2:$H$351,A7,InventoryTransactions!$D$2:$D$351,"Restock") -> 872 | H7: =-SUMIFS(InventoryTransactions!$E$2:$E$351,InventoryTransactions!$H$2:$H$351,A7,InventoryTransactions!$D$2:$D$351,"Damaged") -> 79
A8: 7 | B8: BrightPath Goods | C8: South Korea | D8: 26 | E8: 3.99 | F8: =COUNTIF(Products!$D$2:$D$101,A8) -> 12 | G8: =SUMIFS(InventoryTransactions!$E$2:$E$351,InventoryTransactions!$H$2:$H$351,A8,InventoryTransactions!$D$2:$D$351,"Restock") -> 3282 | H8: =-SUMIFS(InventoryTransactions!$E$2:$E$351,InventoryTransactions!$H$2:$H$351,A8,InventoryTransactions!$D$2:$D$351,"Damaged") -> 163
A9: 8 | B9: Zenith Materials | C9: Italy | D9: 31 | E9: 2.94 | F9: =COUNTIF(Products!$D$2:$D$101,A9) -> 12 | G9: =SUMIFS(InventoryTransactions!$E$2:$E$351,InventoryTransactions!$H$2:$H$351,A9,InventoryTransactions!$D$2:$D$351,"Restock") -> 2943 | H9: =-SUMIFS(InventoryTransactions!$E$2:$E$351,InventoryTransactions!$H$2:$H$351,A9,InventoryTransactions!$D$2:$D$351,"Damaged") -> 149
A10: 9 | B10: Continental Fabrics | C10: Turkey | D10: 31 | E10: 3.66 | F10: =COUNTIF(Products!$D$2:$D$101,A10) -> 4 | G10: =SUMIFS(InventoryTransactions!$E$2:$E$351,InventoryTransactions!$H$2:$H$351,A10,InventoryTransactions!$D$2:$D$351,"Restock") -> 805 | H10: =-SUMIFS(InventoryTransactions!$E$2:$E$351,InventoryTransactions!$H$2:$H$351,A10,InventoryTransactions!$D$2:$D$351,"Damaged") -> 174
A11: 10 | B11: Summit Hardware | C11: Poland | D11: 42 | E11: 4.88 | F11: =COUNTIF(Products!$D$2:$D$101,A11) -> 8 | G11: =SUMIFS(InventoryTransactions!$E$2:$E$351,InventoryTransactions!$H$2:$H$351,A11,InventoryTransactions!$D$2:$D$351,"Restock") -> 3021 | H11: =-SUMIFS(InventoryTransactions!$E$2:$E$351,InventoryTransactions!$H$2:$H$351,A11,InventoryTransactions!$D$2:$D$351,"Damaged") -> 117
A12: 11 | B12: Redwood Electronics | C12: Taiwan | D12: 6 | E12: 4.68 | F12: =COUNTIF(Products!$D$2:$D$101,A12) -> 8 | G12: =SUMIFS(InventoryTransactions!$E$2:$E$351,InventoryTransactions!$H$2:$H$351,A12,InventoryTransactions!$D$2:$D$351,"Restock") -> 2411 | H12: =-SUMIFS(InventoryTransactions!$E$2:$E$351,InventoryTransactions!$H$2:$H$351,A12,InventoryTransactions!$D$2:$D$351,"Damaged") -> 77
A13: 12 | B13: Falcon Packaging | C13: Canada | D13: 41 | E13: 3.64 | F13: =COUNTIF(Products!$D$2:$D$101,A13) -> 11 | G13: =SUMIFS(InventoryTransactions!$E$2:$E$351,InventoryTransactions!$H$2:$H$351,A13,InventoryTransactions!$D$2:$D$351,"Restock") -> 2662 | H13: =-SUMIFS(InventoryTransactions!$E$2:$E$351,InventoryTransactions!$H$2:$H$351,A13,InventoryTransactions!$D$2:$D$351,"Damaged") -> 89

Sheet Categories
A1: category id | B1: category name | C1: Product Count | D1: Total Units Sold | E1: Total Revenue | F1: Inventory Value
A2: 1 | B2: Electronics | C2: =COUNTIF(Products!$C$2:$C$101,A2) -> 10 | D2: =SUMIF(OrderItems!$H$2:$H$1254,A2,OrderItems!$D$2:$D$1254) -> 711 | E2: =SUMIF(OrderItems!$H$2:$H$1254,A2,OrderItems!$G$2:$G$1254) -> 185455.92 | F2: =SUMIF(Products!$C$2:$C$101,A2,Products!$L$2:$L$101) -> 474429.85
A3: 2 | B3: Office Supplies | C3: =COUNTIF(Products!$C$2:$C$101,A3) -> 10 | D3: =SUMIF(OrderItems!$H$2:$H$1254,A3,OrderItems!$D$2:$D$1254) -> 666 | E3: =SUMIF(OrderItems!$H$2:$H$1254,A3,OrderItems!$G$2:$G$1254) -> 188788.64 | F3: =SUMIF(Products!$C$2:$C$101,A3,Products!$L$2:$L$101) -> 494090.55
A4: 3 | B4: Furniture | C4: =COUNTIF(Products!$C$2:$C$101,A4) -> 10 | D4: =SUMIF(OrderItems!$H$2:$H$1254,A4,OrderItems!$D$2:$D$1254) -> 621 | E4: =SUMIF(OrderItems!$H$2:$H$1254,A4,OrderItems!$G$2:$G$1254) -> 144037.7 | F4: =SUMIF(Products!$C$2:$C$101,A4,Products!$L$2:$L$101) -> 374937.3
A5: 4 | B5: Apparel | C5: =COUNTIF(Products!$C$2:$C$101,A5) -> 10 | D5: =SUMIF(OrderItems!$H$2:$H$1254,A5,OrderItems!$D$2:$D$1254) -> 794 | E5: =SUMIF(OrderItems!$H$2:$H$1254,A5,OrderItems!$G$2:$G$1254) -> 206243 | F5: =SUMIF(Products!$C$2:$C$101,A5,Products!$L$2:$L$101) -> 342078.09
A6: 5 | B6: Home & Kitchen | C6: =COUNTIF(Products!$C$2:$C$101,A6) -> 10 | D6: =SUMIF(OrderItems!$H$2:$H$1254,A6,OrderItems!$D$2:$D$1254) -> 710 | E6: =SUMIF(OrderItems!$H$2:$H$1254,A6,OrderItems!$G$2:$G$1254) -> 135507.78 | F6: =SUMIF(Products!$C$2:$C$101,A6,Products!$L$2:$L$101) -> 246239.51
A7: 6 | B7: Sporting Goods | C7: =COUNTIF(Products!$C$2:$C$101,A7) -> 10 | D7: =SUMIF(OrderItems!$H$2:$H$1254,A7,OrderItems!$D$2:$D$1254) -> 757 | E7: =SUMIF(OrderItems!$H$2:$H$1254,A7,OrderItems!$G$2:$G$1254) -> 269240.84 | F7: =SUMIF(Products!$C$2:$C$101,A7,Products!$L$2:$L$101) -> 517487.33
A8: 7 | B8: Toys & Games | C8: =COUNTIF(Products!$C$2:$C$101,A8) -> 10 | D8: =SUMIF(OrderItems!$H$2:$H$1254,A8,OrderItems!$D$2:$D$1254) -> 641 | E8: =SUMIF(OrderItems!$H$2:$H$1254,A8,OrderItems!$G$2:$G$1254) -> 109793.87 | F8: =SUMIF(Products!$C$2:$C$101,A8,Products!$L$2:$L$101) -> 199556.26
A9: 8 | B9: Health & Beauty | C9: =COUNTIF(Products!$C$2:$C$101,A9) -> 10 | D9: =SUMIF(OrderItems!$H$2:$H$1254,A9,OrderItems!$D$2:$D$1254) -> 638 | E9: =SUMIF(OrderItems!$H$2:$H$1254,A9,OrderItems!$G$2:$G$1254) -> 177044.39 | F9: =SUMIF(Products!$C$2:$C$101,A9,Products!$L$2:$L$101) -> 466264.94
A10: 9 | B10: Automotive Parts | C10: =COUNTIF(Products!$C$2:$C$101,A10) -> 10 | D10: =SUMIF(OrderItems!$H$2:$H$1254,A10,OrderItems!$D$2:$D$1254) -> 654 | E10: =SUMIF(OrderItems!$H$2:$H$1254,A10,OrderItems!$G$2:$G$1254) -> 155430.56 | F10: =SUMIF(Products!$C$2:$C$101,A10,Products!$L$2:$L$101) -> 359871.16
A11: 10 | B11: Groceries | C11: =COUNTIF(Products!$C$2:$C$101,A11) -> 10 | D11: =SUMIF(OrderItems!$H$2:$H$1254,A11,OrderItems!$D$2:$D$1254) -> 710 | E11: =SUMIF(OrderItems!$H$2:$H$1254,A11,OrderItems!$G$2:$G$1254) -> 184134.4 | F11: =SUMIF(Products!$C$2:$C$101,A11,Products!$L$2:$L$101) -> 343753.31

Sheet Products
A1: product id | B1: product name | C1: category id | D1: supplier id | E1: unit cost | F1: unit price | G1: stock quantity | H1: reorder level | I1: discontinued | J1: Category Name | K1: Supplier Name | L1: Inventory Value | M1: Reorder Flag | N1: Units Sold | O1: Revenue Generated | P1: Gross Margin %
A2: 1 | B2: Wireless Mouse | C2: 1 | D2: 1 | E2: 235.86 | F2: 384.09 | G2: 199 | H2: 74 | I2: 0 | J2: =INDEX(Categories!$B$2:$B$11,MATCH(C2,Categories!$A$2:$A$11,0)) -> Electronics | K2: =INDEX(Suppliers!$B$2:$B$13,MATCH(D2,Suppliers!$A$2:$A$13,0)) -> Acme Manufacturing | L2: =G2*E2 -> 46936.14 | M2: =IF(G2<=H2,"REORDER","OK") -> OK | N2: =SUMIF(OrderItems!$C$2:$C$1254,A2,OrderItems!$D$2:$D$1254) -> 55 | O2: =SUMIF(OrderItems!$C$2:$C$1254,A2,OrderItems!$G$2:$G$1254) -> 19358.136 | P2: =IFERROR((F2-E2)/F2,0) -> 0.38592517
A3: 2 | B3: Bluetooth Speaker | C3: 1 | D3: 7 | E3: 135.94 | F3: 286.57 | G3: 409 | H3: 58 | I3: 0 | J3: =INDEX(Categories!$B$2:$B$11,MATCH(C3,Categories!$A$2:$A$11,0)) -> Electronics | K3: =INDEX(Suppliers!$B$2:$B$13,MATCH(D3,Suppliers!$A$2:$A$13,0)) -> BrightPath Goods | L3: =G3*E3 -> 55599.46 | M3: =IF(G3<=H3,"REORDER","OK") -> OK | N3: =SUMIF(OrderItems!$C$2:$C$1254,A3,OrderItems!$D$2:$D$1254) -> 81 | O3: =SUMIF(OrderItems!$C$2:$C$1254,A3,OrderItems!$G$2:$G$1254) -> 21679.021 | P3: =IFERROR((F3-E3)/F3,0) -> 0.52563074
A4: 3 | B4: USB-C Hub | C4: 1 | D4: 8 | E4: 57.2 | F4: 101.78 | G4: 14 | H4: 44 | I4: 0 | J4: =INDEX(Categories!$B$2:$B$11,MATCH(C4,Categories!$A$2:$A$11,0)) -> Electronics | K4: =INDEX(Suppliers!$B$2:$B$13,MATCH(D4,Suppliers!$A$2:$A$13,0)) -> Zenith Materials | L4: =G4*E4 -> 800.8 | M4: =IF(G4<=H4,"REORDER","OK") -> REORDER | N4: =SUMIF(OrderItems!$C$2:$C$1254,A4,OrderItems!$D$2:$D$1254) -> 59 | O4: =SUMIF(OrderItems!$C$2:$C$1254,A4,OrderItems!$G$2:$G$1254) -> 5373.984 | P4: =IFERROR((F4-E4)/F4,0) -> 0.43800354
A5: 4 | B5: 4K Monitor | C5: 1 | D5: 11 | E5: 200.14 | F5: 419.61 | G5: 430 | H5: 49 | I5: 0 | J5: =INDEX(Categories!$B$2:$B$11,MATCH(C5,Categories!$A$2:$A$11,0)) -> Electronics | K5: =INDEX(Suppliers!$B$2:$B$13,MATCH(D5,Suppliers!$A$2:$A$13,0)) -> Redwood Electronics | L5: =G5*E5 -> 86060.2 | M5: =IF(G5<=H5,"REORDER","OK") -> OK | N5: =SUMIF(OrderItems!$C$2:$C$1254,A5,OrderItems!$D$2:$D$1254) -> 43 | O5: =SUMIF(OrderItems!$C$2:$C$1254,A5,OrderItems!$G$2:$G$1254) -> 16700.478 | P5: =IFERROR((F5-E5)/F5,0) -> 0.52303329
A6: 5 | B6: Mechanical Keyboard | C6: 1 | D6: 10 | E6: 134.93 | F6: 310.02 | G6: 303 | H6: 56 | I6: 0 | J6: =INDEX(Categories!$B$2:$B$11,MATCH(C6,Categories!$A$2:$A$11,0)) -> Electronics | K6: =INDEX(Suppliers!$B$2:$B$13,MATCH(D6,Suppliers!$A$2:$A$13,0)) -> Summit Hardware | L6: =G6*E6 -> 40883.79 | M6: =IF(G6<=H6,"REORDER","OK") -> OK | N6: =SUMIF(OrderItems!$C$2:$C$1254,A6,OrderItems!$D$2:$D$1254) -> 80 | O6: =SUMIF(OrderItems!$C$2:$C$1254,A6,OrderItems!$G$2:$G$1254) -> 23794.035 | P6: =IFERROR((F6-E6)/F6,0) -> 0.56477001
A7: 6 | B7: Noise-Cancelling Headphones | C7: 1 | D7: 2 | E7: 161.76 | F7: 234.43 | G7: 236 | H7: 31 | I7: 0 | J7: =INDEX(Categories!$B$2:$B$11,MATCH(C7,Categories!$A$2:$A$11,0)) -> Electronics | K7: =INDEX(Suppliers!$B$2:$B$13,MATCH(D7,Suppliers!$A$2:$A$13,0)) -> Global Parts Ltd | L7: =G7*E7 -> 38175.36 | M7: =IF(G7<=H7,"REORDER","OK") -> OK | N7: =SUMIF(OrderItems!$C$2:$C$1254,A7,OrderItems!$D$2:$D$1254) -> 91 | O7: =SUMIF(OrderItems!$C$2:$C$1254,A7,OrderItems!$G$2:$G$1254) -> 18965.387 | P7: =IFERROR((F7-E7)/F7,0) -> 0.30998592
A8: 7 | B8: Smartwatch | C8: 1 | D8: 7 | E8: 83.86 | F8: 150.96 | G8: 172 | H8: 68 | I8: 0 | J8: =INDEX(Categories!$B$2:$B$11,MATCH(C8,Categories!$A$2:$A$11,0)) -> Electronics | K8: =INDEX(Suppliers!$B$2:$B$13,MATCH(D8,Suppliers!$A$2:$A$13,0)) -> BrightPath Goods | L8: =G8*E8 -> 14423.92 | M8: =IF(G8<=H8,"REORDER","OK") -> OK | N8: =SUMIF(OrderItems!$C$2:$C$1254,A8,OrderItems!$D$2:$D$1254) -> 108 | O8: =SUMIF(OrderItems!$C$2:$C$1254,A8,OrderItems!$G$2:$G$1254) -> 15262.056 | P8: =IFERROR((F8-E8)/F8,0) -> 0.44448861
A9: 8 | B9: Portable Charger | C9: 1 | D9: 5 | E9: 188.75 | F9: 418.1 | G9: 129 | H9: 73 | I9: 0 | J9: =INDEX(Categories!$B$2:$B$11,MATCH(C9,Categories!$A$2:$A$11,0)) -> Electronics | K9: =INDEX(Suppliers!$B$2:$B$13,MATCH(D9,Suppliers!$A$2:$A$13,0)) -> Pacific Rim Supply | L9: =G9*E9 -> 24348.75 | M9: =IF(G9<=H9,"REORDER","OK") -> OK | N9: =SUMIF(OrderItems!$C$2:$C$1254,A9,OrderItems!$D$2:$D$1254) -> 65 | O9: =SUMIF(OrderItems!$C$2:$C$1254,A9,OrderItems!$G$2:$G$1254) -> 24333.42 | P9: =IFERROR((F9-E9)/F9,0) -> 0.54855298
A10: 9 | B10: Webcam HD | C10: 1 | D10: 1 | E10: 188.01 | F10: 255.18 | G10: 487 | H10: 42 | I10: 0 | J10: =INDEX(Categories!$B$2:$B$11,MATCH(C10,Categories!$A$2:$A$11,0)) -> Electronics | K10: =INDEX(Suppliers!$B$2:$B$13,MATCH(D10,Suppliers!$A$2:$A$13,0)) -> Acme Manufacturing | L10: =G10*E10 -> 91560.87 | M10: =IF(G10<=H10,"REORDER","OK") -> OK | N10: =SUMIF(OrderItems!$C$2:$C$1254,A10,OrderItems!$D$2:$D$1254) -> 49 | O10: =SUMIF(OrderItems!$C$2:$C$1254,A10,OrderItems!$G$2:$G$1254) -> 11393.787 | P10: =IFERROR((F10-E10)/F10,0) -> 0.26322596
A11: 10 | B11: Laptop Stand | C11: 1 | D11: 2 | E11: 195.96 | F11: 395.24 | G11: 386 | H11: 21 | I11: 0 | J11: =INDEX(Categories!$B$2:$B$11,MATCH(C11,Categories!$A$2:$A$11,0)) -> Electronics | K11: =INDEX(Suppliers!$B$2:$B$13,MATCH(D11,Suppliers!$A$2:$A$13,0)) -> Global Parts Ltd | L11: =G11*E11 -> 75640.56 | M11: =IF(G11<=H11,"REORDER","OK") -> OK | N11: =SUMIF(OrderItems!$C$2:$C$1254,A11,OrderItems!$D$2:$D$1254) -> 80 | O11: =SUMIF(OrderItems!$C$2:$C$1254,A11,OrderItems!$G$2:$G$1254) -> 28595.614 | P11: =IFERROR((F11-E11)/F11,0) -> 0.50419998
A12: 11 | B12: Stapler | C12: 2 | D12: 4 | E12: 210.29 | F12: 417.1 | G12: 122 | H12: 28 | I12: 0 | J12: =INDEX(Categories!$B$2:$B$11,MATCH(C12,Categories!$A$2:$A$11,0)) -> Office Supplies | K12: =INDEX(Suppliers!$B$2:$B$13,MATCH(D12,Suppliers!$A$2:$A$13,0)) -> Nordic Components | L12: =G12*E12 -> 25655.38 | M12: =IF(G12<=H12,"REORDER","OK") -> OK | N12: =SUMIF(OrderItems!$C$2:$C$1254,A12,OrderItems!$D$2:$D$1254) -> 87 | O12: =SUMIF(OrderItems!$C$2:$C$1254,A12,OrderItems!$G$2:$G$1254) -> 34118.78 | P12: =IFERROR((F12-E12)/F12,0) -> 0.49582834
A13: 12 | B13: Printer Paper (Ream) | C13: 2 | D13: 2 | E13: 142.3 | F13: 219.11 | G13: 358 | H13: 36 | I13: 0 | J13: =INDEX(Categories!$B$2:$B$11,MATCH(C13,Categories!$A$2:$A$11,0)) -> Office Supplies | K13: =INDEX(Suppliers!$B$2:$B$13,MATCH(D13,Suppliers!$A$2:$A$13,0)) -> Global Parts Ltd | L13: =G13*E13 -> 50943.4 | M13: =IF(G13<=H13,"REORDER","OK") -> OK | N13: =SUMIF(OrderItems!$C$2:$C$1254,A13,OrderItems!$D$2:$D$1254) -> 61 | O13: =SUMIF(OrderItems!$C$2:$C$1254,A13,OrderItems!$G$2:$G$1254) -> 12587.87 | P13: =IFERROR((F13-E13)/F13,0) -> 0.35055452
... A101: 100 | B101: Trail Mix | C101: 10 | D101: 5 | E101: 187.4 | F101: 313.44 | G101: 58 | H101: 49 | I101: 0 | J101: =INDEX(Categories!$B$2:$B$11,MATCH(C101,Categories!$A$2:$A$11,0)) -> Groceries | K101: =INDEX(Suppliers!$B$2:$B$13,MATCH(D101,Suppliers!$A$2:$A$13,0)) -> Pacific Rim Supply | L101: =G101*E101 -> 10869.2 | M101: =IF(G101<=H101,"REORDER","OK") -> OK | N101: =SUMIF(OrderItems!$C$2:$C$1254,A101,OrderItems!$D$2:$D$1254) -> 105 | O101: =SUMIF(OrderItems!$C$2:$C$1254,A101,OrderItems!$G$2:$G$1254) -> 31234.296 | P101: =IFERROR((F101-E101)/F101,0) -> 0.40211843

Sheet Orders
A1: order_id | B1: customer id | C1: employee id | D1: order date | E1: ship date | F1: status | G1: ship region | H1: Order Revenue | I1: Order Cost | J1: Order Profit | K1: Order Month | L1: Customer Segment | M1: Sales Rep | N1: Fulfillment Days
A2: 1 | B2: 10 | C2: 8 | D2: 2025-03-24 | F2: Pending | G2: North America | H2: =SUMIF(OrderItems!$B$2:$B$1254,A2,OrderItems!$G$2:$G$1254) -> 6946.633 | I2: =SUMIF(OrderItems!$B$2:$B$1254,A2,OrderItems!$K$2:$K$1254) -> 3780.95 | J2: =H2-I2 -> 3165.683 | K2: =IF(D2="","",TEXT(D2,"YYYY-MM")) -> 2025-03 | L2: =IFERROR(INDEX(Customers!$G$2:$G$61,MATCH(B2,Customers!$A$2:$A$61,0)),"") -> Corporate | M2: =IFERROR(INDEX(Employees!$B$2:$B$37,MATCH(C2,Employees!$A$2:$A$37,0))&" "&INDEX(Employees!$C$2:$C$37,MATCH(C2,Employees!$A$2:$A$37,0)),"") -> John Gonzalez | N2: =IF(E2="","",E2-D2)
A3: 2 | B3: 40 | C3: 9 | D3: 2024-03-29 | E3: 2024-04-06 | F3: Delivered | G3: Asia Pacific | H3: =SUMIF(OrderItems!$B$2:$B$1254,A3,OrderItems!$G$2:$G$1254) -> 3948.2525 | I3: =SUMIF(OrderItems!$B$2:$B$1254,A3,OrderItems!$K$2:$K$1254) -> 2405.85 | J3: =H3-I3 -> 1542.4025 | K3: =IF(D3="","",TEXT(D3,"YYYY-MM")) -> 2024-03 | L3: =IFERROR(INDEX(Customers!$G$2:$G$61,MATCH(B3,Customers!$A$2:$A$61,0)),"") -> Corporate | M3: =IFERROR(INDEX(Employees!$B$2:$B$37,MATCH(C3,Employees!$A$2:$A$37,0))&" "&INDEX(Employees!$C$2:$C$37,MATCH(C3,Employees!$A$2:$A$37,0)),"") -> William Johnson | N3: =IF(E3="","",E3-D3) -> 8
A4: 3 | B4: 43 | C4: 10 | D4: 2023-11-13 | F4: Cancelled | G4: North America | H4: =SUMIF(OrderItems!$B$2:$B$1254,A4,OrderItems!$G$2:$G$1254) -> 9650.304 | I4: =SUMIF(OrderItems!$B$2:$B$1254,A4,OrderItems!$K$2:$K$1254) -> 4970.62 | J4: =H4-I4 -> 4679.684 | K4: =IF(D4="","",TEXT(D4,"YYYY-MM")) -> 2023-11 | L4: =IFERROR(INDEX(Customers!$G$2:$G$61,MATCH(B4,Customers!$A$2:$A$61,0)),"") -> Corporate | M4: =IFERROR(INDEX(Employees!$B$2:$B$37,MATCH(C4,Employees!$A$2:$A$37,0))&" "&INDEX(Employees!$C$2:$C$37,MATCH(C4,Employees!$A$2:$A$37,0)),"") -> John Moore | N4: =IF(E4="","",E4-D4)
A5: 4 | B5: 44 | C5: 9 | D5: 2025-01-04 | E5: 2025-01-11 | F5: Delivered | G5: Asia Pacific | H5: =SUMIF(OrderItems!$B$2:$B$1254,A5,OrderItems!$G$2:$G$1254) -> 818.414 | I5: =SUMIF(OrderItems!$B$2:$B$1254,A5,OrderItems!$K$2:$K$1254) -> 473.68 | J5: =H5-I5 -> 344.734 | K5: =IF(D5="","",TEXT(D5,"YYYY-MM")) -> 2025-01 | L5: =IFERROR(INDEX(Customers!$G$2:$G$61,MATCH(B5,Customers!$A$2:$A$61,0)),"") -> Corporate | M5: =IFERROR(INDEX(Employees!$B$2:$B$37,MATCH(C5,Employees!$A$2:$A$37,0))&" "&INDEX(Employees!$C$2:$C$37,MATCH(C5,Employees!$A$2:$A$37,0)),"") -> William Johnson | N5: =IF(E5="","",E5-D5) -> 7
A6: 5 | B6: 4 | C6: 9 | D6: 2024-05-13 | E6: 2024-05-23 | F6: Delivered | G6: Europe | H6: =SUMIF(OrderItems!$B$2:$B$1254,A6,OrderItems!$G$2:$G$1254) -> 607.32 | I6: =SUMIF(OrderItems!$B$2:$B$1254,A6,OrderItems!$K$2:$K$1254) -> 320.76 | J6: =H6-I6 -> 286.56 | K6: =IF(D6="","",TEXT(D6,"YYYY-MM")) -> 2024-05 | L6: =IFERROR(INDEX(Customers!$G$2:$G$61,MATCH(B6,Customers!$A$2:$A$61,0)),"") -> Small Business | M6: =IFERROR(INDEX(Employees!$B$2:$B$37,MATCH(C6,Employees!$A$2:$A$37,0))&" "&INDEX(Employees!$C$2:$C$37,MATCH(C6,Employees!$A$2:$A$37,0)),"") -> William Johnson | N6: =IF(E6="","",E6-D6) -> 10
A7: 6 | B7: 53 | C7: 8 | D7: 2024-11-03 | E7: 2024-11-13 | F7: Delivered | G7: North America | H7: =SUMIF(OrderItems!$B$2:$B$1254,A7,OrderItems!$G$2:$G$1254) -> 1967.39 | I7: =SUMIF(OrderItems!$B$2:$B$1254,A7,OrderItems!$K$2:$K$1254) -> 1561.24 | J7: =H7-I7 -> 406.15 | K7: =IF(D7="","",TEXT(D7,"YYYY-MM")) -> 2024-11 | L7: =IFERROR(INDEX(Customers!$G$2:$G$61,MATCH(B7,Customers!$A$2:$A$61,0)),"") -> Corporate | M7: =IFERROR(INDEX(Employees!$B$2:$B$37,MATCH(C7,Employees!$A$2:$A$37,0))&" "&INDEX(Employees!$C$2:$C$37,MATCH(C7,Employees!$A$2:$A$37,0)),"") -> John Gonzalez | N7: =IF(E7="","",E7-D7) -> 10
A8: 7 | B8: 51 | C8: 8 | D8: 2024-10-25 | E8: 2024-10-28 | F8: Delivered | G8: Asia Pacific | H8: =SUMIF(OrderItems!$B$2:$B$1254,A8,OrderItems!$G$2:$G$1254) -> 1366.092 | I8: =SUMIF(OrderItems!$B$2:$B$1254,A8,OrderItems!$K$2:$K$1254) -> 1059.1 | J8: =H8-I8 -> 306.992 | K8: =IF(D8="","",TEXT(D8,"YYYY-MM")) -> 2024-10 | L8: =IFERROR(INDEX(Customers!$G$2:$G$61,MATCH(B8,Customers!$A$2:$A$61,0)),"") -> Consumer | M8: =IFERROR(INDEX(Employees!$B$2:$B$37,MATCH(C8,Employees!$A$2:$A$37,0))&" "&INDEX(Employees!$C$2:$C$37,MATCH(C8,Employees!$A$2:$A$37,0)),"") -> John Gonzalez | N8: =IF(E8="","",E8-D8) -> 3
A9: 8 | B9: 31 | C9: 10 | D9: 2025-01-11 | E9: 2025-01-19 | F9: Delivered | G9: Middle East | H9: =SUMIF(OrderItems!$B$2:$B$1254,A9,OrderItems!$G$2:$G$1254) -> 4922.504 | I9: =SUMIF(OrderItems!$B$2:$B$1254,A9,OrderItems!$K$2:$K$1254) -> 3231.42 | J9: =H9-I9 -> 1691.084 | K9: =IF(D9="","",TEXT(D9,"YYYY-MM")) -> 2025-01 | L9: =IFERROR(INDEX(Customers!$G$2:$G$61,MATCH(B9,Customers!$A$2:$A$61,0)),"") -> Consumer | M9: =IFERROR(INDEX(Employees!$B$2:$B$37,MATCH(C9,Employees!$A$2:$A$37,0))&" "&INDEX(Employees!$C$2:$C$37,MATCH(C9,Employees!$A$2:$A$37,0)),"") -> John Moore | N9: =IF(E9="","",E9-D9) -> 8
A10: 9 | B10: 31 | C10: 10 | D10: 2025-05-23 | E10: 2025-05-31 | F10: Delivered | G10: Latin America | H10: =SUMIF(OrderItems!$B$2:$B$1254,A10,OrderItems!$G$2:$G$1254) -> 2252.34 | I10: =SUMIF(OrderItems!$B$2:$B$1254,A10,OrderItems!$K$2:$K$1254) -> 1261.74 | J10: =H10-I10 -> 990.6 | K10: =IF(D10="","",TEXT(D10,"YYYY-MM")) -> 2025-05 | L10: =IFERROR(INDEX(Customers!$G$2:$G$61,MATCH(B10,Customers!$A$2:$A$61,0)),"") -> Consumer | M10: =IFERROR(INDEX(Employees!$B$2:$B$37,MATCH(C10,Employees!$A$2:$A$37,0))&" "&INDEX(Employees!$C$2:$C$37,MATCH(C10,Employees!$A$2:$A$37,0)),"") -> John Moore | N10: =IF(E10="","",E10-D10) -> 8
A11: 10 | B11: 9 | C11: 9 | D11: 2024-10-27 | F11: Cancelled | G11: Middle East | H11: =SUMIF(OrderItems!$B$2:$B$1254,A11,OrderItems!$G$2:$G$1254) -> 5824.5535 | I11: =SUMIF(OrderItems!$B$2:$B$1254,A11,OrderItems!$K$2:$K$1254) -> 3532.16 | J11: =H11-I11 -> 2292.3935 | K11: =IF(D11="","",TEXT(D11,"YYYY-MM")) -> 2024-10 | L11: =IFERROR(INDEX(Customers!$G$2:$G$61,MATCH(B11,Customers!$A$2:$A$61,0)),"") -> Consumer | M11: =IFERROR(INDEX(Employees!$B$2:$B$37,MATCH(C11,Employees!$A$2:$A$37,0))&" "&INDEX(Employees!$C$2:$C$37,MATCH(C11,Employees!$A$2:$A$37,0)),"") -> William Johnson | N11: =IF(E11="","",E11-D11)
A12: 11 | B12: 27 | C12: 9 | D12: 2025-07-17 | F12: Cancelled | G12: Latin America | H12: =SUMIF(OrderItems!$B$2:$B$1254,A12,OrderItems!$G$2:$G$1254) -> 2320.22 | I12: =SUMIF(OrderItems!$B$2:$B$1254,A12,OrderItems!$K$2:$K$1254) -> 1069.32 | J12: =H12-I12 -> 1250.9 | K12: =IF(D12="","",TEXT(D12,"YYYY-MM")) -> 2025-07 | L12: =IFERROR(INDEX(Customers!$G$2:$G$61,MATCH(B12,Customers!$A$2:$A$61,0)),"") -> Small Business | M12: =IFERROR(INDEX(Employees!$B$2:$B$37,MATCH(C12,Employees!$A$2:$A$37,0))&" "&INDEX(Employees!$C$2:$C$37,MATCH(C12,Employees!$A$2:$A$37,0)),"") -> William Johnson | N12: =IF(E12="","",E12-D12)
A13: 12 | B13: 43 | C13: 9 | D13: 2025-02-05 | E13: 2025-02-13 | F13: Delivered | G13: North America | H13: =SUMIF(OrderItems!$B$2:$B$1254,A13,OrderItems!$G$2:$G$1254) -> 792.49 | I13: =SUMIF(OrderItems!$B$2:$B$1254,A13,OrderItems!$K$2:$K$1254) -> 420.58 | J13: =H13-I13 -> 371.91 | K13: =IF(D13="","",TEXT(D13,"YYYY-MM")) -> 2025-02 | L13: =IFERROR(INDEX(Customers!$G$2:$G$61,MATCH(B13,Customers!$A$2:$A$61,0)),"") -> Corporate | M13: =IFERROR(INDEX(Employees!$B$2:$B$37,MATCH(C13,Employees!$A$2:$A$37,0))&" "&INDEX(Employees!$C$2:$C$37,MATCH(C13,Employees!$A$2:$A$37,0)),"") -> William Johnson | N13: =IF(E13="","",E13-D13) -> 8
A14: 13 | B14: 52 | C14: 8 | D14: 2023-05-03 | F14: Pending | G14: North America | H14: =SUMIF(OrderItems!$B$2:$B$1254,A14,OrderItems!$G$2:$G$1254) -> 4712.02 | I14: =SUMIF(OrderItems!$B$2:$B$1254,A14,OrderItems!$K$2:$K$1254) -> 2295.63 | J14: =H14-I14 -> 2416.39 | K14: =IF(D14="","",TEXT(D14,"YYYY-MM")) -> 2023-05 | L14: =IFERROR(INDEX(Customers!$G$2:$G$61,MATCH(B14,Customers!$A$2:$A$61,0)),"") -> Corporate | M14: =IFERROR(INDEX(Employees!$B$2:$B$37,MATCH(C14,Employees!$A$2:$A$37,0))&" "&INDEX(Employees!$C$2:$C$37,MATCH(C14,Employees!$A$2:$A$37,0)),"") -> John Gonzalez | N14: =IF(E14="","",E14-D14)
A15: 14 | B15: 15 | C15: 1 | D15: 2024-12-18 | F15: Pending | G15: North America | H15: =SUMIF(OrderItems!$B$2:$B$1254,A15,OrderItems!$G$2:$G$1254) -> 6214.806 | I15: =SUMIF(OrderItems!$B$2:$B$1254,A15,OrderItems!$K$2:$K$1254) -> 3146.82 | J15: =H15-I15 -> 3067.986 | K15: =IF(D15="","",TEXT(D15,"YYYY-MM")) -> 2024-12 | L15: =IFERROR(INDEX(Customers!$G$2:$G$61,MATCH(B15,Customers!$A$2:$A$61,0)),"") -> Small Business | M15: =IFERROR(INDEX(Employees!$B$2:$B$37,MATCH(C15,Employees!$A$2:$A$37,0))&" "&INDEX(Employees!$C$2:$C$37,MATCH(C15,Employees!$A$2:$A$37,0)),"") -> Daniel Brown | N15: =IF(E15="","",E15-D15)
A16: 15 | B16: 18 | C16: 9 | D16: 2024-11-26 | F16: Pending | G16: North America | H16: =SUMIF(OrderItems!$B$2:$B$1254,A16,OrderItems!$G$2:$G$1254) -> 3001.1885 | I16: =SUMIF(OrderItems!$B$2:$B$1254,A16,OrderItems!$K$2:$K$1254) -> 2086.16 | J16: =H16-I16 -> 915.0285 | K16: =IF(D16="","",TEXT(D16,"YYYY-MM")) -> 2024-11 | L16: =IFERROR(INDEX(Customers!$G$2:$G$61,MATCH(B16,Customers!$A$2:$A$61,0)),"") -> Small Business | M16: =IFERROR(INDEX(Employees!$B$2:$B$37,MATCH(C16,Employees!$A$2:$A$37,0))&" "&INDEX(Employees!$C$2:$C$37,MATCH(C16,Employees!$A$2:$A$37,0)),"") -> William Johnson | N16: =IF(E16="","",E16-D16)
A17: 16 | B17: 25 | C17: 10 | D17: 2025-07-18 | F17: Pending | G17: Europe | H17: =SUMIF(OrderItems!$B$2:$B$1254,A17,OrderItems!$G$2:$G$1254) -> 4664.99 | I17: =SUMIF(OrderItems!$B$2:$B$1254,A17,OrderItems!$K$2:$K$1254) -> 3307.88 | J17: =H17-I17 -> 1357.11 | K17: =IF(D17="","",TEXT(D17,"YYYY-MM")) -> 2025-07 | L17: =IFERROR(INDEX(Customers!$G$2:$G$61,MATCH(B17,Customers!$A$2:$A$61,0)),"") -> Small Business | M17: =IFERROR(INDEX(Employees!$B$2:$B$37,MATCH(C17,Employees!$A$2:$A$37,0))&" "&INDEX(Employees!$C$2:$C$37,MATCH(C17,Employees!$A$2:$A$37,0)),"") -> John Moore | N17: =IF(E17="","",E17-D17)
A18: 17 | B18: 18 | C18: 10 | D18: 2025-05-18 | E18: 2025-05-28 | F18: Returned | G18: Latin America | H18: =SUMIF(OrderItems!$B$2:$B$1254,A18,OrderItems!$G$2:$G$1254) -> 3309.605 | I18: =SUMIF(OrderItems!$B$2:$B$1254,A18,OrderItems!$K$2:$K$1254) -> 1993.96 | J18: =H18-I18 -> 1315.645 | K18: =IF(D18="","",TEXT(D18,"YYYY-MM")) -> 2025-05 | L18: =IFERROR(INDEX(Customers!$G$2:$G$61,MATCH(B18,Customers!$A$2:$A$61,0)),"") -> Small Business | M18: =IFERROR(INDEX(Employees!$B$2:$B$37,MATCH(C18,Employees!$A$2:$A$37,0))&" "&INDEX(Employees!$C$2:$C$37,MATCH(C18,Employees!$A$2:$A$37,0)),"") -> John Moore | N18: =IF(E18="","",E18-D18) -> 10
A19: 18 | B19: 39 | C19: 1 | D19: 2023-01-16 | E19: 2023-01-21 | F19: Delivered | G19: Europe | H19: =SUMIF(OrderItems!$B$2:$B$1254,A19,OrderItems!$G$2:$G$1254) -> 1201.5 | I19: =SUMIF(OrderItems!$B$2:$B$1254,A19,OrderItems!$K$2:$K$1254) -> 542.14 | J19: =H19-I19 -> 659.36 | K19: =IF(D19="","",TEXT(D19,"YYYY-MM")) -> 2023-01 | L19: =IFERROR(INDEX(Customers!$G$2:$G$61,MATCH(B19,Customers!$A$2:$A$61,0)),"") -> Consumer | M19: =IFERROR(INDEX(Employees!$B$2:$B$37,MATCH(C19,Employees!$A$2:$A$37,0))&" "&INDEX(Employees!$C$2:$C$37,MATCH(C19,Employees!$A$2:$A$37,0)),"") -> Daniel Brown | N19: =IF(E19="","",E19-D19) -> 5
A20: 19 | B20: 12 | C20: 8 | D20: 2025-02-17 | E20: 2025-02-26 | F20: Delivered | G20: Middle East | H20: =SUMIF(OrderItems!$B$2:$B$1254,A20,OrderItems!$G$2:$G$1254) -> 1421.3825 | I20: =SUMIF(OrderItems!$B$2:$B$1254,A20,OrderItems!$K$2:$K$1254) -> 816.94 | J20: =H20-I20 -> 604.4425 | K20: =IF(D20="","",TEXT(D20,"YYYY-MM")) -> 2025-02 | L20: =IFERROR(INDEX(Customers!$G$2:$G$61,MATCH(B20,Customers!$A$2:$A$61,0)),"") -> Small Business | M20: =IFERROR(INDEX(Employees!$B$2:$B$37,MATCH(C20,Employees!$A$2:$A$37,0))&" "&INDEX(Employees!$C$2:$C$37,MATCH(C20,Employees!$A$2:$A$37,0)),"") -> John Gonzalez | N20: =IF(E20="","",E20-D20) -> 9
A21: 20 | B21: 37 | C21: 10 | D21: 2025-05-05 | E21: 2025-05-07 | F21: Shipped | G21: Latin America | H21: =SUMIF(OrderItems!$B$2:$B$1254,A21,OrderItems!$G$2:$G$1254) -> 888 | I21: =SUMIF(OrderItems!$B$2:$B$1254,A21,OrderItems!$K$2:$K$1254) -> 682.2 | J21: =H21-I21 -> 205.8 | K21: =IF(D21="","",TEXT(D21,"YYYY-MM")) -> 2025-05 | L21: =IFERROR(INDEX(Customers!$G$2:$G$61,MATCH(B21,Customers!$A$2:$A$61,0)),"") -> Corporate | M21: =IFERROR(INDEX(Employees!$B$2:$B$37,MATCH(C21,Employees!$A$2:$A$37,0))&" "&INDEX(Employees!$C$2:$C$37,MATCH(C21,Employees!$A$2:$A$37,0)),"") -> John Moore | N21: =IF(E21="","",E21-D21) -> 2
A22: 21 | B22: 54 | C22: 9 | D22: 2023-06-30 | F22: Cancelled | G22: North America | H22: =SUMIF(OrderItems!$B$2:$B$1254,A22,OrderItems!$G$2:$G$1254) -> 3516.547 | I22: =SUMIF(OrderItems!$B$2:$B$1254,A22,OrderItems!$K$2:$K$1254) -> 2134.38 | J22: =H22-I22 -> 1382.167 | K22: =IF(D22="","",TEXT(D22,"YYYY-MM")) -> 2023-06 | L22: =IFERROR(INDEX(Customers!$G$2:$G$61,MATCH(B22,Customers!$A$2:$A$61,0)),"") -> Corporate | M22: =IFERROR(INDEX(Employees!$B$2:$B$37,MATCH(C22,Employees!$A$2:$A$37,0))&" "&INDEX(Employees!$C$2:$C$37,MATCH(C22,Employees!$A$2:$A$37,0)),"") -> William Johnson | N22: =IF(E22="","",E22-D22)
A23: 22 | B23: 56 | C23: 9 | D23: 2024-11-26 | E23: 2024-12-02 | F23: Delivered | G23: Europe | H23: =SUMIF(OrderItems!$B$2:$B$1254,A23,OrderItems!$G$2:$G$1254) -> 280.584 | I23: =SUMIF(OrderItems!$B$2:$B$1254,A23,OrderItems!$K$2:$K$1254) -> 150.18 | J23: =H23-I23 -> 130.404 | K23: =IF(D23="","",TEXT(D23,"YYYY-MM")) -> 2024-11 | L23: =IFERROR(INDEX(Customers!$G$2:$G$61,MATCH(B23,Customers!$A$2:$A$61,0)),"") -> Consumer | M23: =IFERROR(INDEX(Employees!$B$2:$B$37,MATCH(C23,Employees!$A$2:$A$37,0))&" "&INDEX(Employees!$C$2:$C$37,MATCH(C23,Employees!$A$2:$A$37,0)),"") -> William Johnson | N23: =IF(E23="","",E23-D23) -> 6
A24: 23 | B24: 58 | C24: 9 | D24: 2024-12-20 | E24: 2024-12-24 | F24: Delivered | G24: North America | H24: =SUMIF(OrderItems!$B$2:$B$1254,A24,OrderItems!$G$2:$G$1254) -> 1795.527 | I24: =SUMIF(OrderItems!$B$2:$B$1254,A24,OrderItems!$K$2:$K$1254) -> 966.75 | J24: =H24-I24 -> 828.777 | K24: =IF(D24="","",TEXT(D24,"YYYY-MM")) -> 2024-12 | L24: =IFERROR(INDEX(Customers!$G$2:$G$61,MATCH(B24,Customers!$A$2:$A$61,0)),"") -> Consumer | M24: =IFERROR(INDEX(Employees!$B$2:$B$37,MATCH(C24,Employees!$A$2:$A$37,0))&" "&INDEX(Employees!$C$2:$C$37,MATCH(C24,Employees!$A$2:$A$37,0)),"") -> William Johnson | N24: =IF(E24="","",E24-D24) -> 4
A25: 24 | B25: 12 | C25: 10 | D25: 2025-08-08 | E25: 2025-08-18 | F25: Returned | G25: Middle East | H25: =SUMIF(OrderItems!$B$2:$B$1254,A25,OrderItems!$G$2:$G$1254) -> 8015.696 | I25: =SUMIF(OrderItems!$B$2:$B$1254,A25,OrderItems!$K$2:$K$1254) -> 4105.51 | J25: =H25-I25 -> 3910.186 | K25: =IF(D25="","",TEXT(D25,"YYYY-MM")) -> 2025-08 | L25: =IFERROR(INDEX(Customers!$G$2:$G$61,MATCH(B25,Customers!$A$2:$A$61,0)),"") -> Small Business | M25: =IFERROR(INDEX(Employees!$B$2:$B$37,MATCH(C25,Employees!$A$2:$A$37,0))&" "&INDEX(Employees!$C$2:$C$37,MATCH(C25,Employees!$A$2:$A$37,0)),"") -> John Moore | N25: =IF(E25="","",E25-D25) -> 10
A26: 25 | B26: 20 | C26: 10 | D26: 2025-07-14 | E26: 2025-07-15 | F26: Delivered | G26: Asia Pacific | H26: =SUMIF(OrderItems!$B$2:$B$1254,A26,OrderItems!$G$2:$G$1254) -> 6102.5265 | I26: =SUMIF(OrderItems!$B$2:$B$1254,A26,OrderItems!$K$2:$K$1254) -> 3846.08 | J26: =H26-I26 -> 2256.4465 | K26: =IF(D26="","",TEXT(D26,"YYYY-MM")) -> 2025-07 | L26: =IFERROR(INDEX(Customers!$G$2:$G$61,MATCH(B26,Customers!$A$2:$A$61,0)),"") -> Corporate | M26: =IFERROR(INDEX(Employees!$B$2:$B$37,MATCH(C26,Employees!$A$2:$A$37,0))&" "&INDEX(Employees!$C$2:$C$37,MATCH(C26,Employees!$A$2:$A$37,0)),"") -> John Moore | N26: =IF(E26="","",E26-D26) -> 1
A27: 26 | B27: 29 | C27: 8 | D27: 2024-10-20 | E27: 2024-10-29 | F27: Returned | G27: Europe | H27: =SUMIF(OrderItems!$B$2:$B$1254,A27,OrderItems!$G$2:$G$1254) -> 621.68 | I27: =SUMIF(OrderItems!$B$2:$B$1254,A27,OrderItems!$K$2:$K$1254) -> 407.9 | J27: =H27-I27 -> 213.78 | K27: =IF(D27="","",TEXT(D27,"YYYY-MM")) -> 2024-10 | L27: =IFERROR(INDEX(Customers!$G$2:$G$61,MATCH(B27,Customers!$A$2:$A$61,0)),"") -> Consumer | M27: =IFERROR(INDEX(Employees!$B$2:$B$37,MATCH(C27,Employees!$A$2:$A$37,0))&" "&INDEX(Employees!$C$2:$C$37,MATCH(C27,Employees!$A$2:$A$37,0)),"") -> John Gonzalez | N27: =IF(E27="","",E27-D27) -> 9
A28: 27 | B28: 3 | C28: 8 | D28: 2025-06-15 | E28: 2025-06-24 | F28: Returned | G28: Middle East | H28: =SUMIF(OrderItems!$B$2:$B$1254,A28,OrderItems!$G$2:$G$1254) -> 8595.701 | I28: =SUMIF(OrderItems!$B$2:$B$1254,A28,OrderItems!$K$2:$K$1254) -> 4781.89 | J28: =H28-I28 -> 3813.811 | K28: =IF(D28="","",TEXT(D28,"YYYY-MM")) -> 2025-06 | L28: =IFERROR(INDEX(Customers!$G$2:$G$61,MATCH(B28,Customers!$A$2:$A$61,0)),"") -> Consumer | M28: =IFERROR(INDEX(Employees!$B$2:$B$37,MATCH(C28,Employees!$A$2:$A$37,0))&" "&INDEX(Employees!$C$2:$C$37,MATCH(C28,Employees!$A$2:$A$37,0)),"") -> John Gonzalez | N28: =IF(E28="","",E28-D28) -> 9
A29: 28 | B29: 22 | C29: 1 | D29: 2023-10-17 | F29: Pending | G29: Asia Pacific | H29: =SUMIF(OrderItems!$B$2:$B$1254,A29,OrderItems!$G$2:$G$1254) -> 3423.882 | I29: =SUMIF(OrderItems!$B$2:$B$1254,A29,OrderItems!$K$2:$K$1254) -> 2113.16 | J29: =H29-I29 -> 1310.722 | K29: =IF(D29="","",TEXT(D29,"YYYY-MM")) -> 2023-10 | L29: =IFERROR(INDEX(Customers!$G$2:$G$61,MATCH(B29,Customers!$A$2:$A$61,0)),"") -> Small Business | M29: =IFERROR(INDEX(Employees!$B$2:$B$37,MATCH(C29,Employees!$A$2:$A$37,0))&" "&INDEX(Employees!$C$2:$C$37,MATCH(C29,Employees!$A$2:$A$37,0)),"") -> Daniel Brown | N29: =IF(E29="","",E29-D29)
A30: 29 | B30: 33 | C30: 9 | D30: 2023-02-07 | F30: Pending | G30: Asia Pacific | H30: =SUMIF(OrderItems!$B$2:$B$1254,A30,OrderItems!$G$2:$G$1254) -> 1646.56 | I30: =SUMIF(OrderItems!$B$2:$B$1254,A30,OrderItems!$K$2:$K$1254) -> 1130.08 | J30: =H30-I30 -> 516.48 | K30: =IF(D30="","",TEXT(D30,"YYYY-MM")) -> 2023-02 | L30: =IFERROR(INDEX(Customers!$G$2:$G$61,MATCH(B30,Customers!$A$2:$A$61,0)),"") -> Consumer | M30: =IFERROR(INDEX(Employees!$B$2:$B$37,MATCH(C30,Employees!$A$2:$A$37,0))&" "&INDEX(Employees!$C$2:$C$37,MATCH(C30,Employees!$A$2:$A$37,0)),"") -> William Johnson | N30: =IF(E30="","",E30-D30)
A31: 30 | B31: 55 | C31: 1 | D31: 2025-11-05 | E31: 2025-11-11 | F31: Delivered | G31: Middle East | H31: =SUMIF(OrderItems!$B$2:$B$1254,A31,OrderItems!$G$2:$G$1254) -> 334.98 | I31: =SUMIF(OrderItems!$B$2:$B$1254,A31,OrderItems!$K$2:$K$1254) -> 177.75 | J31: =H31-I31 -> 157.23 | K31: =IF(D31="","",TEXT(D31,"YYYY-MM")) -> 2025-11 | L31: =IFERROR(INDEX(Customers!$G$2:$G$61,MATCH(B31,Customers!$A$2:$A$61,0)),"") -> Consumer | M31: =IFERROR(INDEX(Employees!$B$2:$B$37,MATCH(C31,Employees!$A$2:$A$37,0))&" "&INDEX(Employees!$C$2:$C$37,MATCH(C31,Employees!$A$2:$A$37,0)),"") -> Daniel Brown | N31: =IF(E31="","",E31-D31) -> 6
A32: 31 | B32: 47 | C32: 10 | D32: 2023-03-31 | F32: Cancelled | G32: Asia Pacific | H32: =SUMIF(OrderItems!$B$2:$B$1254,A32,OrderItems!$G$2:$G$1254) -> 4387.64 | I32: =SUMIF(OrderItems!$B$2:$B$1254,A32,OrderItems!$K$2:$K$1254) -> 2796.38 | J32: =H32-I32 -> 1591.26 | K32: =IF(D32="","",TEXT(D32,"YYYY-MM")) -> 2023-03 | L32: =IFERROR(INDEX(Customers!$G$2:$G$61,MATCH(B32,Customers!$A$2:$A$61,0)),"") -> Corporate | M32: =IFERROR(INDEX(Employees!$B$2:$B$37,MATCH(C32,Employees!$A$2:$A$37,0))&" "&INDEX(Employees!$C$2:$C$37,MATCH(C32,Employees!$A$2:$A$37,0)),"") -> John Moore | N32: =IF(E32="","",E32-D32)
A33: 32 | B33: 35 | C33: 8 | D33: 2024-09-25 | E33: 2024-09-29 | F33: Returned | G33: Asia Pacific | H33: =SUMIF(OrderItems!$B$2:$B$1254,A33,OrderItems!$G$2:$G$1254) -> 9700.49 | I33: =SUMIF(OrderItems!$B$2:$B$1254,A33,OrderItems!$K$2:$K$1254) -> 6070.53 | J33: =H33-I33 -> 3629.96 | K33: =IF(D33="","",TEXT(D33,"YYYY-MM")) -> 2024-09 | L33: =IFERROR(INDEX(Customers!$G$2:$G$61,MATCH(B33,Customers!$A$2:$A$61,0)),"") -> Consumer | M33: =IFERROR(INDEX(Employees!$B$2:$B$37,MATCH(C33,Employees!$A$2:$A$37,0))&" "&INDEX(Employees!$C$2:$C$37,MATCH(C33,Employees!$A$2:$A$37,0)),"") -> John Gonzalez | N33: =IF(E33="","",E33-D33) -> 4
A34: 33 | B34: 56 | C34: 9 | D34: 2023-07-30 | E34: 2023-08-04 | F34: Delivered | G34: North America | H34: =SUMIF(OrderItems!$B$2:$B$1254,A34,OrderItems!$G$2:$G$1254) -> 4664.93 | I34: =SUMIF(OrderItems!$B$2:$B$1254,A34,OrderItems!$K$2:$K$1254) -> 2642.02 | J34: =H34-I34 -> 2022.91 | K34: =IF(D34="","",TEXT(D34,"YYYY-MM")) -> 2023-07 | L34: =IFERROR(INDEX(Customers!$G$2:$G$61,MATCH(B34,Customers!$A$2:$A$61,0)),"") -> Consumer | M34: =IFERROR(INDEX(Employees!$B$2:$B$37,MATCH(C34,Employees!$A$2:$A$37,0))&" "&INDEX(Employees!$C$2:$C$37,MATCH(C34,Employees!$A$2:$A$37,0)),"") -> William Johnson | N34: =IF(E34="","",E34-D34) -> 5
A35: 34 | B35: 57 | C35: 9 | D35: 2023-02-24 | F35: Cancelled | G35: North America | H35: =SUMIF(OrderItems!$B$2:$B$1254,A35,OrderItems!$G$2:$G$1254) -> 3687.48 | I35: =SUMIF(OrderItems!$B$2:$B$1254,A35,OrderItems!$K$2:$K$1254) -> 2439.78 | J35: =H35-I35 -> 1247.7 | K35: =IF(D35="","",TEXT(D35,"YYYY-MM")) -> 2023-02 | L35: =IFERROR(INDEX(Customers!$G$2:$G$61,MATCH(B35,Customers!$A$2:$A$61,0)),"") -> Small Business | M35: =IFERROR(INDEX(Employees!$B$2:$B$37,MATCH(C35,Employees!$A$2:$A$37,0))&" "&INDEX(Employees!$C$2:$C$37,MATCH(C35,Employees!$A$2:$A$37,0)),"") -> William Johnson | N35: =IF(E35="","",E35-D35)
A36: 35 | B36: 10 | C36: 8 | D36: 2023-03-20 | E36: 2023-03-28 | F36: Shipped | G36: Europe | H36: =SUMIF(OrderItems!$B$2:$B$1254,A36,OrderItems!$G$2:$G$1254) -> 6362.917 | I36: =SUMIF(OrderItems!$B$2:$B$1254,A36,OrderItems!$K$2:$K$1254) -> 3875.47 | J36: =H36-I36 -> 2487.447 | K36: =IF(D36="","",TEXT(D36,"YYYY-MM")) -> 2023-03 | L36: =IFERROR(INDEX(Customers!$G$2:$G$61,MATCH(B36,Customers!$A$2:$A$61,0)),"") -> Corporate | M36: =IFERROR(INDEX(Employees!$B$2:$B$37,MATCH(C36,Employees!$A$2:$A$37,0))&" "&INDEX(Employees!$C$2:$C$37,MATCH(C36,Employees!$A$2:$A$37,0)),"") -> John Gonzalez | N36: =IF(E36="","",E36-D36) -> 8
A37: 36 | B37: 50 | C37: 9 | D37: 2024-05-01 | E37: 2024-05-03 | F37: Shipped | G37: North America | H37: =SUMIF(OrderItems!$B$2:$B$1254,A37,OrderItems!$G$2:$G$1254) -> 4564 | I37: =SUMIF(OrderItems!$B$2:$B$1254,A37,OrderItems!$K$2:$K$1254) -> 2495.96 | J37: =H37-I37 -> 2068.04 | K37: =IF(D37="","",TEXT(D37,"YYYY-MM")) -> 2024-05 | L37: =IFERROR(INDEX(Customers!$G$2:$G$61,MATCH(B37,Customers!$A$2:$A$61,0)),"") -> Consumer | M37: =IFERROR(INDEX(Employees!$B$2:$B$37,MATCH(C37,Employees!$A$2:$A$37,0))&" "&INDEX(Employees!$C$2:$C$37,MATCH(C37,Employees!$A$2:$A$37,0)),"") -> William Johnson | N37: =IF(E37="","",E37-D37) -> 2
A38: 37 | B38: 41 | C38: 8 | D38: 2023-10-22 | E38: 2023-10-29 | F38: Shipped | G38: North America | H38: =SUMIF(OrderItems!$B$2:$B$1254,A38,OrderItems!$G$2:$G$1254) -> 6554.511 | I38: =SUMIF(OrderItems!$B$2:$B$1254,A38,OrderItems!$K$2:$K$1254) -> 4024 | J38: =H38-I38 -> 2530.511 | K38: =IF(D38="","",TEXT(D38,"YYYY-MM")) -> 2023-10 | L38: =IFERROR(INDEX(Customers!$G$2:$G$61,MATCH(B38,Customers!$A$2:$A$61,0)),"") -> Small Business | M38: =IFERROR(INDEX(Employees!$B$2:$B$37,MATCH(C38,Employees!$A$2:$A$37,0))&" "&INDEX(Employees!$C$2:$C$37,MATCH(C38,Employees!$A$2:$A$37,0)),"") -> John Gonzalez | N38: =IF(E38="","",E38-D38) -> 7
A39: 38 | B39: 56 | C39: 10 | D39: 2023-03-31 | F39: Cancelled | G39: Asia Pacific | H39: =SUMIF(OrderItems!$B$2:$B$1254,A39,OrderItems!$G$2:$G$1254) -> 1079.508 | I39: =SUMIF(OrderItems!$B$2:$B$1254,A39,OrderItems!$K$2:$K$1254) -> 674.44 | J39: =H39-I39 -> 405.068 | K39: =IF(D39="","",TEXT(D39,"YYYY-MM")) -> 2023-03 | L39: =IFERROR(INDEX(Customers!$G$2:$G$61,MATCH(B39,Customers!$A$2:$A$61,0)),"") -> Consumer | M39: =IFERROR(INDEX(Employees!$B$2:$B$37,MATCH(C39,Employees!$A$2:$A$37,0))&" "&INDEX(Employees!$C$2:$C$37,MATCH(C39,Employees!$A$2:$A$37,0)),"") -> John Moore | N39: =IF(E39="","",E39-D39)
A40: 39 | B40: 38 | C40: 9 | D40: 2023-10-01 | E40: 2023-10-07 | F40: Delivered | G40: Middle East | H40: =SUMIF(OrderItems!$B$2:$B$1254,A40,OrderItems!$G$2:$G$1254) -> 3876.176 | I40: =SUMIF(OrderItems!$B$2:$B$1254,A40,OrderItems!$K$2:$K$1254) -> 2993.24 | J40: =H40-I40 -> 882.936 | K40: =IF(D40="","",TEXT(D40,"YYYY-MM")) -> 2023-10 | L40: =IFERROR(INDEX(Customers!$G$2:$G$61,MATCH(B40,Customers!$A$2:$A$61,0)),"") -> Small Business | M40: =IFERROR(INDEX(Employees!$B$2:$B$37,MATCH(C40,Employees!$A$2:$A$37,0))&" "&INDEX(Employees!$C$2:$C$37,MATCH(C40,Employees!$A$2:$A$37,0)),"") -> William Johnson | N40: =IF(E40="","",E40-D40) -> 6
A41: 40 | B41: 46 | C41: 10 | D41: 2023-03-17 | E41: 2023-03-21 | F41: Shipped | G41: North America | H41: =SUMIF(OrderItems!$B$2:$B$1254,A41,OrderItems!$G$2:$G$1254) -> 2911.111 | I41: =SUMIF(OrderItems!$B$2:$B$1254,A41,OrderItems!$K$2:$K$1254) -> 1878.12 | J41: =H41-I41 -> 1032.991 | K41: =IF(D41="","",TEXT(D41,"YYYY-MM")) -> 2023-03 | L41: =IFERROR(INDEX(Customers!$G$2:$G$61,MATCH(B41,Customers!$A$2:$A$61,0)),"") -> Small Business | M41: =IFERROR(INDEX(Employees!$B$2:$B$37,MATCH(C41,Employees!$A$2:$A$37,0))&" "&INDEX(Employees!$C$2:$C$37,MATCH(C41,Employees!$A$2:$A$37,0)),"") -> John Moore | N41: =IF(E41="","",E41-D41) -> 4
A42: 41 | B42: 17 | C42: 1 | D42: 2024-01-27 | E42: 2024-02-02 | F42: Shipped | G42: North America | H42: =SUMIF(OrderItems!$B$2:$B$1254,A42,OrderItems!$G$2:$G$1254) -> 5293.05 | I42: =SUMIF(OrderItems!$B$2:$B$1254,A42,OrderItems!$K$2:$K$1254) -> 2981.21 | J42: =H42-I42 -> 2311.84 | K42: =IF(D42="","",TEXT(D42,"YYYY-MM")) -> 2024-01 | L42: =IFERROR(INDEX(Customers!$G$2:$G$61,MATCH(B42,Customers!$A$2:$A$61,0)),"") -> Small Business | M42: =IFERROR(INDEX(Employees!$B$2:$B$37,MATCH(C42,Employees!$A$2:$A$37,0))&" "&INDEX(Employees!$C$2:$C$37,MATCH(C42,Employees!$A$2:$A$37,0)),"") -> Daniel Brown | N42: =IF(E42="","",E42-D42) -> 6
A43: 42 | B43: 24 | C43: 9 | D43: 2023-06-19 | F43: Cancelled | G43: North America | H43: =SUMIF(OrderItems!$B$2:$B$1254,A43,OrderItems!$G$2:$G$1254) -> 3193.494 | I43: =SUMIF(OrderItems!$B$2:$B$1254,A43,OrderItems!$K$2:$K$1254) -> 1598.48 | J43: =H43-I43 -> 1595.014 | K43: =IF(D43="","",TEXT(D43,"YYYY-MM")) -> 2023-06 | L43: =IFERROR(INDEX(Customers!$G$2:$G$61,MATCH(B43,Customers!$A$2:$A$61,0)),"") -> Consumer | M43: =IFERROR(INDEX(Employees!$B$2:$B$37,MATCH(C43,Employees!$A$2:$A$37,0))&" "&INDEX(Employees!$C$2:$C$37,MATCH(C43,Employees!$A$2:$A$37,0)),"") -> William Johnson | N43: =IF(E43="","",E43-D43)
A44: 43 | B44: 46 | C44: 10 | D44: 2023-12-08 | E44: 2023-12-14 | F44: Returned | G44: Latin America | H44: =SUMIF(OrderItems!$B$2:$B$1254,A44,OrderItems!$G$2:$G$1254) -> 1673.19 | I44: =SUMIF(OrderItems!$B$2:$B$1254,A44,OrderItems!$K$2:$K$1254) -> 1206.48 | J44: =H44-I44 -> 466.71 | K44: =IF(D44="","",TEXT(D44,"YYYY-MM")) -> 2023-12 | L44: =IFERROR(INDEX(Customers!$G$2:$G$61,MATCH(B44,Customers!$A$2:$A$61,0)),"") -> Small Business | M44: =IFERROR(INDEX(Employees!$B$2:$B$37,MATCH(C44,Employees!$A$2:$A$37,0))&" "&INDEX(Employees!$C$2:$C$37,MATCH(C44,Employees!$A$2:$A$37,0)),"") -> John Moore | N44: =IF(E44="","",E44-D44) -> 6
A45: 44 | B45: 5 | C45: 10 | D45: 2025-01-14 | E45: 2025-01-15 | F45: Delivered | G45: Europe | H45: =SUMIF(OrderItems!$B$2:$B$1254,A45,OrderItems!$G$2:$G$1254) -> 6247.251 | I45: =SUMIF(OrderItems!$B$2:$B$1254,A45,OrderItems!$K$2:$K$1254) -> 3849.12 | J45: =H45-I45 -> 2398.131 | K45: =IF(D45="","",TEXT(D45,"YYYY-MM")) -> 2025-01 | L45: =IFERROR(INDEX(Customers!$G$2:$G$61,MATCH(B45,Customers!$A$2:$A$61,0)),"") -> Consumer | M45: =IFERROR(INDEX(Employees!$B$2:$B$37,MATCH(C45,Employees!$A$2:$A$37,0))&" "&INDEX(Employees!$C$2:$C$37,MATCH(C45,Employees!$A$2:$A$37,0)),"") -> John Moore | N45: =IF(E45="","",E45-D45) -> 1
A46: 45 | B46: 24 | C46: 10 | D46: 2023-06-07 | E46: 2023-06-16 | F46: Delivered | G46: Asia Pacific | H46: =SUMIF(OrderItems!$B$2:$B$1254,A46,OrderItems!$G$2:$G$1254) -> 9848.7835 | I46: =SUMIF(OrderItems!$B$2:$B$1254,A46,OrderItems!$K$2:$K$1254) -> 4974.66 | J46: =H46-I46 -> 4874.1235 | K46: =IF(D46="","",TEXT(D46,"YYYY-MM")) -> 2023-06 | L46: =IFERROR(INDEX(Customers!$G$2:$G$61,MATCH(B46,Customers!$A$2:$A$61,0)),"") -> Consumer | M46: =IFERROR(INDEX(Employees!$B$2:$B$37,MATCH(C46,Employees!$A$2:$A$37,0))&" "&INDEX(Employees!$C$2:$C$37,MATCH(C46,Employees!$A$2:$A$37,0)),"") -> John Moore | N46: =IF(E46="","",E46-D46) -> 9
A47: 46 | B47: 46 | C47: 10 | D47: 2024-03-15 | E47: 2024-03-23 | F47: Shipped | G47: Europe | H47: =SUMIF(OrderItems!$B$2:$B$1254,A47,OrderItems!$G$2:$G$1254) -> 353.039 | I47: =SUMIF(OrderItems!$B$2:$B$1254,A47,OrderItems!$K$2:$K$1254) -> 217.62 | J47: =H47-I47 -> 135.419 | K47: =IF(D47="","",TEXT(D47,"YYYY-MM")) -> 2024-03 | L47: =IFERROR(INDEX(Customers!$G$2:$G$61,MATCH(B47,Customers!$A$2:$A$61,0)),"") -> Small Business | M47: =IFERROR(INDEX(Employees!$B$2:$B$37,MATCH(C47,Employees!$A$2:$A$37,0))&" "&INDEX(Employees!$C$2:$C$37,MATCH(C47,Employees!$A$2:$A$37,0)),"") -> John Moore | N47: =IF(E47="","",E47-D47) -> 8
A48: 47 | B48: 6 | C48: 9 | D48: 2024-12-12 | E48: 2024-12-21 | F48: Delivered | G48: Middle East | H48: =SUMIF(OrderItems!$B$2:$B$1254,A48,OrderItems!$G$2:$G$1254) -> 3906.976 | I48: =SUMIF(OrderItems!$B$2:$B$1254,A48,OrderItems!$K$2:$K$1254) -> 1861.36 | J48: =H48-I48 -> 2045.616 | K48: =IF(D48="","",TEXT(D48,"YYYY-MM")) -> 2024-12 | L48: =IFERROR(INDEX(Customers!$G$2:$G$61,MATCH(B48,Customers!$A$2:$A$61,0)),"") -> Consumer | M48: =IFERROR(INDEX(Employees!$B$2:$B$37,MATCH(C48,Employees!$A$2:$A$37,0))&" "&INDEX(Employees!$C$2:$C$37,MATCH(C48,Employees!$A$2:$A$37,0)),"") -> William Johnson | N48: =IF(E48="","",E48-D48) -> 9
A49: 48 | B49: 16 | C49: 10 | D49: 2023-02-23 | F49: Pending | G49: Middle East | H49: =SUMIF(OrderItems!$B$2:$B$1254,A49,OrderItems!$G$2:$G$1254) -> 6831.217 | I49: =SUMIF(OrderItems!$B$2:$B$1254,A49,OrderItems!$K$2:$K$1254) -> 4697.38 | J49: =H49-I49 -> 2133.837 | K49: =IF(D49="","",TEXT(D49,"YYYY-MM")) -> 2023-02 | L49: =IFERROR(INDEX(Customers!$G$2:$G$61,MATCH(B49,Customers!$A$2:$A$61,0)),"") -> Small Business | M49: =IFERROR(INDEX(Employees!$B$2:$B$37,MATCH(C49,Employees!$A$2:$A$37,0))&" "&INDEX(Employees!$C$2:$C$37,MATCH(C49,Employees!$A$2:$A$37,0)),"") -> John Moore | N49: =IF(E49="","",E49-D49)
A50: 49 | B50: 42 | C50: 1 | D50: 2025-07-10 | E50: 2025-07-19 | F50: Returned | G50: Asia Pacific | H50: =SUMIF(OrderItems!$B$2:$B$1254,A50,OrderItems!$G$2:$G$1254) -> 3785.568 | I50: =SUMIF(OrderItems!$B$2:$B$1254,A50,OrderItems!$K$2:$K$1254) -> 2282.09 | J50: =H50-I50 -> 1503.478 | K50: =IF(D50="","",TEXT(D50,"YYYY-MM")) -> 2025-07 | L50: =IFERROR(INDEX(Customers!$G$2:$G$61,MATCH(B50,Customers!$A$2:$A$61,0)),"") -> Small Business | M50: =IFERROR(INDEX(Employees!$B$2:$B$37,MATCH(C50,Employees!$A$2:$A$37,0))&" "&INDEX(Employees!$C$2:$C$37,MATCH(C50,Employees!$A$2:$A$37,0)),"") -> Daniel Brown | N50: =IF(E50="","",E50-D50) -> 9
A51: 50 | B51: 20 | C51: 8 | D51: 2023-11-28 | F51: Pending | G51: Europe | H51: =SUMIF(OrderItems!$B$2:$B$1254,A51,OrderItems!$G$2:$G$1254) -> 4032.915 | I51: =SUMIF(OrderItems!$B$2:$B$1254,A51,OrderItems!$K$2:$K$1254) -> 2249.98 | J51: =H51-I51 -> 1782.935 | K51: =IF(D51="","",TEXT(D51,"YYYY-MM")) -> 2023-11 | L51: =IFERROR(INDEX(Customers!$G$2:$G$61,MATCH(B51,Customers!$A$2:$A$61,0)),"") -> Corporate | M51: =IFERROR(INDEX(Employees!$B$2:$B$37,MATCH(C51,Employees!$A$2:$A$37,0))&" "&INDEX(Employees!$C$2:$C$37,MATCH(C51,Employees!$A$2:$A$37,0)),"") -> John Gonzalez | N51: =IF(E51="","",E51-D51)
A52: 51 | B52: 33 | C52: 8 | D52: 2023-11-12 | E52: 2023-11-22 | F52: Delivered | G52: Middle East | H52: =SUMIF(OrderItems!$B$2:$B$1254,A52,OrderItems!$G$2:$G$1254) -> 4438.392 | I52: =SUMIF(OrderItems!$B$2:$B$1254,A52,OrderItems!$K$2:$K$1254) -> 2847.04 | J52: =H52-I52 -> 1591.352 | K52: =IF(D52="","",TEXT(D52,"YYYY-MM")) -> 2023-11 | L52: =IFERROR(INDEX(Customers!$G$2:$G$61,MATCH(B52,Customers!$A$2:$A$61,0)),"") -> Consumer | M52: =IFERROR(INDEX(Employees!$B$2:$B$37,MATCH(C52,Employees!$A$2:$A$37,0))&" "&INDEX(Employees!$C$2:$C$37,MATCH(C52,Employees!$A$2:$A$37,0)),"") -> John Gonzalez | N52: =IF(E52="","",E52-D52) -> 10
A53: 52 | B53: 40 | C53: 1 | D53: 2025-10-16 | E53: 2025-10-21 | F53: Shipped | G53: Latin America | H53: =SUMIF(OrderItems!$B$2:$B$1254,A53,OrderItems!$G$2:$G$1254) -> 1692.741 | I53: =SUMIF(OrderItems!$B$2:$B$1254,A53,OrderItems!$K$2:$K$1254) -> 1005.93 | J53: =H53-I53 -> 686.811 | K53: =IF(D53="","",TEXT(D53,"YYYY-MM")) -> 2025-10 | L53: =IFERROR(INDEX(Customers!$G$2:$G$61,MATCH(B53,Customers!$A$2:$A$61,0)),"") -> Corporate | M53: =IFERROR(INDEX(Employees!$B$2:$B$37,MATCH(C53,Employees!$A$2:$A$37,0))&" "&INDEX(Employees!$C$2:$C$37,MATCH(C53,Employees!$A$2:$A$37,0)),"") -> Daniel Brown | N53: =IF(E53="","",E53-D53) -> 5
A54: 53 | B54: 29 | C54: 10 | D54: 2025-09-18 | E54: 2025-09-22 | F54: Returned | G54: Asia Pacific | H54: =SUMIF(OrderItems!$B$2:$B$1254,A54,OrderItems!$G$2:$G$1254) -> 10479.784 | I54: =SUMIF(OrderItems!$B$2:$B$1254,A54,OrderItems!$K$2:$K$1254) -> 5849.19 | J54: =H54-I54 -> 4630.594 | K54: =IF(D54="","",TEXT(D54,"YYYY-MM")) -> 2025-09 | L54: =IFERROR(INDEX(Customers!$G$2:$G$61,MATCH(B54,Customers!$A$2:$A$61,0)),"") -> Consumer | M54: =IFERROR(INDEX(Employees!$B$2:$B$37,MATCH(C54,Employees!$A$2:$A$37,0))&" "&INDEX(Employees!$C$2:$C$37,MATCH(C54,Employees!$A$2:$A$37,0)),"") -> John Moore | N54: =IF(E54="","",E54-D54) -> 4
A55: 54 | B55: 7 | C55: 1 | D55: 2024-08-17 | F55: Cancelled | G55: Middle East | H55: =SUMIF(OrderItems!$B$2:$B$1254,A55,OrderItems!$G$2:$G$1254) -> 8721.87 | I55: =SUMIF(OrderItems!$B$2:$B$1254,A55,OrderItems!$K$2:$K$1254) -> 4726.09 | J55: =H55-I55 -> 3995.78 | K55: =IF(D55="","",TEXT(D55,"YYYY-MM")) -> 2024-08 | L55: =IFERROR(INDEX(Customers!$G$2:$G$61,MATCH(B55,Customers!$A$2:$A$61,0)),"") -> Small Business | M55: =IFERROR(INDEX(Employees!$B$2:$B$37,MATCH(C55,Employees!$A$2:$A$37,0))&" "&INDEX(Employees!$C$2:$C$37,MATCH(C55,Employees!$A$2:$A$37,0)),"") -> Daniel Brown | N55: =IF(E55="","",E55-D55)
A56: 55 | B56: 32 | C56: 1 | D56: 2023-07-04 | F56: Cancelled | G56: Middle East | H56: =SUMIF(OrderItems!$B$2:$B$1254,A56,OrderItems!$G$2:$G$1254) -> 4583.3875 | I56: =SUMIF(OrderItems!$B$2:$B$1254,A56,OrderItems!$K$2:$K$1254) -> 3528.06 | J56: =H56-I56 -> 1055.3275 | K56: =IF(D56="","",TEXT(D56,"YYYY-MM")) -> 2023-07 | L56: =IFERROR(INDEX(Customers!$G$2:$G$61,MATCH(B56,Customers!$A$2:$A$61,0)),"") -> Small Business | M56: =IFERROR(INDEX(Employees!$B$2:$B$37,MATCH(C56,Employees!$A$2:$A$37,0))&" "&INDEX(Employees!$C$2:$C$37,MATCH(C56,Employees!$A$2:$A$37,0)),"") -> Daniel Brown | N56: =IF(E56="","",E56-D56)
A57: 56 | B57: 35 | C57: 1 | D57: 2023-08-09 | F57: Cancelled | G57: Europe | H57: =SUMIF(OrderItems!$B$2:$B$1254,A57,OrderItems!$G$2:$G$1254) -> 2321.3665 | I57: =SUMIF(OrderItems!$B$2:$B$1254,A57,OrderItems!$K$2:$K$1254) -> 1503.86 | J57: =H57-I57 -> 817.5065 | K57: =IF(D57="","",TEXT(D57,"YYYY-MM")) -> 2023-08 | L57: =IFERROR(INDEX(Customers!$G$2:$G$61,MATCH(B57,Customers!$A$2:$A$61,0)),"") -> Consumer | M57: =IFERROR(INDEX(Employees!$B$2:$B$37,MATCH(C57,Employees!$A$2:$A$37,0))&" "&INDEX(Employees!$C$2:$C$37,MATCH(C57,Employees!$A$2:$A$37,0)),"") -> Daniel Brown | N57: =IF(E57="","",E57-D57)
A58: 57 | B58: 36 | C58: 8 | D58: 2025-01-12 | E58: 2025-01-14 | F58: Shipped | G58: Latin America | H58: =SUMIF(OrderItems!$B$2:$B$1254,A58,OrderItems!$G$2:$G$1254) -> 9644.978 | I58: =SUMIF(OrderItems!$B$2:$B$1254,A58,OrderItems!$K$2:$K$1254) -> 5826.65 | J58: =H58-I58 -> 3818.328 | K58: =IF(D58="","",TEXT(D58,"YYYY-MM")) -> 2025-01 | L58: =IFERROR(INDEX(Customers!$G$2:$G$61,MATCH(B58,Customers!$A$2:$A$61,0)),"") -> Corporate | M58: =IFERROR(INDEX(Employees!$B$2:$B$37,MATCH(C58,Employees!$A$2:$A$37,0))&" "&INDEX(Employees!$C$2:$C$37,MATCH(C58,Employees!$A$2:$A$37,0)),"") -> John Gonzalez | N58: =IF(E58="","",E58-D58) -> 2
A59: 58 | B59: 39 | C59: 10 | D59: 2025-10-21 | E59: 2025-10-22 | F59: Delivered | G59: North America | H59: =SUMIF(OrderItems!$B$2:$B$1254,A59,OrderItems!$G$2:$G$1254) -> 3700.664 | I59: =SUMIF(OrderItems!$B$2:$B$1254,A59,OrderItems!$K$2:$K$1254) -> 1876.4 | J59: =H59-I59 -> 1824.264 | K59: =IF(D59="","",TEXT(D59,"YYYY-MM")) -> 2025-10 | L59: =IFERROR(INDEX(Customers!$G$2:$G$61,MATCH(B59,Customers!$A$2:$A$61,0)),"") -> Consumer | M59: =IFERROR(INDEX(Employees!$B$2:$B$37,MATCH(C59,Employees!$A$2:$A$37,0))&" "&INDEX(Employees!$C$2:$C$37,MATCH(C59,Employees!$A$2:$A$37,0)),"") -> John Moore | N59: =IF(E59="","",E59-D59) -> 1
A60: 59 | B60: 21 | C60: 9 | D60: 2023-11-29 | F60: Cancelled | G60: Middle East | H60: =SUMIF(OrderItems!$B$2:$B$1254,A60,OrderItems!$G$2:$G$1254) -> 5595.644 | I60: =SUMIF(OrderItems!$B$2:$B$1254,A60,OrderItems!$K$2:$K$1254) -> 3581.13 | J60: =H60-I60 -> 2014.514 | K60: =IF(D60="","",TEXT(D60,"YYYY-MM")) -> 2023-11 | L60: =IFERROR(INDEX(Customers!$G$2:$G$61,MATCH(B60,Customers!$A$2:$A$61,0)),"") -> Corporate | M60: =IFERROR(INDEX(Employees!$B$2:$B$37,MATCH(C60,Employees!$A$2:$A$37,0))&" "&INDEX(Employees!$C$2:$C$37,MATCH(C60,Employees!$A$2:$A$37,0)),"") -> William Johnson | N60: =IF(E60="","",E60-D60)
A61: 60 | B61: 31 | C61: 1 | D61: 2025-01-24 | F61: Pending | G61: North America | H61: =SUMIF(OrderItems!$B$2:$B$1254,A61,OrderItems!$G$2:$G$1254) -> 6618.753 | I61: =SUMIF(OrderItems!$B$2:$B$1254,A61,OrderItems!$K$2:$K$1254) -> 4091.69 | J61: =H61-I61 -> 2527.063 | K61: =IF(D61="","",TEXT(D61,"YYYY-MM")) -> 2025-01 | L61: =IFERROR(INDEX(Customers!$G$2:$G$61,MATCH(B61,Customers!$A$2:$A$61,0)),"") -> Consumer | M61: =IFERROR(INDEX(Employees!$B$2:$B$37,MATCH(C61,Employees!$A$2:$A$37,0))&" "&INDEX(Employees!$C$2:$C$37,MATCH(C61,Employees!$A$2:$A$37,0)),"") -> Daniel Brown | N61: =IF(E61="","",E61-D61)
A62: 61 | B62: 11 | C62: 10 | D62: 2023-10-30 | E62: 2023-10-31 | F62: Delivered | G62: Middle East | H62: =SUMIF(OrderItems!$B$2:$B$1254,A62,OrderItems!$G$2:$G$1254) -> 318.231 | I62: =SUMIF(OrderItems!$B$2:$B$1254,A62,OrderItems!$K$2:$K$1254) -> 200.06 | J62: =H62-I62 -> 118.171 | K62: =IF(D62="","",TEXT(D62,"YYYY-MM")) -> 2023-10 | L62: =IFERROR(INDEX(Customers!$G$2:$G$61,MATCH(B62,Customers!$A$2:$A$61,0)),"") -> Consumer | M62: =IFERROR(INDEX(Employees!$B$2:$B$37,MATCH(C62,Employees!$A$2:$A$37,0))&" "&INDEX(Employees!$C$2:$C$37,MATCH(C62,Employees!$A$2:$A$37,0)),"") -> John Moore | N62: =IF(E62="","",E62-D62) -> 1
A63: 62 | B63: 10 | C63: 10 | D63: 2024-02-22 | F63: Cancelled | G63: Middle East | H63: =SUMIF(OrderItems!$B$2:$B$1254,A63,OrderItems!$G$2:$G$1254) -> 8056.021 | I63: =SUMIF(OrderItems!$B$2:$B$1254,A63,OrderItems!$K$2:$K$1254) -> 4488.57 | J63: =H63-I63 -> 3567.451 | K63: =IF(D63="","",TEXT(D63,"YYYY-MM")) -> 2024-02 | L63: =IFERROR(INDEX(Customers!$G$2:$G$61,MATCH(B63,Customers!$A$2:$A$61,0)),"") -> Corporate | M63: =IFERROR(INDEX(Employees!$B$2:$B$37,MATCH(C63,Employees!$A$2:$A$37,0))&" "&INDEX(Employees!$C$2:$C$37,MATCH(C63,Employees!$A$2:$A$37,0)),"") -> John Moore | N63: =IF(E63="","",E63-D63)
A64: 63 | B64: 12 | C64: 10 | D64: 2025-12-27 | F64: Pending | G64: Middle East | H64: =SUMIF(OrderItems!$B$2:$B$1254,A64,OrderItems!$G$2:$G$1254) -> 5623.45 | I64: =SUMIF(OrderItems!$B$2:$B$1254,A64,OrderItems!$K$2:$K$1254) -> 3292.95 | J64: =H64-I64 -> 2330.5 | K64: =IF(D64="","",TEXT(D64,"YYYY-MM")) -> 2025-12 | L64: =IFERROR(INDEX(Customers!$G$2:$G$61,MATCH(B64,Customers!$A$2:$A$61,0)),"") -> Small Business | M64: =IFERROR(INDEX(Employees!$B$2:$B$37,MATCH(C64,Employees!$A$2:$A$37,0))&" "&INDEX(Employees!$C$2:$C$37,MATCH(C64,Employees!$A$2:$A$37,0)),"") -> John Moore | N64: =IF(E64="","",E64-D64)
A65: 64 | B65: 50 | C65: 9 | D65: 2024-02-29 | E65: 2024-03-06 | F65: Returned | G65: Latin America | H65: =SUMIF(OrderItems!$B$2:$B$1254,A65,OrderItems!$G$2:$G$1254) -> 9127.0835 | I65: =SUMIF(OrderItems!$B$2:$B$1254,A65,OrderItems!$K$2:$K$1254) -> 4549.66 | J65: =H65-I65 -> 4577.4235 | K65: =IF(D65="","",TEXT(D65,"YYYY-MM")) -> 2024-02 | L65: =IFERROR(INDEX(Customers!$G$2:$G$61,MATCH(B65,Customers!$A$2:$A$61,0)),"") -> Consumer | M65: =IFERROR(INDEX(Employees!$B$2:$B$37,MATCH(C65,Employees!$A$2:$A$37,0))&" "&INDEX(Employees!$C$2:$C$37,MATCH(C65,Employees!$A$2:$A$37,0)),"") -> William Johnson | N65: =IF(E65="","",E65-D65) -> 6
A66: 65 | B66: 3 | C66: 9 | D66: 2023-06-11 | F66: Pending | G66: Latin America | H66: =SUMIF(OrderItems!$B$2:$B$1254,A66,OrderItems!$G$2:$G$1254) -> 4896.5245 | I66: =SUMIF(OrderItems!$B$2:$B$1254,A66,OrderItems!$K$2:$K$1254) -> 2921.84 | J66: =H66-I66 -> 1974.6845 | K66: =IF(D66="","",TEXT(D66,"YYYY-MM")) -> 2023-06 | L66: =IFERROR(INDEX(Customers!$G$2:$G$61,MATCH(B66,Customers!$A$2:$A$61,0)),"") -> Consumer | M66: =IFERROR(INDEX(Employees!$B$2:$B$37,MATCH(C66,Employees!$A$2:$A$37,0))&" "&INDEX(Employees!$C$2:$C$37,MATCH(C66,Employees!$A$2:$A$37,0)),"") -> William Johnson | N66: =IF(E66="","",E66-D66)
A67: 66 | B67: 40 | C67: 8 | D67: 2024-05-11 | E67: 2024-05-20 | F67: Delivered | G67: Europe | H67: =SUMIF(OrderItems!$B$2:$B$1254,A67,OrderItems!$G$2:$G$1254) -> 3939.04 | I67: =SUMIF(OrderItems!$B$2:$B$1254,A67,OrderItems!$K$2:$K$1254) -> 1808.3 | J67: =H67-I67 -> 2130.74 | K67: =IF(D67="","",TEXT(D67,"YYYY-MM")) -> 2024-05 | L67: =IFERROR(INDEX(Customers!$G$2:$G$61,MATCH(B67,Customers!$A$2:$A$61,0)),"") -> Corporate | M67: =IFERROR(INDEX(Employees!$B$2:$B$37,MATCH(C67,Employees!$A$2:$A$37,0))&" "&INDEX(Employees!$C$2:$C$37,MATCH(C67,Employees!$A$2:$A$37,0)),"") -> John Gonzalez | N67: =IF(E67="","",E67-D67) -> 9
A68: 67 | B68: 1 | C68: 8 | D68: 2025-04-13 | E68: 2025-04-21 | F68: Returned | G68: Europe | H68: =SUMIF(OrderItems!$B$2:$B$1254,A68,OrderItems!$G$2:$G$1254) -> 1874.983 | I68: =SUMIF(OrderItems!$B$2:$B$1254,A68,OrderItems!$K$2:$K$1254) -> 1348.18 | J68: =H68-I68 -> 526.803 | K68: =IF(D68="","",TEXT(D68,"YYYY-MM")) -> 2025-04 | L68: =IFERROR(INDEX(Customers!$G$2:$G$61,MATCH(B68,Customers!$A$2:$A$61,0)),"") -> Corporate | M68: =IFERROR(INDEX(Employees!$B$2:$B$37,MATCH(C68,Employees!$A$2:$A$37,0))&" "&INDEX(Employees!$C$2:$C$37,MATCH(C68,Employees!$A$2:$A$37,0)),"") -> John Gonzalez | N68: =IF(E68="","",E68-D68) -> 8
A69: 68 | B69: 60 | C69: 1 | D69: 2025-03-24 | E69: 2025-03-27 | F69: Returned | G69: Asia Pacific | H69: =SUMIF(OrderItems!$B$2:$B$1254,A69,OrderItems!$G$2:$G$1254) -> 1289.565 | I69: =SUMIF(OrderItems!$B$2:$B$1254,A69,OrderItems!$K$2:$K$1254) -> 679.7 | J69: =H69-I69 -> 609.865 | K69: =IF(D69="","",TEXT(D69,"YYYY-MM")) -> 2025-03 | L69: =IFERROR(INDEX(Customers!$G$2:$G$61,MATCH(B69,Customers!$A$2:$A$61,0)),"") -> Consumer | M69: =IFERROR(INDEX(Employees!$B$2:$B$37,MATCH(C69,Employees!$A$2:$A$37,0))&" "&INDEX(Employees!$C$2:$C$37,MATCH(C69,Employees!$A$2:$A$37,0)),"") -> Daniel Brown | N69: =IF(E69="","",E69-D69) -> 3
A70: 69 | B70: 42 | C70: 10 | D70: 2023-10-02 | E70: 2023-10-07 | F70: Returned | G70: Europe | H70: =SUMIF(OrderItems!$B$2:$B$1254,A70,OrderItems!$G$2:$G$1254) -> 107.4315 | I70: =SUMIF(OrderItems!$B$2:$B$1254,A70,OrderItems!$K$2:$K$1254) -> 53.64 | J70: =H70-I70 -> 53.7915 | K70: =IF(D70="","",TEXT(D70,"YYYY-MM")) -> 2023-10 | L70: =IFERROR(INDEX(Customers!$G$2:$G$61,MATCH(B70,Customers!$A$2:$A$61,0)),"") -> Small Business | M70: =IFERROR(INDEX(Employees!$B$2:$B$37,MATCH(C70,Employees!$A$2:$A$37,0))&" "&INDEX(Employees!$C$2:$C$37,MATCH(C70,Employees!$A$2:$A$37,0)),"") -> John Moore | N70: =IF(E70="","",E70-D70) -> 5
A71: 70 | B71: 1 | C71: 9 | D71: 2024-08-27 | E71: 2024-08-30 | F71: Delivered | G71: Middle East | H71: =SUMIF(OrderItems!$B$2:$B$1254,A71,OrderItems!$G$2:$G$1254) -> 4931.6265 | I71: =SUMIF(OrderItems!$B$2:$B$1254,A71,OrderItems!$K$2:$K$1254) -> 2833.62 | J71: =H71-I71 -> 2098.0065 | K71: =IF(D71="","",TEXT(D71,"YYYY-MM")) -> 2024-08 | L71: =IFERROR(INDEX(Customers!$G$2:$G$61,MATCH(B71,Customers!$A$2:$A$61,0)),"") -> Corporate | M71: =IFERROR(INDEX(Employees!$B$2:$B$37,MATCH(C71,Employees!$A$2:$A$37,0))&" "&INDEX(Employees!$C$2:$C$37,MATCH(C71,Employees!$A$2:$A$37,0)),"") -> William Johnson | N71: =IF(E71="","",E71-D71) -> 3
A72: 71 | B72: 25 | C72: 8 | D72: 2025-07-03 | E72: 2025-07-09 | F72: Shipped | G72: Asia Pacific | H72: =SUMIF(OrderItems!$B$2:$B$1254,A72,OrderItems!$G$2:$G$1254) -> 6045.393 | I72: =SUMIF(OrderItems!$B$2:$B$1254,A72,OrderItems!$K$2:$K$1254) -> 3402.16 | J72: =H72-I72 -> 2643.233 | K72: =IF(D72="","",TEXT(D72,"YYYY-MM")) -> 2025-07 | L72: =IFERROR(INDEX(Customers!$G$2:$G$61,MATCH(B72,Customers!$A$2:$A$61,0)),"") -> Small Business | M72: =IFERROR(INDEX(Employees!$B$2:$B$37,MATCH(C72,Employees!$A$2:$A$37,0))&" "&INDEX(Employees!$C$2:$C$37,MATCH(C72,Employees!$A$2:$A$37,0)),"") -> John Gonzalez | N72: =IF(E72="","",E72-D72) -> 6
A73: 72 | B73: 45 | C73: 1 | D73: 2024-08-27 | F73: Pending | G73: Middle East | H73: =SUMIF(OrderItems!$B$2:$B$1254,A73,OrderItems!$G$2:$G$1254) -> 2483.668 | I73: =SUMIF(OrderItems!$B$2:$B$1254,A73,OrderItems!$K$2:$K$1254) -> 1499.52 | J73: =H73-I73 -> 984.148 | K73: =IF(D73="","",TEXT(D73,"YYYY-MM")) -> 2024-08 | L73: =IFERROR(INDEX(Customers!$G$2:$G$61,MATCH(B73,Customers!$A$2:$A$61,0)),"") -> Consumer | M73: =IFERROR(INDEX(Employees!$B$2:$B$37,MATCH(C73,Employees!$A$2:$A$37,0))&" "&INDEX(Employees!$C$2:$C$37,MATCH(C73,Employees!$A$2:$A$37,0)),"") -> Daniel Brown | N73: =IF(E73="","",E73-D73)
A74: 73 | B74: 49 | C74: 8 | D74: 2024-05-21 | E74: 2024-05-30 | F74: Delivered | G74: Latin America | H74: =SUMIF(OrderItems!$B$2:$B$1254,A74,OrderItems!$G$2:$G$1254) -> 6897.791 | I74: =SUMIF(OrderItems!$B$2:$B$1254,A74,OrderItems!$K$2:$K$1254) -> 4017.5 | J74: =H74-I74 -> 2880.291 | K74: =IF(D74="","",TEXT(D74,"YYYY-MM")) -> 2024-05 | L74: =IFERROR(INDEX(Customers!$G$2:$G$61,MATCH(B74,Customers!$A$2:$A$61,0)),"") -> Corporate | M74: =IFERROR(INDEX(Employees!$B$2:$B$37,MATCH(C74,Employees!$A$2:$A$37,0))&" "&INDEX(Employees!$C$2:$C$37,MATCH(C74,Employees!$A$2:$A$37,0)),"") -> John Gonzalez | N74: =IF(E74="","",E74-D74) -> 9
A75: 74 | B75: 8 | C75: 8 | D75: 2025-09-28 | E75: 2025-10-07 | F75: Delivered | G75: Latin America | H75: =SUMIF(OrderItems!$B$2:$B$1254,A75,OrderItems!$G$2:$G$1254) -> 183.6 | I75: =SUMIF(OrderItems!$B$2:$B$1254,A75,OrderItems!$K$2:$K$1254) -> 94.89 | J75: =H75-I75 -> 88.71 | K75: =IF(D75="","",TEXT(D75,"YYYY-MM")) -> 2025-09 | L75: =IFERROR(INDEX(Customers!$G$2:$G$61,MATCH(B75,Customers!$A$2:$A$61,0)),"") -> Consumer | M75: =IFERROR(INDEX(Employees!$B$2:$B$37,MATCH(C75,Employees!$A$2:$A$37,0))&" "&INDEX(Employees!$C$2:$C$37,MATCH(C75,Employees!$A$2:$A$37,0)),"") -> John Gonzalez | N75: =IF(E75="","",E75-D75) -> 9
A76: 75 | B76: 37 | C76: 1 | D76: 2025-08-04 | E76: 2025-08-05 | F76: Shipped | G76: Latin America | H76: =SUMIF(OrderItems!$B$2:$B$1254,A76,OrderItems!$G$2:$G$1254) -> 4859.131 | I76: =SUMIF(OrderItems!$B$2:$B$1254,A76,OrderItems!$K$2:$K$1254) -> 3203.45 | J76: =H76-I76 -> 1655.681 | K76: =IF(D76="","",TEXT(D76,"YYYY-MM")) -> 2025-08 | L76: =IFERROR(INDEX(Customers!$G$2:$G$61,MATCH(B76,Customers!$A$2:$A$61,0)),"") -> Corporate | M76: =IFERROR(INDEX(Employees!$B$2:$B$37,MATCH(C76,Employees!$A$2:$A$37,0))&" "&INDEX(Employees!$C$2:$C$37,MATCH(C76,Employees!$A$2:$A$37,0)),"") -> Daniel Brown | N76: =IF(E76="","",E76-D76) -> 1
A77: 76 | B77: 60 | C77: 1 | D77: 2025-08-24 | E77: 2025-08-29 | F77: Delivered | G77: Latin America | H77: =SUMIF(OrderItems!$B$2:$B$1254,A77,OrderItems!$G$2:$G$1254) -> 3541.4365 | I77: =SUMIF(OrderItems!$B$2:$B$1254,A77,OrderItems!$K$2:$K$1254) -> 2218.58 | J77: =H77-I77 -> 1322.8565 | K77: =IF(D77="","",TEXT(D77,"YYYY-MM")) -> 2025-08 | L77: =IFERROR(INDEX(Customers!$G$2:$G$61,MATCH(B77,Customers!$A$2:$A$61,0)),"") -> Consumer | M77: =IFERROR(INDEX(Employees!$B$2:$B$37,MATCH(C77,Employees!$A$2:$A$37,0))&" "&INDEX(Employees!$C$2:$C$37,MATCH(C77,Employees!$A$2:$A$37,0)),"") -> Daniel Brown | N77: =IF(E77="","",E77-D77) -> 5
A78: 77 | B78: 6 | C78: 8 | D78: 2024-12-13 | E78: 2024-12-16 | F78: Delivered | G78: Middle East | H78: =SUMIF(OrderItems!$B$2:$B$1254,A78,OrderItems!$G$2:$G$1254) -> 3845.194 | I78: =SUMIF(OrderItems!$B$2:$B$1254,A78,OrderItems!$K$2:$K$1254) -> 2654.94 | J78: =H78-I78 -> 1190.254 | K78: =IF(D78="","",TEXT(D78,"YYYY-MM")) -> 2024-12 | L78: =IFERROR(INDEX(Customers!$G$2:$G$61,MATCH(B78,Customers!$A$2:$A$61,0)),"") -> Consumer | M78: =IFERROR(INDEX(Employees!$B$2:$B$37,MATCH(C78,Employees!$A$2:$A$37,0))&" "&INDEX(Employees!$C$2:$C$37,MATCH(C78,Employees!$A$2:$A$37,0)),"") -> John Gonzalez | N78: =IF(E78="","",E78-D78) -> 3
A79: 78 | B79: 53 | C79: 8 | D79: 2024-05-21 | E79: 2024-05-27 | F79: Returned | G79: Europe | H79: =SUMIF(OrderItems!$B$2:$B$1254,A79,OrderItems!$G$2:$G$1254) -> 2554.36 | I79: =SUMIF(OrderItems!$B$2:$B$1254,A79,OrderItems!$K$2:$K$1254) -> 1315.59 | J79: =H79-I79 -> 1238.77 | K79: =IF(D79="","",TEXT(D79,"YYYY-MM")) -> 2024-05 | L79: =IFERROR(INDEX(Customers!$G$2:$G$61,MATCH(B79,Customers!$A$2:$A$61,0)),"") -> Corporate | M79: =IFERROR(INDEX(Employees!$B$2:$B$37,MATCH(C79,Employees!$A$2:$A$37,0))&" "&INDEX(Employees!$C$2:$C$37,MATCH(C79,Employees!$A$2:$A$37,0)),"") -> John Gonzalez | N79: =IF(E79="","",E79-D79) -> 6
A80: 79 | B80: 29 | C80: 1 | D80: 2024-05-16 | E80: 2024-05-23 | F80: Delivered | G80: Latin America | H80: =SUMIF(OrderItems!$B$2:$B$1254,A80,OrderItems!$G$2:$G$1254) -> 1499.04 | I80: =SUMIF(OrderItems!$B$2:$B$1254,A80,OrderItems!$K$2:$K$1254) -> 1100.04 | J80: =H80-I80 -> 399 | K80: =IF(D80="","",TEXT(D80,"YYYY-MM")) -> 2024-05 | L80: =IFERROR(INDEX(Customers!$G$2:$G$61,MATCH(B80,Customers!$A$2:$A$61,0)),"") -> Consumer | M80: =IFERROR(INDEX(Employees!$B$2:$B$37,MATCH(C80,Employees!$A$2:$A$37,0))&" "&INDEX(Employees!$C$2:$C$37,MATCH(C80,Employees!$A$2:$A$37,0)),"") -> Daniel Brown | N80: =IF(E80="","",E80-D80) -> 7
A81: 80 | B81: 37 | C81: 9 | D81: 2024-04-30 | E81: 2024-05-03 | F81: Shipped | G81: Middle East | H81: =SUMIF(OrderItems!$B$2:$B$1254,A81,OrderItems!$G$2:$G$1254) -> 3013.764 | I81: =SUMIF(OrderItems!$B$2:$B$1254,A81,OrderItems!$K$2:$K$1254) -> 1394.65 | J81: =H81-I81 -> 1619.114 | K81: =IF(D81="","",TEXT(D81,"YYYY-MM")) -> 2024-04 | L81: =IFERROR(INDEX(Customers!$G$2:$G$61,MATCH(B81,Customers!$A$2:$A$61,0)),"") -> Corporate | M81: =IFERROR(INDEX(Employees!$B$2:$B$37,MATCH(C81,Employees!$A$2:$A$37,0))&" "&INDEX(Employees!$C$2:$C$37,MATCH(C81,Employees!$A$2:$A$37,0)),"") -> William Johnson | N81: =IF(E81="","",E81-D81) -> 3
A82: 81 | B82: 41 | C82: 10 | D82: 2025-10-12 | E82: 2025-10-18 | F82: Delivered | G82: Latin America | H82: =SUMIF(OrderItems!$B$2:$B$1254,A82,OrderItems!$G$2:$G$1254) -> 8073.183 | I82: =SUMIF(OrderItems!$B$2:$B$1254,A82,OrderItems!$K$2:$K$1254) -> 4378.03 | J82: =H82-I82 -> 3695.153 | K82: =IF(D82="","",TEXT(D82,"YYYY-MM")) -> 2025-10 | L82: =IFERROR(INDEX(Customers!$G$2:$G$61,MATCH(B82,Customers!$A$2:$A$61,0)),"") -> Small Business | M82: =IFERROR(INDEX(Employees!$B$2:$B$37,MATCH(C82,Employees!$A$2:$A$37,0))&" "&INDEX(Employees!$C$2:$C$37,MATCH(C82,Employees!$A$2:$A$37,0)),"") -> John Moore | N82: =IF(E82="","",E82-D82) -> 6
A83: 82 | B83: 52 | C83: 10 | D83: 2023-04-29 | F83: Cancelled | G83: Latin America | H83: =SUMIF(OrderItems!$B$2:$B$1254,A83,OrderItems!$G$2:$G$1254) -> 9381.302 | I83: =SUMIF(OrderItems!$B$2:$B$1254,A83,OrderItems!$K$2:$K$1254) -> 5218.83 | J83: =H83-I83 -> 4162.472 | K83: =IF(D83="","",TEXT(D83,"YYYY-MM")) -> 2023-04 | L83: =IFERROR(INDEX(Customers!$G$2:$G$61,MATCH(B83,Customers!$A$2:$A$61,0)),"") -> Corporate | M83: =IFERROR(INDEX(Employees!$B$2:$B$37,MATCH(C83,Employees!$A$2:$A$37,0))&" "&INDEX(Employees!$C$2:$C$37,MATCH(C83,Employees!$A$2:$A$37,0)),"") -> John Moore | N83: =IF(E83="","",E83-D83)
A84: 83 | B84: 18 | C84: 10 | D84: 2023-03-22 | E84: 2023-03-26 | F84: Delivered | G84: Middle East | H84: =SUMIF(OrderItems!$B$2:$B$1254,A84,OrderItems!$G$2:$G$1254) -> 2390.381 | I84: =SUMIF(OrderItems!$B$2:$B$1254,A84,OrderItems!$K$2:$K$1254) -> 1271.74 | J84: =H84-I84 -> 1118.641 | K84: =IF(D84="","",TEXT(D84,"YYYY-MM")) -> 2023-03 | L84: =IFERROR(INDEX(Customers!$G$2:$G$61,MATCH(B84,Customers!$A$2:$A$61,0)),"") -> Small Business | M84: =IFERROR(INDEX(Employees!$B$2:$B$37,MATCH(C84,Employees!$A$2:$A$37,0))&" "&INDEX(Employees!$C$2:$C$37,MATCH(C84,Employees!$A$2:$A$37,0)),"") -> John Moore | N84: =IF(E84="","",E84-D84) -> 4
A85: 84 | B85: 59 | C85: 8 | D85: 2024-10-20 | E85: 2024-10-27 | F85: Shipped | G85: Latin America | H85: =SUMIF(OrderItems!$B$2:$B$1254,A85,OrderItems!$G$2:$G$1254) -> 7938.364 | I85: =SUMIF(OrderItems!$B$2:$B$1254,A85,OrderItems!$K$2:$K$1254) -> 5204.52 | J85: =H85-I85 -> 2733.844 | K85: =IF(D85="","",TEXT(D85,"YYYY-MM")) -> 2024-10 | L85: =IFERROR(INDEX(Customers!$G$2:$G$61,MATCH(B85,Customers!$A$2:$A$61,0)),"") -> Corporate | M85: =IFERROR(INDEX(Employees!$B$2:$B$37,MATCH(C85,Employees!$A$2:$A$37,0))&" "&INDEX(Employees!$C$2:$C$37,MATCH(C85,Employees!$A$2:$A$37,0)),"") -> John Gonzalez | N85: =IF(E85="","",E85-D85) -> 7
A86: 85 | B86: 37 | C86: 8 | D86: 2023-10-26 | E86: 2023-10-31 | F86: Delivered | G86: Middle East | H86: =SUMIF(OrderItems!$B$2:$B$1254,A86,OrderItems!$G$2:$G$1254) -> 8646.8835 | I86: =SUMIF(OrderItems!$B$2:$B$1254,A86,OrderItems!$K$2:$K$1254) -> 5387.73 | J86: =H86-I86 -> 3259.1535 | K86: =IF(D86="","",TEXT(D86,"YYYY-MM")) -> 2023-10 | L86: =IFERROR(INDEX(Customers!$G$2:$G$61,MATCH(B86,Customers!$A$2:$A$61,0)),"") -> Corporate | M86: =IFERROR(INDEX(Employees!$B$2:$B$37,MATCH(C86,Employees!$A$2:$A$37,0))&" "&INDEX(Employees!$C$2:$C$37,MATCH(C86,Employees!$A$2:$A$37,0)),"") -> John Gonzalez | N86: =IF(E86="","",E86-D86) -> 5
A87: 86 | B87: 17 | C87: 10 | D87: 2025-10-01 | E87: 2025-10-04 | F87: Returned | G87: Asia Pacific | H87: =SUMIF(OrderItems!$B$2:$B$1254,A87,OrderItems!$G$2:$G$1254) -> 2367.3555 | I87: =SUMIF(OrderItems!$B$2:$B$1254,A87,OrderItems!$K$2:$K$1254) -> 1356.36 | J87: =H87-I87 -> 1010.9955 | K87: =IF(D87="","",TEXT(D87,"YYYY-MM")) -> 2025-10 | L87: =IFERROR(INDEX(Customers!$G$2:$G$61,MATCH(B87,Customers!$A$2:$A$61,0)),"") -> Small Business | M87: =IFERROR(INDEX(Employees!$B$2:$B$37,MATCH(C87,Employees!$A$2:$A$37,0))&" "&INDEX(Employees!$C$2:$C$37,MATCH(C87,Employees!$A$2:$A$37,0)),"") -> John Moore | N87: =IF(E87="","",E87-D87) -> 3
A88: 87 | B88: 49 | C88: 1 | D88: 2025-04-24 | E88: 2025-04-28 | F88: Delivered | G88: North America | H88: =SUMIF(OrderItems!$B$2:$B$1254,A88,OrderItems!$G$2:$G$1254) -> 3349.9935 | I88: =SUMIF(OrderItems!$B$2:$B$1254,A88,OrderItems!$K$2:$K$1254) -> 1905.66 | J88: =H88-I88 -> 1444.3335 | K88: =IF(D88="","",TEXT(D88,"YYYY-MM")) -> 2025-04 | L88: =IFERROR(INDEX(Customers!$G$2:$G$61,MATCH(B88,Customers!$A$2:$A$61,0)),"") -> Corporate | M88: =IFERROR(INDEX(Employees!$B$2:$B$37,MATCH(C88,Employees!$A$2:$A$37,0))&" "&INDEX(Employees!$C$2:$C$37,MATCH(C88,Employees!$A$2:$A$37,0)),"") -> Daniel Brown | N88: =IF(E88="","",E88-D88) -> 4
A89: 88 | B89: 43 | C89: 10 | D89: 2023-02-02 | E89: 2023-02-11 | F89: Delivered | G89: Middle East | H89: =SUMIF(OrderItems!$B$2:$B$1254,A89,OrderItems!$G$2:$G$1254) -> 5369.457 | I89: =SUMIF(OrderItems!$B$2:$B$1254,A89,OrderItems!$K$2:$K$1254) -> 3531.5 | J89: =H89-I89 -> 1837.957 | K89: =IF(D89="","",TEXT(D89,"YYYY-MM")) -> 2023-02 | L89: =IFERROR(INDEX(Customers!$G$2:$G$61,MATCH(B89,Customers!$A$2:$A$61,0)),"") -> Corporate | M89: =IFERROR(INDEX(Employees!$B$2:$B$37,MATCH(C89,Employees!$A$2:$A$37,0))&" "&INDEX(Employees!$C$2:$C$37,MATCH(C89,Employees!$A$2:$A$37,0)),"") -> John Moore | N89: =IF(E89="","",E89-D89) -> 9
A90: 89 | B90: 59 | C90: 1 | D90: 2025-12-09 | E90: 2025-12-13 | F90: Delivered | G90: Europe | H90: =SUMIF(OrderItems!$B$2:$B$1254,A90,OrderItems!$G$2:$G$1254) -> 6272.9635 | I90: =SUMIF(OrderItems!$B$2:$B$1254,A90,OrderItems!$K$2:$K$1254) -> 3261.55 | J90: =H90-I90 -> 3011.4135 | K90: =IF(D90="","",TEXT(D90,"YYYY-MM")) -> 2025-12 | L90: =IFERROR(INDEX(Customers!$G$2:$G$61,MATCH(B90,Customers!$A$2:$A$61,0)),"") -> Corporate | M90: =IFERROR(INDEX(Employees!$B$2:$B$37,MATCH(C90,Employees!$A$2:$A$37,0))&" "&INDEX(Employees!$C$2:$C$37,MATCH(C90,Employees!$A$2:$A$37,0)),"") -> Daniel Brown | N90: =IF(E90="","",E90-D90) -> 4
A91: 90 | B91: 6 | C91: 10 | D91: 2025-02-15 | F91: Cancelled | G91: Middle East | H91: =SUMIF(OrderItems!$B$2:$B$1254,A91,OrderItems!$G$2:$G$1254) -> 5732.5575 | I91: =SUMIF(OrderItems!$B$2:$B$1254,A91,OrderItems!$K$2:$K$1254) -> 3442.11 | J91: =H91-I91 -> 2290.4475 | K91: =IF(D91="","",TEXT(D91,"YYYY-MM")) -> 2025-02 | L91: =IFERROR(INDEX(Customers!$G$2:$G$61,MATCH(B91,Customers!$A$2:$A$61,0)),"") -> Consumer | M91: =IFERROR(INDEX(Employees!$B$2:$B$37,MATCH(C91,Employees!$A$2:$A$37,0))&" "&INDEX(Employees!$C$2:$C$37,MATCH(C91,Employees!$A$2:$A$37,0)),"") -> John Moore | N91: =IF(E91="","",E91-D91)
A92: 91 | B92: 55 | C92: 1 | D92: 2025-12-17 | E92: 2025-12-21 | F92: Delivered | G92: Europe | H92: =SUMIF(OrderItems!$B$2:$B$1254,A92,OrderItems!$G$2:$G$1254) -> 6425.086 | I92: =SUMIF(OrderItems!$B$2:$B$1254,A92,OrderItems!$K$2:$K$1254) -> 3919.21 | J92: =H92-I92 -> 2505.876 | K92: =IF(D92="","",TEXT(D92,"YYYY-MM")) -> 2025-12 | L92: =IFERROR(INDEX(Customers!$G$2:$G$61,MATCH(B92,Customers!$A$2:$A$61,0)),"") -> Consumer | M92: =IFERROR(INDEX(Employees!$B$2:$B$37,MATCH(C92,Employees!$A$2:$A$37,0))&" "&INDEX(Employees!$C$2:$C$37,MATCH(C92,Employees!$A$2:$A$37,0)),"") -> Daniel Brown | N92: =IF(E92="","",E92-D92) -> 4
A93: 92 | B93: 60 | C93: 1 | D93: 2024-09-04 | E93: 2024-09-14 | F93: Delivered | G93: Europe | H93: =SUMIF(OrderItems!$B$2:$B$1254,A93,OrderItems!$G$2:$G$1254) -> 2957.343 | I93: =SUMIF(OrderItems!$B$2:$B$1254,A93,OrderItems!$K$2:$K$1254) -> 1779.69 | J93: =H93-I93 -> 1177.653 | K93: =IF(D93="","",TEXT(D93,"YYYY-MM")) -> 2024-09 | L93: =IFERROR(INDEX(Customers!$G$2:$G$61,MATCH(B93,Customers!$A$2:$A$61,0)),"") -> Consumer | M93: =IFERROR(INDEX(Employees!$B$2:$B$37,MATCH(C93,Employees!$A$2:$A$37,0))&" "&INDEX(Employees!$C$2:$C$37,MATCH(C93,Employees!$A$2:$A$37,0)),"") -> Daniel Brown | N93: =IF(E93="","",E93-D93) -> 10
A94: 93 | B94: 39 | C94: 10 | D94: 2024-10-30 | E94: 2024-11-04 | F94: Delivered | G94: Latin America | H94: =SUMIF(OrderItems!$B$2:$B$1254,A94,OrderItems!$G$2:$G$1254) -> 6291.405 | I94: =SUMIF(OrderItems!$B$2:$B$1254,A94,OrderItems!$K$2:$K$1254) -> 3504.5 | J94: =H94-I94 -> 2786.905 | K94: =IF(D94="","",TEXT(D94,"YYYY-MM")) -> 2024-10 | L94: =IFERROR(INDEX(Customers!$G$2:$G$61,MATCH(B94,Customers!$A$2:$A$61,0)),"") -> Consumer | M94: =IFERROR(INDEX(Employees!$B$2:$B$37,MATCH(C94,Employees!$A$2:$A$37,0))&" "&INDEX(Employees!$C$2:$C$37,MATCH(C94,Employees!$A$2:$A$37,0)),"") -> John Moore | N94: =IF(E94="","",E94-D94) -> 5
A95: 94 | B95: 6 | C95: 9 | D95: 2023-11-12 | F95: Cancelled | G95: Europe | H95: =SUMIF(OrderItems!$B$2:$B$1254,A95,OrderItems!$G$2:$G$1254) -> 3472.72 | I95: =SUMIF(OrderItems!$B$2:$B$1254,A95,OrderItems!$K$2:$K$1254) -> 2271.39 | J95: =H95-I95 -> 1201.33 | K95: =IF(D95="","",TEXT(D95,"YYYY-MM")) -> 2023-11 | L95: =IFERROR(INDEX(Customers!$G$2:$G$61,MATCH(B95,Customers!$A$2:$A$61,0)),"") -> Consumer | M95: =IFERROR(INDEX(Employees!$B$2:$B$37,MATCH(C95,Employees!$A$2:$A$37,0))&" "&INDEX(Employees!$C$2:$C$37,MATCH(C95,Employees!$A$2:$A$37,0)),"") -> William Johnson | N95: =IF(E95="","",E95-D95)
A96: 95 | B96: 12 | C96: 10 | D96: 2025-07-08 | F96: Cancelled | G96: North America | H96: =SUMIF(OrderItems!$B$2:$B$1254,A96,OrderItems!$G$2:$G$1254) -> 1183.194 | I96: =SUMIF(OrderItems!$B$2:$B$1254,A96,OrderItems!$K$2:$K$1254) -> 853.8 | J96: =H96-I96 -> 329.394 | K96: =IF(D96="","",TEXT(D96,"YYYY-MM")) -> 2025-07 | L96: =IFERROR(INDEX(Customers!$G$2:$G$61,MATCH(B96,Customers!$A$2:$A$61,0)),"") -> Small Business | M96: =IFERROR(INDEX(Employees!$B$2:$B$37,MATCH(C96,Employees!$A$2:$A$37,0))&" "&INDEX(Employees!$C$2:$C$37,MATCH(C96,Employees!$A$2:$A$37,0)),"") -> John Moore | N96: =IF(E96="","",E96-D96)
A97: 96 | B97: 6 | C97: 9 | D97: 2025-02-27 | E97: 2025-03-04 | F97: Delivered | G97: Latin America | H97: =SUMIF(OrderItems!$B$2:$B$1254,A97,OrderItems!$G$2:$G$1254) -> 8481.184 | I97: =SUMIF(OrderItems!$B$2:$B$1254,A97,OrderItems!$K$2:$K$1254) -> 4222.27 | J97: =H97-I97 -> 4258.914 | K97: =IF(D97="","",TEXT(D97,"YYYY-MM")) -> 2025-02 | L97: =IFERROR(INDEX(Customers!$G$2:$G$61,MATCH(B97,Customers!$A$2:$A$61,0)),"") -> Consumer | M97: =IFERROR(INDEX(Employees!$B$2:$B$37,MATCH(C97,Employees!$A$2:$A$37,0))&" "&INDEX(Employees!$C$2:$C$37,MATCH(C97,Employees!$A$2:$A$37,0)),"") -> William Johnson | N97: =IF(E97="","",E97-D97) -> 5
A98: 97 | B98: 32 | C98: 8 | D98: 2023-05-10 | E98: 2023-05-17 | F98: Delivered | G98: Asia Pacific | H98: =SUMIF(OrderItems!$B$2:$B$1254,A98,OrderItems!$G$2:$G$1254) -> 7253.28 | I98: =SUMIF(OrderItems!$B$2:$B$1254,A98,OrderItems!$K$2:$K$1254) -> 3660.66 | J98: =H98-I98 -> 3592.62 | K98: =IF(D98="","",TEXT(D98,"YYYY-MM")) -> 2023-05 | L98: =IFERROR(INDEX(Customers!$G$2:$G$61,MATCH(B98,Customers!$A$2:$A$61,0)),"") -> Small Business | M98: =IFERROR(INDEX(Employees!$B$2:$B$37,MATCH(C98,Employees!$A$2:$A$37,0))&" "&INDEX(Employees!$C$2:$C$37,MATCH(C98,Employees!$A$2:$A$37,0)),"") -> John Gonzalez | N98: =IF(E98="","",E98-D98) -> 7
A99: 98 | B99: 1 | C99: 10 | D99: 2024-11-11 | F99: Cancelled | G99: Asia Pacific | H99: =SUMIF(OrderItems!$B$2:$B$1254,A99,OrderItems!$G$2:$G$1254) -> 4007.868 | I99: =SUMIF(OrderItems!$B$2:$B$1254,A99,OrderItems!$K$2:$K$1254) -> 2276.26 | J99: =H99-I99 -> 1731.608 | K99: =IF(D99="","",TEXT(D99,"YYYY-MM")) -> 2024-11 | L99: =IFERROR(INDEX(Customers!$G$2:$G$61,MATCH(B99,Customers!$A$2:$A$61,0)),"") -> Corporate | M99: =IFERROR(INDEX(Employees!$B$2:$B$37,MATCH(C99,Employees!$A$2:$A$37,0))&" "&INDEX(Employees!$C$2:$C$37,MATCH(C99,Employees!$A$2:$A$37,0)),"") -> John Moore | N99: =IF(E99="","",E99-D99)
A100: 99 | B100: 26 | C100: 9 | D100: 2024-08-19 | E100: 2024-08-29 | F100: Returned | G100: Europe | H100: =SUMIF(OrderItems!$B$2:$B$1254,A100,OrderItems!$G$2:$G$1254) -> 8839.17 | I100: =SUMIF(OrderItems!$B$2:$B$1254,A100,OrderItems!$K$2:$K$1254) -> 4844.14 | J100: =H100-I100 -> 3995.03 | K100: =IF(D100="","",TEXT(D100,"YYYY-MM")) -> 2024-08 | L100: =IFERROR(INDEX(Customers!$G$2:$G$61,MATCH(B100,Customers!$A$2:$A$61,0)),"") -> Small Business | M100: =IFERROR(INDEX(Employees!$B$2:$B$37,MATCH(C100,Employees!$A$2:$A$37,0))&" "&INDEX(Employees!$C$2:$C$37,MATCH(C100,Employees!$A$2:$A$37,0)),"") -> William Johnson | N100: =IF(E100="","",E100-D100) -> 10
...

Sheet OrderItems
A1: order item_id | B1: order id | C1: product id | D1: quantity | E1: unit price | F1: discount | G1: Line Revenue | H1: Category ID | I1: Category Name | J1: Unit Cost | K1: Line Cost | L1: Line Profit
A2: 1 | B2: 1 | C2: 2 | D2: 8 | E2: 286.57 | F2: 0 | G2: =D2*E2*(1-F2) -> 2292.56 | H2: =INDEX(Products!$C$2:$C$101,MATCH(C2,Products!$A$2:$A$101,0)) -> 1 | I2: =INDEX(Categories!$B$2:$B$11,MATCH(H2,Categories!$A$2:$A$11,0)) -> Electronics | J2: =INDEX(Products!$E$2:$E$101,MATCH(C2,Products!$A$2:$A$101,0)) -> 135.94 | K2: =D2*J2 -> 1087.52 | L2: =G2-K2 -> 1205.04
A3: 2 | B3: 1 | C3: 34 | D3: 5 | E3: 339.25 | F3: 0.1 | G3: =D3*E3*(1-F3) -> 1526.625 | H3: =INDEX(Products!$C$2:$C$101,MATCH(C3,Products!$A$2:$A$101,0)) -> 4 | I3: =INDEX(Categories!$B$2:$B$11,MATCH(H3,Categories!$A$2:$A$11,0)) -> Apparel | J3: =INDEX(Products!$E$2:$E$101,MATCH(C3,Products!$A$2:$A$101,0)) -> 208.66 | K3: =D3*J3 -> 1043.3 | L3: =G3-K3 -> 483.325
A4: 3 | B4: 1 | C4: 69 | D4: 7 | E4: 188.38 | F4: 0.2 | G4: =D4*E4*(1-F4) -> 1054.928 | H4: =INDEX(Products!$C$2:$C$101,MATCH(C4,Products!$A$2:$A$101,0)) -> 7 | I4: =INDEX(Categories!$B$2:$B$11,MATCH(H4,Categories!$A$2:$A$11,0)) -> Toys & Games | J4: =INDEX(Products!$E$2:$E$101,MATCH(C4,Products!$A$2:$A$101,0)) -> 86.95 | K4: =D4*J4 -> 608.65 | L4: =G4-K4 -> 446.278
A5: 4 | B5: 1 | C5: 16 | D5: 6 | E5: 345.42 | F5: 0 | G5: =D5*E5*(1-F5) -> 2072.52 | H5: =INDEX(Products!$C$2:$C$101,MATCH(C5,Products!$A$2:$A$101,0)) -> 2 | I5: =INDEX(Categories!$B$2:$B$11,MATCH(H5,Categories!$A$2:$A$11,0)) -> Office Supplies | J5: =INDEX(Products!$E$2:$E$101,MATCH(C5,Products!$A$2:$A$101,0)) -> 173.58 | K5: =D5*J5 -> 1041.48 | L5: =G5-K5 -> 1031.04
A6: 5 | B6: 2 | C6: 15 | D6: 5 | E6: 389.29 | F6: 0.05 | G6: =D6*E6*(1-F6) -> 1849.1275 | H6: =INDEX(Products!$C$2:$C$101,MATCH(C6,Products!$A$2:$A$101,0)) -> 2 | I6: =INDEX(Categories!$B$2:$B$11,MATCH(H6,Categories!$A$2:$A$11,0)) -> Office Supplies | J6: =INDEX(Products!$E$2:$E$101,MATCH(C6,Products!$A$2:$A$101,0)) -> 227.28 | K6: =D6*J6 -> 1136.4 | L6: =G6-K6 -> 712.7275
A7: 6 | B7: 2 | C7: 18 | D7: 2 | E7: 185.81 | F7: 0 | G7: =D7*E7*(1-F7) -> 371.62 | H7: =INDEX(Products!$C$2:$C$101,MATCH(C7,Products!$A$2:$A$101,0)) -> 2 | I7: =INDEX(Categories!$B$2:$B$11,MATCH(H7,Categories!$A$2:$A$11,0)) -> Office Supplies | J7: =INDEX(Products!$E$2:$E$101,MATCH(C7,Products!$A$2:$A$101,0)) -> 108.81 | K7: =D7*J7 -> 217.62 | L7: =G7-K7 -> 154
A8: 7 | B8: 2 | C8: 6 | D8: 4 | E8: 234.43 | F8: 0.1 | G8: =D8*E8*(1-F8) -> 843.948 | H8: =INDEX(Products!$C$2:$C$101,MATCH(C8,Products!$A$2:$A$101,0)) -> 1 | I8: =INDEX(Categories!$B$2:$B$11,MATCH(H8,Categories!$A$2:$A$11,0)) -> Electronics | J8: =INDEX(Products!$E$2:$E$101,MATCH(C8,Products!$A$2:$A$101,0)) -> 161.76 | K8: =D8*J8 -> 647.04 | L8: =G8-K8 -> 196.908
A9: 8 | B9: 2 | C9: 5 | D9: 3 | E9: 310.02 | F9: 0.05 | G9: =D9*E9*(1-F9) -> 883.557 | H9: =INDEX(Products!$C$2:$C$101,MATCH(C9,Products!$A$2:$A$101,0)) -> 1 | I9: =INDEX(Categories!$B$2:$B$11,MATCH(H9,Categories!$A$2:$A$11,0)) -> Electronics | J9: =INDEX(Products!$E$2:$E$101,MATCH(C9,Products!$A$2:$A$101,0)) -> 134.93 | K9: =D9*J9 -> 404.79 | L9: =G9-K9 -> 478.767
A10: 9 | B10: 3 | C10: 79 | D10: 6 | E10: 369.82 | F10: 0 | G10: =D10*E10*(1-F10) -> 2218.92 | H10: =INDEX(Products!$C$2:$C$101,MATCH(C10,Products!$A$2:$A$101,0)) -> 8 | I10: =INDEX(Categories!$B$2:$B$11,MATCH(H10,Categories!$A$2:$A$11,0)) -> Health & Beauty | J10: =INDEX(Products!$E$2:$E$101,MATCH(C10,Products!$A$2:$A$101,0)) -> 215.26 | K10: =D10*J10 -> 1291.56 | L10: =G10-K10 -> 927.36
A11: 10 | B11: 3 | C11: 53 | D11: 8 | E11: 534 | F11: 0.05 | G11: =D11*E11*(1-F11) -> 4058.4 | H11: =INDEX(Products!$C$2:$C$101,MATCH(C11,Products!$A$2:$A$101,0)) -> 6 | I11: =INDEX(Categories!$B$2:$B$11,MATCH(H11,Categories!$A$2:$A$11,0)) -> Sporting Goods | J11: =INDEX(Products!$E$2:$E$101,MATCH(C11,Products!$A$2:$A$101,0)) -> 240.59 | K11: =D11*J11 -> 1924.72 | L11: =G11-K11 -> 2133.68
A12: 11 | B12: 3 | C12: 36 | D12: 4 | E12: 472.77 | F12: 0.2 | G12: =D12*E12*(1-F12) -> 1512.864 | H12: =INDEX(Products!$C$2:$C$101,MATCH(C12,Products!$A$2:$A$101,0)) -> 4 | I12: =INDEX(Categories!$B$2:$B$11,MATCH(H12,Categories!$A$2:$A$11,0)) -> Apparel | J12: =INDEX(Products!$E$2:$E$101,MATCH(C12,Products!$A$2:$A$101,0)) -> 236.19 | K12: =D12*J12 -> 944.76 | L12: =G12-K12 -> 568.104
A13: 12 | B13: 3 | C13: 5 | D13: 6 | E13: 310.02 | F13: 0 | G13: =D13*E13*(1-F13) -> 1860.12 | H13: =INDEX(Products!$C$2:$C$101,MATCH(C13,Products!$A$2:$A$101,0)) -> 1 | I13: =INDEX(Categories!$B$2:$B$11,MATCH(H13,Categories!$A$2:$A$11,0)) -> Electronics | J13: =INDEX(Products!$E$2:$E$101,MATCH(C13,Products!$A$2:$A$101,0)) -> 134.93 | K13: =D13*J13 -> 809.58 | L13: =G13-K13 -> 1050.54
... A1254: 1253 | B1254: 400 | C1254: 52 | D1254: 10 | E1254: 469.43 | F1254: 0 | G1254: =D1254*E1254*(1-F1254) -> 4694.3 | H1254: =INDEX(Products!$C$2:$C$101,MATCH(C1254,Products!$A$2:$A$101,0)) -> 6 | I1254: =INDEX(Categories!$B$2:$B$11,MATCH(H1254,Categories!$A$2:$A$11,0)) -> Sporting Goods | J1254: =INDEX(Products!$E$2:$E$101,MATCH(C1254,Products!$A$2:$A$101,0)) -> 222.69 | K1254: =D1254*J1254 -> 2226.9 | L1254: =G1254-K1254 -> 2467.4

Sheet Payments
A1: payment_id | B1: order_id | C1: payment_date | D1: amount | E1: method | F1: status | G1: Order Revenue | H1: Payment Month | I1: Order Status
A2: 1 | B2: 1 | C2: 2025-03-27 | D2: 6946.63 | E2: Credit Card | F2: Completed | G2: =IFERROR(INDEX(Orders!$H$2:$H$401,MATCH(B2,Orders!$A$2:$A$401,0)),"") -> 6946.633 | H2: =IF(C2="","",TEXT(C2,"YYYY-MM")) -> 2025-03 | I2: =IFERROR(INDEX(Orders!$F$2:$F$401,MATCH(B2,Orders!$A$2:$A$401,0)),"") -> Pending
A3: 2 | B3: 2 | C3: 2024-04-01 | D3: 3948.26 | E3: PayPal | F3: Completed | G3: =IFERROR(INDEX(Orders!$H$2:$H$401,MATCH(B3,Orders!$A$2:$A$401,0)),"") -> 3948.2525 | H3: =IF(C3="","",TEXT(C3,"YYYY-MM")) -> 2024-04 | I3: =IFERROR(INDEX(Orders!$F$2:$F$401,MATCH(B3,Orders!$A$2:$A$401,0)),"") -> Delivered
A4: 3 | B4: 4 | C4: 2025-01-09 | D4: 818.41 | E4: Credit Card | F4: Completed | G4: =IFERROR(INDEX(Orders!$H$2:$H$401,MATCH(B4,Orders!$A$2:$A$401,0)),"") -> 818.414 | H4: =IF(C4="","",TEXT(C4,"YYYY-MM")) -> 2025-01 | I4: =IFERROR(INDEX(Orders!$F$2:$F$401,MATCH(B4,Orders!$A$2:$A$401,0)),"") -> Delivered
A5: 4 | B5: 5 | C5: 2024-05-17 | D5: 607.32 | E5: Bank Transfer | F5: Completed | G5: =IFERROR(INDEX(Orders!$H$2:$H$401,MATCH(B5,Orders!$A$2:$A$401,0)),"") -> 607.32 | H5: =IF(C5="","",TEXT(C5,"YYYY-MM")) -> 2024-05 | I5: =IFERROR(INDEX(Orders!$F$2:$F$401,MATCH(B5,Orders!$A$2:$A$401,0)),"") -> Delivered
A6: 5 | B6: 6 | C6: 2024-11-03 | D6: 1967.39 | E6: PayPal | F6: Completed | G6: =IFERROR(INDEX(Orders!$H$2:$H$401,MATCH(B6,Orders!$A$2:$A$401,0)),"") -> 1967.39 | H6: =IF(C6="","",TEXT(C6,"YYYY-MM")) -> 2024-11 | I6: =IFERROR(INDEX(Orders!$F$2:$F$401,MATCH(B6,Orders!$A$2:$A$401,0)),"") -> Delivered
A7: 6 | B7: 7 | C7: 2024-10-25 | D7: 1366.09 | E7: Credit Card | F7: Completed | G7: =IFERROR(INDEX(Orders!$H$2:$H$401,MATCH(B7,Orders!$A$2:$A$401,0)),"") -> 1366.092 | H7: =IF(C7="","",TEXT(C7,"YYYY-MM")) -> 2024-10 | I7: =IFERROR(INDEX(Orders!$F$2:$F$401,MATCH(B7,Orders!$A$2:$A$401,0)),"") -> Delivered
A8: 7 | B8: 8 | C8: 2025-01-11 | D8: 4922.5 | E8: Credit Card | F8: Completed | G8: =IFERROR(INDEX(Orders!$H$2:$H$401,MATCH(B8,Orders!$A$2:$A$401,0)),"") -> 4922.504 | H8: =IF(C8="","",TEXT(C8,"YYYY-MM")) -> 2025-01 | I8: =IFERROR(INDEX(Orders!$F$2:$F$401,MATCH(B8,Orders!$A$2:$A$401,0)),"") -> Delivered
A9: 8 | B9: 9 | C9: 2025-05-24 | D9: 2252.34 | E9: Credit Card | F9: Completed | G9: =IFERROR(INDEX(Orders!$H$2:$H$401,MATCH(B9,Orders!$A$2:$A$401,0)),"") -> 2252.34 | H9: =IF(C9="","",TEXT(C9,"YYYY-MM")) -> 2025-05 | I9: =IFERROR(INDEX(Orders!$F$2:$F$401,MATCH(B9,Orders!$A$2:$A$401,0)),"") -> Delivered
A10: 9 | B10: 12 | C10: 2025-02-05 | D10: 792.49 | E10: PayPal | F10: Completed | G10: =IFERROR(INDEX(Orders!$H$2:$H$401,MATCH(B10,Orders!$A$2:$A$401,0)),"") -> 792.49 | H10: =IF(C10="","",TEXT(C10,"YYYY-MM")) -> 2025-02 | I10: =IFERROR(INDEX(Orders!$F$2:$F$401,MATCH(B10,Orders!$A$2:$A$401,0)),"") -> Delivered
A11: 10 | B11: 13 | C11: 2023-05-04 | D11: 4712.02 | E11: Check | F11: Completed | G11: =IFERROR(INDEX(Orders!$H$2:$H$401,MATCH(B11,Orders!$A$2:$A$401,0)),"") -> 4712.02 | H11: =IF(C11="","",TEXT(C11,"YYYY-MM")) -> 2023-05 | I11: =IFERROR(INDEX(Orders!$F$2:$F$401,MATCH(B11,Orders!$A$2:$A$401,0)),"") -> Pending
A12: 11 | B12: 14 | C12: 2024-12-18 | D12: 6214.81 | E12: Bank Transfer | F12: Pending | G12: =IFERROR(INDEX(Orders!$H$2:$H$401,MATCH(B12,Orders!$A$2:$A$401,0)),"") -> 6214.806 | H12: =IF(C12="","",TEXT(C12,"YYYY-MM")) -> 2024-12 | I12: =IFERROR(INDEX(Orders!$F$2:$F$401,MATCH(B12,Orders!$A$2:$A$401,0)),"") -> Pending
A13: 12 | B13: 15 | C13: 2024-11-26 | D13: 3001.19 | E13: Bank Transfer | F13: Completed | G13: =IFERROR(INDEX(Orders!$H$2:$H$401,MATCH(B13,Orders!$A$2:$A$401,0)),"") -> 3001.1885 | H13: =IF(C13="","",TEXT(C13,"YYYY-MM")) -> 2024-11 | I13: =IFERROR(INDEX(Orders!$F$2:$F$401,MATCH(B13,Orders!$A$2:$A$401,0)),"") -> Pending
... A349: 348 | B349: 400 | C349: 2023-07-04 | D349: 6128.42 | E349: Bank Transfer | F349: Refunded | G349: =IFERROR(INDEX(Orders!$H$2:$H$401,MATCH(B349,Orders!$A$2:$A$401,0)),"") -> 6128.42 | H349: =IF(C349="","",TEXT(C349,"YYYY-MM")) -> 2023-07 | I349: =IFERROR(INDEX(Orders!$F$2:$F$401,MATCH(B349,Orders!$A$2:$A$401,0)),"") -> Returned

Sheet InventoryTransactions
A1: transaction id | B1: product id | C1: transaction date | D1: transaction type | E1: quantity | F1: Product Name | G1: Category Name | H1: Supplier ID
A2: 1 | B2: 73 | C2: 2023-08-29 | D2: Restock | E2: 184 | F2: =INDEX(Products!$B$2:$B$101,MATCH(B2,Products!$A$2:$A$101,0)) -> Skincare Set | G2: =INDEX(Products!$J$2:$J$101,MATCH(B2,Products!$A$2:$A$101,0)) -> Health & Beauty | H2: =INDEX(Products!$D$2:$D$101,MATCH(B2,Products!$A$2:$A$101,0)) -> 4
A3: 2 | B3: 56 | C3: 2025-07-18 | D3: Damaged | E3: -8 | F3: =INDEX(Products!$B$2:$B$101,MATCH(B3,Products!$A$2:$A$101,0)) -> Bicycle Helmet | G3: =INDEX(Products!$J$2:$J$101,MATCH(B3,Products!$A$2:$A$101,0)) -> Sporting Goods | H3: =INDEX(Products!$D$2:$D$101,MATCH(B3,Products!$A$2:$A$101,0)) -> 8
A4: 3 | B4: 29 | C4: 2024-02-21 | D4: Restock | E4: 270 | F4: =INDEX(Products!$B$2:$B$101,MATCH(B4,Products!$A$2:$A$101,0)) -> Storage Cabinet | G4: =INDEX(Products!$J$2:$J$101,MATCH(B4,Products!$A$2:$A$101,0)) -> Furniture | H4: =INDEX(Products!$D$2:$D$101,MATCH(B4,Products!$A$2:$A$101,0)) -> 4
A5: 4 | B5: 35 | C5: 2024-08-12 | D5: Damaged | E5: -9 | F5: =INDEX(Products!$B$2:$B$101,MATCH(B5,Products!$A$2:$A$101,0)) -> Baseball Cap | G5: =INDEX(Products!$J$2:$J$101,MATCH(B5,Products!$A$2:$A$101,0)) -> Apparel | H5: =INDEX(Products!$D$2:$D$101,MATCH(B5,Products!$A$2:$A$101,0)) -> 12
A6: 5 | B6: 56 | C6: 2024-02-28 | D6: Damaged | E6: -13 | F6: =INDEX(Products!$B$2:$B$101,MATCH(B6,Products!$A$2:$A$101,0)) -> Bicycle Helmet | G6: =INDEX(Products!$J$2:$J$101,MATCH(B6,Products!$A$2:$A$101,0)) -> Sporting Goods | H6: =INDEX(Products!$D$2:$D$101,MATCH(B6,Products!$A$2:$A$101,0)) -> 8
A7: 6 | B7: 54 | C7: 2024-01-05 | D7: Restock | E7: 87 | F7: =INDEX(Products!$B$2:$B$101,MATCH(B7,Products!$A$2:$A$101,0)) -> Tennis Racket | G7: =INDEX(Products!$J$2:$J$101,MATCH(B7,Products!$A$2:$A$101,0)) -> Sporting Goods | H7: =INDEX(Products!$D$2:$D$101,MATCH(B7,Products!$A$2:$A$101,0)) -> 11
A8: 7 | B8: 4 | C8: 2024-08-17 | D8: Sale | E8: -40 | F8: =INDEX(Products!$B$2:$B$101,MATCH(B8,Products!$A$2:$A$101,0)) -> 4K Monitor | G8: =INDEX(Products!$J$2:$J$101,MATCH(B8,Products!$A$2:$A$101,0)) -> Electronics | H8: =INDEX(Products!$D$2:$D$101,MATCH(B8,Products!$A$2:$A$101,0)) -> 11
A9: 8 | B9: 58 | C9: 2024-05-23 | D9: Restock | E9: 225 | F9: =INDEX(Products!$B$2:$B$101,MATCH(B9,Products!$A$2:$A$101,0)) -> Water Bottle | G9: =INDEX(Products!$J$2:$J$101,MATCH(B9,Products!$A$2:$A$101,0)) -> Sporting Goods | H9: =INDEX(Products!$D$2:$D$101,MATCH(B9,Products!$A$2:$A$101,0)) -> 7
A10: 9 | B10: 83 | C10: 2025-07-27 | D10: Restock | E10: 170 | F10: =INDEX(Products!$B$2:$B$101,MATCH(B10,Products!$A$2:$A$101,0)) -> Air Filter | G10: =INDEX(Products!$J$2:$J$101,MATCH(B10,Products!$A$2:$A$101,0)) -> Automotive Parts | H10: =INDEX(Products!$D$2:$D$101,MATCH(B10,Products!$A$2:$A$101,0)) -> 1
A11: 10 | B11: 18 | C11: 2024-10-24 | D11: Damaged | E11: -14 | F11: =INDEX(Products!$B$2:$B$101,MATCH(B11,Products!$A$2:$A$101,0)) -> Filing Cabinet | G11: =INDEX(Products!$J$2:$J$101,MATCH(B11,Products!$A$2:$A$101,0)) -> Office Supplies | H11: =INDEX(Products!$D$2:$D$101,MATCH(B11,Products!$A$2:$A$101,0)) -> 9
A12: 11 | B12: 92 | C12: 2025-02-24 | D12: Adjustment | E12: -39 | F12: =INDEX(Products!$B$2:$B$101,MATCH(B12,Products!$A$2:$A$101,0)) -> Olive Oil 1L | G12: =INDEX(Products!$J$2:$J$101,MATCH(B12,Products!$A$2:$A$101,0)) -> Groceries | H12: =INDEX(Products!$D$2:$D$101,MATCH(B12,Products!$A$2:$A$101,0)) -> 10
A13: 12 | B13: 33 | C13: 2023-05-30 | D13: Restock | E13: 65 | F13: =INDEX(Products!$B$2:$B$101,MATCH(B13,Products!$A$2:$A$101,0)) -> Running Shoes | G13: =INDEX(Products!$J$2:$J$101,MATCH(B13,Products!$A$2:$A$101,0)) -> Apparel | H13: =INDEX(Products!$D$2:$D$101,MATCH(B13,Products!$A$2:$A$101,0)) -> 5
... A351: 350 | B351: 46 | C351: 2023-12-31 | D351: Restock | E351: 58 | F351: =INDEX(Products!$B$2:$B$101,MATCH(B351,Products!$A$2:$A$101,0)) -> Cutlery Set | G351: =INDEX(Products!$J$2:$J$101,MATCH(B351,Products!$A$2:$A$101,0)) -> Home & Kitchen | H351: =INDEX(Products!$D$2:$D$101,MATCH(B351,Products!$A$2:$A$101,0)) -> 1
